Workbook

Sheet Dashboard
B6: Swapnil Wale | E6: Project BRMS Tech | S6: =TODAY() -> 44835
B21: Open Risks (Rating) | H21: Open Issues (Severity) | N21: Open Action Items | Q21: Open Change Requests | T21: Pending Decisions
N22: =Data!H16 -> 4 | Q22: =Data!K17 -> 2 | T22: =Data!N17 -> 1

Sheet Schedule
B6: BRMS Implementation | D6: View Start | G6: 42495 | H6: Timeline | K6: days | L6: 1 | M6: =G6 -> 42495 | N6: =M6+$L$6 -> 42496 | O6: =N6+$L$6 -> 42497 | P6: =O6+$L$6 -> 42498 | Q6: =P6+$L$6 -> 42499 | R6: =Q6+$L$6 -> 42500 | S6: =R6+$L$6 -> 42501 | T6: =S6+$L$6 -> 42502 | U6: =T6+$L$6 -> 42503 | ... JK6: =JJ6+$L$6 -> 42753
B7: # | C7: Task Name | D7: Resource | E7: Pre | F7: Start | G7: Finish | H7: Effort (days) | I7: % | J7: % | K7: % | L7: Status
G8: Auto | I8: Act | J8: Plan | K8: Plan | M8: =LEFT(TEXT(M6,"ddd")) -> T | N8: =LEFT(TEXT(N6,"ddd")) -> F | O8: =LEFT(TEXT(O6,"ddd")) -> S | P8: =LEFT(TEXT(P6,"ddd")) -> S | Q8: =LEFT(TEXT(Q6,"ddd")) -> M | R8: =LEFT(TEXT(R6,"ddd")) -> T | S8: =LEFT(TEXT(S6,"ddd")) -> W | T8: =LEFT(TEXT(T6,"ddd")) -> T | ... JK8: =LEFT(TEXT(JK6,"ddd")) -> W
B9: 1 | C9: Requirement Gathering | D9: John | F9: 42495 | G9: =WORKDAY(F9,H9-1,Config!D7:D26) -> 42529 | H9: 25 | I9: 0.94 | J9: =IF(((NETWORKDAYS(F9,TODAY(),Data!C2:C21)*100)/H9)/100 > 0,((NETWORKDAYS(F9,TODAY(),Data!C2:C21)*100)/H9)/100,0) -> 66.88 | K9: =IF(J9>1, "100%",$J9) -> 100% | L9: =K9-I9 -> 0.06 | M9: =IF(AND(M$6>=$F9,M$6<=$G9),"."," ") -> . | N9: =IF(AND(N$6>=$F9,N$6<=$G9),"."," ") -> . | O9: =IF(AND(O$6>=$F9,O$6<=$G9),"."," ") -> . | P9: =IF(AND(P$6>=$F9,P$6<=$G9),"."," ") -> . | Q9: =IF(AND(Q$6>=$F9,Q$6<=$G9),"."," ") -> . | T9: =IF(AND(T$6>=$F9,T$6<=$G9),"."," ") -> . | U9: =IF(AND(U$6>=$F9,U$6<=$G9),"."," ") -> . | V9: =IF(AND(V$6>=$F9,V$6<=$G9),"."," ") -> . | W9: =IF(AND(W$6>=$F9,W$6<=$G9),"."," ") -> . | X9: =IF(AND(X$6>=$F9,X$6<=$G9),"."," ") -> . | AA9: =IF(AND(AA$6>=$F9,AA$6<=$G9),"."," ") -> . | AB9: =IF(AND(AB$6>=$F9,AB$6<=$G9),"."," ") -> . | AC9: =IF(AND(AC$6>=$F9,AC$6<=$G9),"."," ") -> . | AD9: =IF(AND(AD$6>=$F9,AD$6<=$G9),"."," ") -> . | AE9: =IF(AND(AE$6>=$F9,AE$6<=$G9),"."," ") -> . | AH9: =IF(AND(AH$6>=$F9,AH$6<=$G9),"."," ") -> . | AI9: =IF(AND(AI$6>=$F9,AI$6<=$G9),"."," ") -> . | AJ9: =IF(AND(AJ$6>=$F9,AJ$6<=$G9),"."," ") -> . | AK9: =IF(AND(AK$6>=$F9,AK$6<=$G9),"."," ") -> . | AL9: =IF(AND(AL$6>=$F9,AL$6<=$G9),"."," ") -> . | AO9: =IF(AND(AO$6>=$F9,AO$6<=$G9),"."," ") -> . | AP9: =IF(AND(AP$6>=$F9,AP$6<=$G9),"."," ") -> . | AQ9: =IF(AND(AQ$6>=$F9,AQ$6<=$G9),"."," ") -> . | AR9: =IF(AND(AR$6>=$F9,AR$6<=$G9),"."," ") -> . | AS9: =IF(AND(AS$6>=$F9,AS$6<=$G9),"."," ") -> . | AV9: =IF(AND(AV$6>=$F9,AV$6<=$G9),"."," ") | AW9: =IF(AND(AW$6>=$F9,AW$6<=$G9),"."," ") | AX9: =IF(AND(AX$6>=$F9,AX$6<=$G9),"."," ") | AY9: =IF(AND(AY$6>=$F9,AY$6<=$G9),"."," ") | AZ9: =IF(AND(AZ$6>=$F9,AZ$6<=$G9),"."," ") | BC9: =IF(AND(BC$6>=$F9,BC$6<=$G9),"."," ") | BD9: =IF(AND(BD$6>=$F9,BD$6<=$G9),"."," ") | BE9: =IF(AND(BE$6>=$F9,BE$6<=$G9),"."," ") | BF9: =IF(AND(BF$6>=$F9,BF$6<=$G9),"."," ") | BG9: =IF(AND(BG$6>=$F9,BG$6<=$G9),"."," ") | BJ9: =IF(AND(BJ$6>=$F9,BJ$6<=$G9),"."," ") | BK9: =IF(AND(BK$6>=$F9,BK$6<=$G9),"."," ") | BL9: =IF(AND(BL$6>=$F9,BL$6<=$G9),"."," ") | BM9: =IF(AND(BM$6>=$F9,BM$6<=$G9),"."," ") | BN9: =IF(AND(BN$6>=$F9,BN$6<=$G9),"."," ") | BQ9: =IF(AND(BQ$6>=$F9,BQ$6<=$G9),"."," ") | BR9: =IF(AND(BR$6>=$F9,BR$6<=$G9),"."," ") | BS9: =IF(AND(BS$6>=$F9,BS$6<=$G9),"."," ") | BT9: =IF(AND(BT$6>=$F9,BT$6<=$G9),"."," ") | BU9: =IF(AND(BU$6>=$F9,BU$6<=$G9),"."," ") | BX9: =IF(AND(BX$6>=$F9,BX$6<=$G9),"."," ") | BY9: =IF(AND(BY$6>=$F9,BY$6<=$G9),"."," ") | BZ9: =IF(AND(BZ$6>=$F9,BZ$6<=$G9),"."," ") | CA9: =IF(AND(CA$6>=$F9,CA$6<=$G9),"."," ") | CB9: =IF(AND(CB$6>=$F9,CB$6<=$G9),"."," ") | CE9: =IF(AND(CE$6>=$F9,CE$6<=$G9),"."," ") | CF9: =IF(AND(CF$6>=$F9,CF$6<=$G9),"."," ") | CG9: =IF(AND(CG$6>=$F9,CG$6<=$G9),"."," ") | CH9: =IF(AND(CH$6>=$F9,CH$6<=$G9),"."," ") | CI9: =IF(AND(CI$6>=$F9,CI$6<=$G9),"."," ") | CL9: =IF(AND(CL$6>=$F9,CL$6<=$G9),"."," ") | CM9: =IF(AND(CM$6>=$F9,CM$6<=$G9),"."," ") | CN9: =IF(AND(CN$6>=$F9,CN$6<=$G9),"."," ") | CO9: =IF(AND(CO$6>=$F9,CO$6<=$G9),"."," ") | CP9: =IF(AND(CP$6>=$F9,CP$6<=$G9),"."," ") | CS9: =IF(AND(CS$6>=$F9,CS$6<=$G9),"."," ") | CT9: =IF(AND(CT$6>=$F9,CT$6<=$G9),"."," ") | CU9: =IF(AND(CU$6>=$F9,CU$6<=$G9),"."," ") | CV9: =IF(AND(CV$6>=$F9,CV$6<=$G9),"."," ") | CW9: =IF(AND(CW$6>=$F9,CW$6<=$G9),"."," ") | CZ9: =IF(AND(CZ$6>=$F9,CZ$6<=$G9),"."," ") | DA9: =IF(AND(DA$6>=$F9,DA$6<=$G9),"."," ") | DB9: =IF(AND(DB$6>=$F9,DB$6<=$G9),"."," ") | DC9: =IF(AND(DC$6>=$F9,DC$6<=$G9),"."," ") | DD9: =IF(AND(DD$6>=$F9,DD$6<=$G9),"."," ") | DG9: =IF(AND(DG$6>=$F9,DG$6<=$G9),"."," ") | DH9: =IF(AND(DH$6>=$F9,DH$6<=$G9),"."," ") | DI9: =IF(AND(DI$6>=$F9,DI$6<=$G9),"."," ") | DJ9: =IF(AND(DJ$6>=$F9,DJ$6<=$G9),"."," ") | DK9: =IF(AND(DK$6>=$F9,DK$6<=$G9),"."," ") | DN9: =IF(AND(DN$6>=$F9,DN$6<=$G9),"."," ") | DO9: =IF(AND(DO$6>=$F9,DO$6<=$G9),"."," ") | DP9: =IF(AND(DP$6>=$F9,DP$6<=$G9),"."," ") | DQ9: =IF(AND(DQ$6>=$F9,DQ$6<=$G9),"."," ") | DR9: =IF(AND(DR$6>=$F9,DR$6<=$G9),"."," ") | DU9: =IF(AND(DU$6>=$F9,DU$6<=$G9),"."," ") | DV9: =IF(AND(DV$6>=$F9,DV$6<=$G9),"."," ") | DW9: =IF(AND(DW$6>=$F9,DW$6<=$G9),"."," ") | DX9: =IF(AND(DX$6>=$F9,DX$6<=$G9),"."," ") | DY9: =IF(AND(DY$6>=$F9,DY$6<=$G9),"."," ") | EB9: =IF(AND(EB$6>=$F9,EB$6<=$G9),"."," ") | EC9: =IF(AND(EC$6>=$F9,EC$6<=$G9),"."," ") | ED9: =IF(AND(ED$6>=$F9,ED$6<=$G9),"."," ") | EE9: =IF(AND(EE$6>=$F9,EE$6<=$G9),"."," ") | EF9: =IF(AND(EF$6>=$F9,EF$6<=$G9),"."," ") | EI9: =IF(AND(EI$6>=$F9,EI$6<=$G9),"."," ") | EJ9: =IF(AND(EJ$6>=$F9,EJ$6<=$G9),"."," ") | EK9: =IF(AND(EK$6>=$F9,EK$6<=$G9),"."," ") | EL9: =IF(AND(EL$6>=$F9,EL$6<=$G9),"."," ") | EM9: =IF(AND(EM$6>=$F9,EM$6<=$G9),"."," ") | EP9: =IF(AND(EP$6>=$F9,EP$6<=$G9),"."," ") | EQ9: =IF(AND(EQ$6>=$F9,EQ$6<=$G9),"."," ") | ER9: =IF(AND(ER$6>=$F9,ER$6<=$G9),"."," ") | ES9: =IF(AND(ES$6>=$F9,ES$6<=$G9),"."," ") | ET9: =IF(AND(ET$6>=$F9,ET$6<=$G9),"."," ") | EW9: =IF(AND(EW$6>=$F9,EW$6<=$G9),"."," ") | EX9: =IF(AND(EX$6>=$F9,EX$6<=$G9),"."," ") | EY9: =IF(AND(EY$6>=$F9,EY$6<=$G9),"."," ") | EZ9: =IF(AND(EZ$6>=$F9,EZ$6<=$G9),"."," ") | FA9: =IF(AND(FA$6>=$F9,FA$6<=$G9),"."," ") | FD9: =IF(AND(FD$6>=$F9,FD$6<=$G9),"."," ") | FE9: =IF(AND(FE$6>=$F9,FE$6<=$G9),"."," ") | FF9: =IF(AND(FF$6>=$F9,FF$6<=$G9),"."," ") | FG9: =IF(AND(FG$6>=$F9,FG$6<=$G9),"."," ") | FH9: =IF(AND(FH$6>=$F9,FH$6<=$G9),"."," ") | FK9: =IF(AND(FK$6>=$F9,FK$6<=$G9),"."," ") | FL9: =IF(AND(FL$6>=$F9,FL$6<=$G9),"."," ") | FM9: =IF(AND(FM$6>=$F9,FM$6<=$G9),"."," ") | FN9: =IF(AND(FN$6>=$F9,FN$6<=$G9),"."," ") | FO9: =IF(AND(FO$6>=$F9,FO$6<=$G9),"."," ") | FR9: =IF(AND(FR$6>=$F9,FR$6<=$G9),"."," ") | FS9: =IF(AND(FS$6>=$F9,FS$6<=$G9),"."," ") | FT9: =IF(AND(FT$6>=$F9,FT$6<=$G9),"."," ") | FU9: =IF(AND(FU$6>=$F9,FU$6<=$G9),"."," ") | FV9: =IF(AND(FV$6>=$F9,FV$6<=$G9),"."," ") | FY9: =IF(AND(FY$6>=$F9,FY$6<=$G9),"."," ") | FZ9: =IF(AND(FZ$6>=$F9,FZ$6<=$G9),"."," ") | GA9: =IF(AND(GA$6>=$F9,GA$6<=$G9),"."," ") | GB9: =IF(AND(GB$6>=$F9,GB$6<=$G9),"."," ") | GC9: =IF(AND(GC$6>=$F9,GC$6<=$G9),"."," ") | GF9: =IF(AND(GF$6>=$F9,GF$6<=$G9),"."," ") | GG9: =IF(AND(GG$6>=$F9,GG$6<=$G9),"."," ") | GH9: =IF(AND(GH$6>=$F9,GH$6<=$G9),"."," ") | GI9: =IF(AND(GI$6>=$F9,GI$6<=$G9),"."," ") | GJ9: =IF(AND(GJ$6>=$F9,GJ$6<=$G9),"."," ") | GM9: =IF(AND(GM$6>=$F9,GM$6<=$G9),"."," ") | GN9: =IF(AND(GN$6>=$F9,GN$6<=$G9),"."," ") | GO9: =IF(AND(GO$6>=$F9,GO$6<=$G9),"."," ") | GP9: =IF(AND(GP$6>=$F9,GP$6<=$G9),"."," ") | GQ9: =IF(AND(GQ$6>=$F9,GQ$6<=$G9),"."," ") | GT9: =IF(AND(GT$6>=$F9,GT$6<=$G9),"."," ") | GU9: =IF(AND(GU$6>=$F9,GU$6<=$G9),"."," ") | GV9: =IF(AND(GV$6>=$F9,GV$6<=$G9),"."," ") | GW9: =IF(AND(GW$6>=$F9,GW$6<=$G9),"."," ") | GX9: =IF(AND(GX$6>=$F9,GX$6<=$G9),"."," ") | HA9: =IF(AND(HA$6>=$F9,HA$6<=$G9),"."," ") | HB9: =IF(AND(HB$6>=$F9,HB$6<=$G9),"."," ") | HC9: =IF(AND(HC$6>=$F9,HC$6<=$G9),"."," ") | HD9: =IF(AND(HD$6>=$F9,HD$6<=$G9),"."," ") | HE9: =IF(AND(HE$6>=$F9,HE$6<=$G9),"."," ") | HH9: =IF(AND(HH$6>=$F9,HH$6<=$G9),"."," ") | HI9: =IF(AND(HI$6>=$F9,HI$6<=$G9),"."," ") | HJ9: =IF(AND(HJ$6>=$F9,HJ$6<=$G9),"."," ") | HK9: =IF(AND(HK$6>=$F9,HK$6<=$G9),"."," ") | HL9: =IF(AND(HL$6>=$F9,HL$6<=$G9),"."," ") | HO9: =IF(AND(HO$6>=$F9,HO$6<=$G9),"."," ") | HP9: =IF(AND(HP$6>=$F9,HP$6<=$G9),"."," ") | HQ9: =IF(AND(HQ$6>=$F9,HQ$6<=$G9),"."," ") | HR9: =IF(AND(HR$6>=$F9,HR$6<=$G9),"."," ") | HS9: =IF(AND(HS$6>=$F9,HS$6<=$G9),"."," ") | HV9: =IF(AND(HV$6>=$F9,HV$6<=$G9),"."," ") | HW9: =IF(AND(HW$6>=$F9,HW$6<=$G9),"."," ") | HX9: =IF(AND(HX$6>=$F9,HX$6<=$G9),"."," ") | HY9: =IF(AND(HY$6>=$F9,HY$6<=$G9),"."," ") | HZ9: =IF(AND(HZ$6>=$F9,HZ$6<=$G9),"."," ") | IC9: =IF(AND(IC$6>=$F9,IC$6<=$G9),"."," ") | ID9: =IF(AND(ID$6>=$F9,ID$6<=$G9),"."," ") | IE9: =IF(AND(IE$6>=$F9,IE$6<=$G9),"."," ") | IF9: =IF(AND(IF$6>=$F9,IF$6<=$G9),"."," ") | IG9: =IF(AND(IG$6>=$F9,IG$6<=$G9),"."," ") | IJ9: =IF(AND(IJ$6>=$F9,IJ$6<=$G9),"."," ") | IK9: =IF(AND(IK$6>=$F9,IK$6<=$G9),"."," ") | IL9: =IF(AND(IL$6>=$F9,IL$6<=$G9),"."," ") | IM9: =IF(AND(IM$6>=$F9,IM$6<=$G9),"."," ") | IN9: =IF(AND(IN$6>=$F9,IN$6<=$G9),"."," ") | IQ9: =IF(AND(IQ$6>=$F9,IQ$6<=$G9),"."," ") | IR9: =IF(AND(IR$6>=$F9,IR$6<=$G9),"."," ") | IS9: =IF(AND(IS$6>=$F9,IS$6<=$G9),"."," ") | IT9: =IF(AND(IT$6>=$F9,IT$6<=$G9),"."," ") | IU9: =IF(AND(IU$6>=$F9,IU$6<=$G9),"."," ") | IX9: =IF(AND(IX$6>=$F9,IX$6<=$G9),"."," ") | IY9: =IF(AND(IY$6>=$F9,IY$6<=$G9),"."," ") | IZ9: =IF(AND(IZ$6>=$F9,IZ$6<=$G9),"."," ") | JA9: =IF(AND(JA$6>=$F9,JA$6<=$G9),"."," ") | JB9: =IF(AND(JB$6>=$F9,JB$6<=$G9),"."," ") | JE9: =IF(AND(JE$6>=$F9,JE$6<=$G9),"."," ") | JF9: =IF(AND(JF$6>=$F9,JF$6<=$G9),"."," ") | JG9: =IF(AND(JG$6>=$F9,JG$6<=$G9),"."," ") | JH9: =IF(AND(JH$6>=$F9,JH$6<=$G9),"."," ") | JI9: =IF(AND(JI$6>=$F9,JI$6<=$G9),"."," ")
B10: =B9+1 -> 2 | C10: Draft Business Requirements | D10: John | E10: 1 | F10: 42502 | G10: =WORKDAY(F10,H10-1,Config!D8:D27) -> 42506 | H10: 3 | I10: 0.94 | J10: =IF(((NETWORKDAYS(F10,TODAY(),Data!C3:C22)*100)/H10)/100 > 0,((NETWORKDAYS(F10,TODAY(),Data!C3:C22)*100)/H10)/100,0) -> 555.66667 | K10: =IF(J10>1, "100%",$J10) -> 100% | L10: =K10-I10 -> 0.06 | M10: =IF(AND(M$6>=$F10,M$6<=$G10),"."," ") | N10: =IF(AND(N$6>=$F10,N$6<=$G10),"."," ") | O10: =IF(AND(O$6>=$F10,O$6<=$G10),"."," ") | P10: =IF(AND(P$6>=$F10,P$6<=$G10),"."," ") | Q10: =IF(AND(Q$6>=$F10,Q$6<=$G10),"."," ") | T10: =IF(AND(T$6>=$F10,T$6<=$G10),"."," ") -> . | U10: =IF(AND(U$6>=$F10,U$6<=$G10),"."," ") -> . | V10: =IF(AND(V$6>=$F10,V$6<=$G10),"."," ") -> . | W10: =IF(AND(W$6>=$F10,W$6<=$G10),"."," ") -> . | X10: =IF(AND(X$6>=$F10,X$6<=$G10),"."," ") -> . | AA10: =IF(AND(AA$6>=$F10,AA$6<=$G10),"."," ") | AB10: =IF(AND(AB$6>=$F10,AB$6<=$G10),"."," ") | AC10: =IF(AND(AC$6>=$F10,AC$6<=$G10),"."," ") | AD10: =IF(AND(AD$6>=$F10,AD$6<=$G10),"."," ") | AE10: =IF(AND(AE$6>=$F10,AE$6<=$G10),"."," ") | AH10: =IF(AND(AH$6>=$F10,AH$6<=$G10),"."," ") | AI10: =IF(AND(AI$6>=$F10,AI$6<=$G10),"."," ") | AJ10: =IF(AND(AJ$6>=$F10,AJ$6<=$G10),"."," ") | AK10: =IF(AND(AK$6>=$F10,AK$6<=$G10),"."," ") | AL10: =IF(AND(AL$6>=$F10,AL$6<=$G10),"."," ") | AO10: =IF(AND(AO$6>=$F10,AO$6<=$G10),"."," ") | AP10: =IF(AND(AP$6>=$F10,AP$6<=$G10),"."," ") | AQ10: =IF(AND(AQ$6>=$F10,AQ$6<=$G10),"."," ") | AR10: =IF(AND(AR$6>=$F10,AR$6<=$G10),"."," ") | AS10: =IF(AND(AS$6>=$F10,AS$6<=$G10),"."," ") | AV10: =IF(AND(AV$6>=$F10,AV$6<=$G10),"."," ") | AW10: =IF(AND(AW$6>=$F10,AW$6<=$G10),"."," ") | AX10: =IF(AND(AX$6>=$F10,AX$6<=$G10),"."," ") | AY10: =IF(AND(AY$6>=$F10,AY$6<=$G10),"."," ") | AZ10: =IF(AND(AZ$6>=$F10,AZ$6<=$G10),"."," ") | BC10: =IF(AND(BC$6>=$F10,BC$6<=$G10),"."," ") | BD10: =IF(AND(BD$6>=$F10,BD$6<=$G10),"."," ") | BE10: =IF(AND(BE$6>=$F10,BE$6<=$G10),"."," ") | BF10: =IF(AND(BF$6>=$F10,BF$6<=$G10),"."," ") | BG10: =IF(AND(BG$6>=$F10,BG$6<=$G10),"."," ") | BJ10: =IF(AND(BJ$6>=$F10,BJ$6<=$G10),"."," ") | BK10: =IF(AND(BK$6>=$F10,BK$6<=$G10),"."," ") | BL10: =IF(AND(BL$6>=$F10,BL$6<=$G10),"."," ") | BM10: =IF(AND(BM$6>=$F10,BM$6<=$G10),"."," ") | BN10: =IF(AND(BN$6>=$F10,BN$6<=$G10),"."," ") | BQ10: =IF(AND(BQ$6>=$F10,BQ$6<=$G10),"."," ") | BR10: =IF(AND(BR$6>=$F10,BR$6<=$G10),"."," ") | BS10: =IF(AND(BS$6>=$F10,BS$6<=$G10),"."," ") | BT10: =IF(AND(BT$6>=$F10,BT$6<=$G10),"."," ") | BU10: =IF(AND(BU$6>=$F10,BU$6<=$G10),"."," ") | BX10: =IF(AND(BX$6>=$F10,BX$6<=$G10),"."," ") | BY10: =IF(AND(BY$6>=$F10,BY$6<=$G10),"."," ") | BZ10: =IF(AND(BZ$6>=$F10,BZ$6<=$G10),"."," ") | CA10: =IF(AND(CA$6>=$F10,CA$6<=$G10),"."," ") | CB10: =IF(AND(CB$6>=$F10,CB$6<=$G10),"."," ") | CE10: =IF(AND(CE$6>=$F10,CE$6<=$G10),"."," ") | CF10: =IF(AND(CF$6>=$F10,CF$6<=$G10),"."," ") | CG10: =IF(AND(CG$6>=$F10,CG$6<=$G10),"."," ") | CH10: =IF(AND(CH$6>=$F10,CH$6<=$G10),"."," ") | CI10: =IF(AND(CI$6>=$F10,CI$6<=$G10),"."," ") | CL10: =IF(AND(CL$6>=$F10,CL$6<=$G10),"."," ") | CM10: =IF(AND(CM$6>=$F10,CM$6<=$G10),"."," ") | CN10: =IF(AND(CN$6>=$F10,CN$6<=$G10),"."," ") | CO10: =IF(AND(CO$6>=$F10,CO$6<=$G10),"."," ") | CP10: =IF(AND(CP$6>=$F10,CP$6<=$G10),"."," ") | CS10: =IF(AND(CS$6>=$F10,CS$6<=$G10),"."," ") | CT10: =IF(AND(CT$6>=$F10,CT$6<=$G10),"."," ") | CU10: =IF(AND(CU$6>=$F10,CU$6<=$G10),"."," ") | CV10: =IF(AND(CV$6>=$F10,CV$6<=$G10),"."," ") | CW10: =IF(AND(CW$6>=$F10,CW$6<=$G10),"."," ") | CZ10: =IF(AND(CZ$6>=$F10,CZ$6<=$G10),"."," ") | DA10: =IF(AND(DA$6>=$F10,DA$6<=$G10),"."," ") | DB10: =IF(AND(DB$6>=$F10,DB$6<=$G10),"."," ") | DC10: =IF(AND(DC$6>=$F10,DC$6<=$G10),"."," ") | DD10: =IF(AND(DD$6>=$F10,DD$6<=$G10),"."," ") | DG10: =IF(AND(DG$6>=$F10,DG$6<=$G10),"."," ") | DH10: =IF(AND(DH$6>=$F10,DH$6<=$G10),"."," ") | DI10: =IF(AND(DI$6>=$F10,DI$6<=$G10),"."," ") | DJ10: =IF(AND(DJ$6>=$F10,DJ$6<=$G10),"."," ") | DK10: =IF(AND(DK$6>=$F10,DK$6<=$G10),"."," ") | DN10: =IF(AND(DN$6>=$F10,DN$6<=$G10),"."," ") | DO10: =IF(AND(DO$6>=$F10,DO$6<=$G10),"."," ") | DP10: =IF(AND(DP$6>=$F10,DP$6<=$G10),"."," ") | DQ10: =IF(AND(DQ$6>=$F10,DQ$6<=$G10),"."," ") | DR10: =IF(AND(DR$6>=$F10,DR$6<=$G10),"."," ") | DU10: =IF(AND(DU$6>=$F10,DU$6<=$G10),"."," ") | DV10: =IF(AND(DV$6>=$F10,DV$6<=$G10),"."," ") | DW10: =IF(AND(DW$6>=$F10,DW$6<=$G10),"."," ") | DX10: =IF(AND(DX$6>=$F10,DX$6<=$G10),"."," ") | DY10: =IF(AND(DY$6>=$F10,DY$6<=$G10),"."," ") | EB10: =IF(AND(EB$6>=$F10,EB$6<=$G10),"."," ") | EC10: =IF(AND(EC$6>=$F10,EC$6<=$G10),"."," ") | ED10: =IF(AND(ED$6>=$F10,ED$6<=$G10),"."," ") | EE10: =IF(AND(EE$6>=$F10,EE$6<=$G10),"."," ") | EF10: =IF(AND(EF$6>=$F10,EF$6<=$G10),"."," ") | EI10: =IF(AND(EI$6>=$F10,EI$6<=$G10),"."," ") | EJ10: =IF(AND(EJ$6>=$F10,EJ$6<=$G10),"."," ") | EK10: =IF(AND(EK$6>=$F10,EK$6<=$G10),"."," ") | EL10: =IF(AND(EL$6>=$F10,EL$6<=$G10),"."," ") | EM10: =IF(AND(EM$6>=$F10,EM$6<=$G10),"."," ") | EP10: =IF(AND(EP$6>=$F10,EP$6<=$G10),"."," ") | EQ10: =IF(AND(EQ$6>=$F10,EQ$6<=$G10),"."," ") | ER10: =IF(AND(ER$6>=$F10,ER$6<=$G10),"."," ") | ES10: =IF(AND(ES$6>=$F10,ES$6<=$G10),"."," ") | ET10: =IF(AND(ET$6>=$F10,ET$6<=$G10),"."," ") | EW10: =IF(AND(EW$6>=$F10,EW$6<=$G10),"."," ") | EX10: =IF(AND(EX$6>=$F10,EX$6<=$G10),"."," ") | EY10: =IF(AND(EY$6>=$F10,EY$6<=$G10),"."," ") | EZ10: =IF(AND(EZ$6>=$F10,EZ$6<=$G10),"."," ") | FA10: =IF(AND(FA$6>=$F10,FA$6<=$G10),"."," ") | FD10: =IF(AND(FD$6>=$F10,FD$6<=$G10),"."," ") | FE10: =IF(AND(FE$6>=$F10,FE$6<=$G10),"."," ") | FF10: =IF(AND(FF$6>=$F10,FF$6<=$G10),"."," ") | FG10: =IF(AND(FG$6>=$F10,FG$6<=$G10),"."," ") | FH10: =IF(AND(FH$6>=$F10,FH$6<=$G10),"."," ") | FK10: =IF(AND(FK$6>=$F10,FK$6<=$G10),"."," ") | FL10: =IF(AND(FL$6>=$F10,FL$6<=$G10),"."," ") | FM10: =IF(AND(FM$6>=$F10,FM$6<=$G10),"."," ") | FN10: =IF(AND(FN$6>=$F10,FN$6<=$G10),"."," ") | FO10: =IF(AND(FO$6>=$F10,FO$6<=$G10),"."," ") | FR10: =IF(AND(FR$6>=$F10,FR$6<=$G10),"."," ") | FS10: =IF(AND(FS$6>=$F10,FS$6<=$G10),"."," ") | FT10: =IF(AND(FT$6>=$F10,FT$6<=$G10),"."," ") | FU10: =IF(AND(FU$6>=$F10,FU$6<=$G10),"."," ") | FV10: =IF(AND(FV$6>=$F10,FV$6<=$G10),"."," ") | FY10: =IF(AND(FY$6>=$F10,FY$6<=$G10),"."," ") | FZ10: =IF(AND(FZ$6>=$F10,FZ$6<=$G10),"."," ") | GA10: =IF(AND(GA$6>=$F10,GA$6<=$G10),"."," ") | GB10: =IF(AND(GB$6>=$F10,GB$6<=$G10),"."," ") | GC10: =IF(AND(GC$6>=$F10,GC$6<=$G10),"."," ") | GF10: =IF(AND(GF$6>=$F10,GF$6<=$G10),"."," ") | GG10: =IF(AND(GG$6>=$F10,GG$6<=$G10),"."," ") | GH10: =IF(AND(GH$6>=$F10,GH$6<=$G10),"."," ") | GI10: =IF(AND(GI$6>=$F10,GI$6<=$G10),"."," ") | GJ10: =IF(AND(GJ$6>=$F10,GJ$6<=$G10),"."," ") | GM10: =IF(AND(GM$6>=$F10,GM$6<=$G10),"."," ") | GN10: =IF(AND(GN$6>=$F10,GN$6<=$G10),"."," ") | GO10: =IF(AND(GO$6>=$F10,GO$6<=$G10),"."," ") | GP10: =IF(AND(GP$6>=$F10,GP$6<=$G10),"."," ") | GQ10: =IF(AND(GQ$6>=$F10,GQ$6<=$G10),"."," ") | GT10: =IF(AND(GT$6>=$F10,GT$6<=$G10),"."," ") | GU10: =IF(AND(GU$6>=$F10,GU$6<=$G10),"."," ") | GV10: =IF(AND(GV$6>=$F10,GV$6<=$G10),"."," ") | GW10: =IF(AND(GW$6>=$F10,GW$6<=$G10),"."," ") | GX10: =IF(AND(GX$6>=$F10,GX$6<=$G10),"."," ") | HA10: =IF(AND(HA$6>=$F10,HA$6<=$G10),"."," ") | HB10: =IF(AND(HB$6>=$F10,HB$6<=$G10),"."," ") | HC10: =IF(AND(HC$6>=$F10,HC$6<=$G10),"."," ") | HD10: =IF(AND(HD$6>=$F10,HD$6<=$G10),"."," ") | HE10: =IF(AND(HE$6>=$F10,HE$6<=$G10),"."," ") | HH10: =IF(AND(HH$6>=$F10,HH$6<=$G10),"."," ") | HI10: =IF(AND(HI$6>=$F10,HI$6<=$G10),"."," ") | HJ10: =IF(AND(HJ$6>=$F10,HJ$6<=$G10),"."," ") | HK10: =IF(AND(HK$6>=$F10,HK$6<=$G10),"."," ") | HL10: =IF(AND(HL$6>=$F10,HL$6<=$G10),"."," ") | HO10: =IF(AND(HO$6>=$F10,HO$6<=$G10),"."," ") | HP10: =IF(AND(HP$6>=$F10,HP$6<=$G10),"."," ") | HQ10: =IF(AND(HQ$6>=$F10,HQ$6<=$G10),"."," ") | HR10: =IF(AND(HR$6>=$F10,HR$6<=$G10),"."," ") | HS10: =IF(AND(HS$6>=$F10,HS$6<=$G10),"."," ") | HV10: =IF(AND(HV$6>=$F10,HV$6<=$G10),"."," ") | HW10: =IF(AND(HW$6>=$F10,HW$6<=$G10),"."," ") | HX10: =IF(AND(HX$6>=$F10,HX$6<=$G10),"."," ") | HY10: =IF(AND(HY$6>=$F10,HY$6<=$G10),"."," ") | HZ10: =IF(AND(HZ$6>=$F10,HZ$6<=$G10),"."," ") | IC10: =IF(AND(IC$6>=$F10,IC$6<=$G10),"."," ") | ID10: =IF(AND(ID$6>=$F10,ID$6<=$G10),"."," ") | IE10: =IF(AND(IE$6>=$F10,IE$6<=$G10),"."," ") | IF10: =IF(AND(IF$6>=$F10,IF$6<=$G10),"."," ") | IG10: =IF(AND(IG$6>=$F10,IG$6<=$G10),"."," ") | IJ10: =IF(AND(IJ$6>=$F10,IJ$6<=$G10),"."," ") | IK10: =IF(AND(IK$6>=$F10,IK$6<=$G10),"."," ") | IL10: =IF(AND(IL$6>=$F10,IL$6<=$G10),"."," ") | IM10: =IF(AND(IM$6>=$F10,IM$6<=$G10),"."," ") | IN10: =IF(AND(IN$6>=$F10,IN$6<=$G10),"."," ") | IQ10: =IF(AND(IQ$6>=$F10,IQ$6<=$G10),"."," ") | IR10: =IF(AND(IR$6>=$F10,IR$6<=$G10),"."," ") | IS10: =IF(AND(IS$6>=$F10,IS$6<=$G10),"."," ") | IT10: =IF(AND(IT$6>=$F10,IT$6<=$G10),"."," ") | IU10: =IF(AND(IU$6>=$F10,IU$6<=$G10),"."," ") | IX10: =IF(AND(IX$6>=$F10,IX$6<=$G10),"."," ") | IY10: =IF(AND(IY$6>=$F10,IY$6<=$G10),"."," ") | IZ10: =IF(AND(IZ$6>=$F10,IZ$6<=$G10),"."," ") | JA10: =IF(AND(JA$6>=$F10,JA$6<=$G10),"."," ") | JB10: =IF(AND(JB$6>=$F10,JB$6<=$G10),"."," ") | JE10: =IF(AND(JE$6>=$F10,JE$6<=$G10),"."," ") | JF10: =IF(AND(JF$6>=$F10,JF$6<=$G10),"."," ") | JG10: =IF(AND(JG$6>=$F10,JG$6<=$G10),"."," ") | JH10: =IF(AND(JH$6>=$F10,JH$6<=$G10),"."," ") | JI10: =IF(AND(JI$6>=$F10,JI$6<=$G10),"."," ")
B11: =B10+1 -> 3 | C11: Sign Off Business Requirements | D11: John | E11: 2 | F11: =VLOOKUP(E11,$B$6:$G$150,6,FALSE) + 1 -> 42507 | G11: =WORKDAY(F11,H11-1,Config!D9:D28) -> 42507 | H11: 1 | I11: 1 | J11: =IF(((NETWORKDAYS(F11,TODAY(),Data!C4:C23)*100)/H11)/100 > 0,((NETWORKDAYS(F11,TODAY(),Data!C4:C23)*100)/H11)/100,0) -> 1664 | K11: =IF(J11>1, "100%",$J11) -> 100% | L11: =K11-I11 -> 0 | M11: =IF(AND(M$6>=$F11,M$6<=$G11),"."," ") | N11: =IF(AND(N$6>=$F11,N$6<=$G11),"."," ") | O11: =IF(AND(O$6>=$F11,O$6<=$G11),"."," ") | P11: =IF(AND(P$6>=$F11,P$6<=$G11),"."," ") | Q11: =IF(AND(Q$6>=$F11,Q$6<=$G11),"."," ") | T11: =IF(AND(T$6>=$F11,T$6<=$G11),"."," ") | U11: =IF(AND(U$6>=$F11,U$6<=$G11),"."," ") | V11: =IF(AND(V$6>=$F11,V$6<=$G11),"."," ") | W11: =IF(AND(W$6>=$F11,W$6<=$G11),"."," ") | X11: =IF(AND(X$6>=$F11,X$6<=$G11),"."," ") | AA11: =IF(AND(AA$6>=$F11,AA$6<=$G11),"."," ") | AB11: =IF(AND(AB$6>=$F11,AB$6<=$G11),"."," ") | AC11: =IF(AND(AC$6>=$F11,AC$6<=$G11),"."," ") | AD11: =IF(AND(AD$6>=$F11,AD$6<=$G11),"."," ") | AE11: =IF(AND(AE$6>=$F11,AE$6<=$G11),"."," ") | AH11: =IF(AND(AH$6>=$F11,AH$6<=$G11),"."," ") | AI11: =IF(AND(AI$6>=$F11,AI$6<=$G11),"."," ") | AJ11: =IF(AND(AJ$6>=$F11,AJ$6<=$G11),"."," ") | AK11: =IF(AND(AK$6>=$F11,AK$6<=$G11),"."," ") | AL11: =IF(AND(AL$6>=$F11,AL$6<=$G11),"."," ") | AO11: =IF(AND(AO$6>=$F11,AO$6<=$G11),"."," ") | AP11: =IF(AND(AP$6>=$F11,AP$6<=$G11),"."," ") | AQ11: =IF(AND(AQ$6>=$F11,AQ$6<=$G11),"."," ") | AR11: =IF(AND(AR$6>=$F11,AR$6<=$G11),"."," ") | AS11: =IF(AND(AS$6>=$F11,AS$6<=$G11),"."," ") | AV11: =IF(AND(AV$6>=$F11,AV$6<=$G11),"."," ") | AW11: =IF(AND(AW$6>=$F11,AW$6<=$G11),"."," ") | AX11: =IF(AND(AX$6>=$F11,AX$6<=$G11),"."," ") | AY11: =IF(AND(AY$6>=$F11,AY$6<=$G11),"."," ") | AZ11: =IF(AND(AZ$6>=$F11,AZ$6<=$G11),"."," ") | BC11: =IF(AND(BC$6>=$F11,BC$6<=$G11),"."," ") | BD11: =IF(AND(BD$6>=$F11,BD$6<=$G11),"."," ") | BE11: =IF(AND(BE$6>=$F11,BE$6<=$G11),"."," ") | BF11: =IF(AND(BF$6>=$F11,BF$6<=$G11),"."," ") | BG11: =IF(AND(BG$6>=$F11,BG$6<=$G11),"."," ") | BJ11: =IF(AND(BJ$6>=$F11,BJ$6<=$G11),"."," ") | BK11: =IF(AND(BK$6>=$F11,BK$6<=$G11),"."," ") | BL11: =IF(AND(BL$6>=$F11,BL$6<=$G11),"."," ") | BM11: =IF(AND(BM$6>=$F11,BM$6<=$G11),"."," ") | BN11: =IF(AND(BN$6>=$F11,BN$6<=$G11),"."," ") | BQ11: =IF(AND(BQ$6>=$F11,BQ$6<=$G11),"."," ") | BR11: =IF(AND(BR$6>=$F11,BR$6<=$G11),"."," ") | BS11: =IF(AND(BS$6>=$F11,BS$6<=$G11),"."," ") | BT11: =IF(AND(BT$6>=$F11,BT$6<=$G11),"."," ") | BU11: =IF(AND(BU$6>=$F11,BU$6<=$G11),"."," ") | BX11: =IF(AND(BX$6>=$F11,BX$6<=$G11),"."," ") | BY11: =IF(AND(BY$6>=$F11,BY$6<=$G11),"."," ") | BZ11: =IF(AND(BZ$6>=$F11,BZ$6<=$G11),"."," ") | CA11: =IF(AND(CA$6>=$F11,CA$6<=$G11),"."," ") | CB11: =IF(AND(CB$6>=$F11,CB$6<=$G11),"."," ") | CE11: =IF(AND(CE$6>=$F11,CE$6<=$G11),"."," ") | CF11: =IF(AND(CF$6>=$F11,CF$6<=$G11),"."," ") | CG11: =IF(AND(CG$6>=$F11,CG$6<=$G11),"."," ") | CH11: =IF(AND(CH$6>=$F11,CH$6<=$G11),"."," ") | CI11: =IF(AND(CI$6>=$F11,CI$6<=$G11),"."," ") | CL11: =IF(AND(CL$6>=$F11,CL$6<=$G11),"."," ") | CM11: =IF(AND(CM$6>=$F11,CM$6<=$G11),"."," ") | CN11: =IF(AND(CN$6>=$F11,CN$6<=$G11),"."," ") | CO11: =IF(AND(CO$6>=$F11,CO$6<=$G11),"."," ") | CP11: =IF(AND(CP$6>=$F11,CP$6<=$G11),"."," ") | CS11: =IF(AND(CS$6>=$F11,CS$6<=$G11),"."," ") | CT11: =IF(AND(CT$6>=$F11,CT$6<=$G11),"."," ") | CU11: =IF(AND(CU$6>=$F11,CU$6<=$G11),"."," ") | CV11: =IF(AND(CV$6>=$F11,CV$6<=$G11),"."," ") | CW11: =IF(AND(CW$6>=$F11,CW$6<=$G11),"."," ") | CZ11: =IF(AND(CZ$6>=$F11,CZ$6<=$G11),"."," ") | DA11: =IF(AND(DA$6>=$F11,DA$6<=$G11),"."," ") | DB11: =IF(AND(DB$6>=$F11,DB$6<=$G11),"."," ") | DC11: =IF(AND(DC$6>=$F11,DC$6<=$G11),"."," ") | DD11: =IF(AND(DD$6>=$F11,DD$6<=$G11),"."," ") | DG11: =IF(AND(DG$6>=$F11,DG$6<=$G11),"."," ") | DH11: =IF(AND(DH$6>=$F11,DH$6<=$G11),"."," ") | DI11: =IF(AND(DI$6>=$F11,DI$6<=$G11),"."," ") | DJ11: =IF(AND(DJ$6>=$F11,DJ$6<=$G11),"."," ") | DK11: =IF(AND(DK$6>=$F11,DK$6<=$G11),"."," ") | DN11: =IF(AND(DN$6>=$F11,DN$6<=$G11),"."," ") | DO11: =IF(AND(DO$6>=$F11,DO$6<=$G11),"."," ") | DP11: =IF(AND(DP$6>=$F11,DP$6<=$G11),"."," ") | DQ11: =IF(AND(DQ$6>=$F11,DQ$6<=$G11),"."," ") | DR11: =IF(AND(DR$6>=$F11,DR$6<=$G11),"."," ") | DU11: =IF(AND(DU$6>=$F11,DU$6<=$G11),"."," ") | DV11: =IF(AND(DV$6>=$F11,DV$6<=$G11),"."," ") | DW11: =IF(AND(DW$6>=$F11,DW$6<=$G11),"."," ") | DX11: =IF(AND(DX$6>=$F11,DX$6<=$G11),"."," ") | DY11: =IF(AND(DY$6>=$F11,DY$6<=$G11),"."," ") | EB11: =IF(AND(EB$6>=$F11,EB$6<=$G11),"."," ") | EC11: =IF(AND(EC$6>=$F11,EC$6<=$G11),"."," ") | ED11: =IF(AND(ED$6>=$F11,ED$6<=$G11),"."," ") | EE11: =IF(AND(EE$6>=$F11,EE$6<=$G11),"."," ") | EF11: =IF(AND(EF$6>=$F11,EF$6<=$G11),"."," ") | EI11: =IF(AND(EI$6>=$F11,EI$6<=$G11),"."," ") | EJ11: =IF(AND(EJ$6>=$F11,EJ$6<=$G11),"."," ") | EK11: =IF(AND(EK$6>=$F11,EK$6<=$G11),"."," ") | EL11: =IF(AND(EL$6>=$F11,EL$6<=$G11),"."," ") | EM11: =IF(AND(EM$6>=$F11,EM$6<=$G11),"."," ") | EP11: =IF(AND(EP$6>=$F11,EP$6<=$G11),"."," ") | EQ11: =IF(AND(EQ$6>=$F11,EQ$6<=$G11),"."," ") | ER11: =IF(AND(ER$6>=$F11,ER$6<=$G11),"."," ") | ES11: =IF(AND(ES$6>=$F11,ES$6<=$G11),"."," ") | ET11: =IF(AND(ET$6>=$F11,ET$6<=$G11),"."," ") | EW11: =IF(AND(EW$6>=$F11,EW$6<=$G11),"."," ") | EX11: =IF(AND(EX$6>=$F11,EX$6<=$G11),"."," ") | EY11: =IF(AND(EY$6>=$F11,EY$6<=$G11),"."," ") | EZ11: =IF(AND(EZ$6>=$F11,EZ$6<=$G11),"."," ") | FA11: =IF(AND(FA$6>=$F11,FA$6<=$G11),"."," ") | FD11: =IF(AND(FD$6>=$F11,FD$6<=$G11),"."," ") | FE11: =IF(AND(FE$6>=$F11,FE$6<=$G11),"."," ") | FF11: =IF(AND(FF$6>=$F11,FF$6<=$G11),"."," ") | FG11: =IF(AND(FG$6>=$F11,FG$6<=$G11),"."," ") | FH11: =IF(AND(FH$6>=$F11,FH$6<=$G11),"."," ") | FK11: =IF(AND(FK$6>=$F11,FK$6<=$G11),"."," ") | FL11: =IF(AND(FL$6>=$F11,FL$6<=$G11),"."," ") | FM11: =IF(AND(FM$6>=$F11,FM$6<=$G11),"."," ") | FN11: =IF(AND(FN$6>=$F11,FN$6<=$G11),"."," ") | FO11: =IF(AND(FO$6>=$F11,FO$6<=$G11),"."," ") | FR11: =IF(AND(FR$6>=$F11,FR$6<=$G11),"."," ") | FS11: =IF(AND(FS$6>=$F11,FS$6<=$G11),"."," ") | FT11: =IF(AND(FT$6>=$F11,FT$6<=$G11),"."," ") | FU11: =IF(AND(FU$6>=$F11,FU$6<=$G11),"."," ") | FV11: =IF(AND(FV$6>=$F11,FV$6<=$G11),"."," ") | FY11: =IF(AND(FY$6>=$F11,FY$6<=$G11),"."," ") | FZ11: =IF(AND(FZ$6>=$F11,FZ$6<=$G11),"."," ") | GA11: =IF(AND(GA$6>=$F11,GA$6<=$G11),"."," ") | GB11: =IF(AND(GB$6>=$F11,GB$6<=$G11),"."," ") | GC11: =IF(AND(GC$6>=$F11,GC$6<=$G11),"."," ") | GF11: =IF(AND(GF$6>=$F11,GF$6<=$G11),"."," ") | GG11: =IF(AND(GG$6>=$F11,GG$6<=$G11),"."," ") | GH11: =IF(AND(GH$6>=$F11,GH$6<=$G11),"."," ") | GI11: =IF(AND(GI$6>=$F11,GI$6<=$G11),"."," ") | GJ11: =IF(AND(GJ$6>=$F11,GJ$6<=$G11),"."," ") | GM11: =IF(AND(GM$6>=$F11,GM$6<=$G11),"."," ") | GN11: =IF(AND(GN$6>=$F11,GN$6<=$G11),"."," ") | GO11: =IF(AND(GO$6>=$F11,GO$6<=$G11),"."," ") | GP11: =IF(AND(GP$6>=$F11,GP$6<=$G11),"."," ") | GQ11: =IF(AND(GQ$6>=$F11,GQ$6<=$G11),"."," ") | GT11: =IF(AND(GT$6>=$F11,GT$6<=$G11),"."," ") | GU11: =IF(AND(GU$6>=$F11,GU$6<=$G11),"."," ") | GV11: =IF(AND(GV$6>=$F11,GV$6<=$G11),"."," ") | GW11: =IF(AND(GW$6>=$F11,GW$6<=$G11),"."," ") | GX11: =IF(AND(GX$6>=$F11,GX$6<=$G11),"."," ") | HA11: =IF(AND(HA$6>=$F11,HA$6<=$G11),"."," ") | HB11: =IF(AND(HB$6>=$F11,HB$6<=$G11),"."," ") | HC11: =IF(AND(HC$6>=$F11,HC$6<=$G11),"."," ") | HD11: =IF(AND(HD$6>=$F11,HD$6<=$G11),"."," ") | HE11: =IF(AND(HE$6>=$F11,HE$6<=$G11),"."," ") | HH11: =IF(AND(HH$6>=$F11,HH$6<=$G11),"."," ") | HI11: =IF(AND(HI$6>=$F11,HI$6<=$G11),"."," ") | HJ11: =IF(AND(HJ$6>=$F11,HJ$6<=$G11),"."," ") | HK11: =IF(AND(HK$6>=$F11,HK$6<=$G11),"."," ") | HL11: =IF(AND(HL$6>=$F11,HL$6<=$G11),"."," ") | HO11: =IF(AND(HO$6>=$F11,HO$6<=$G11),"."," ") | HP11: =IF(AND(HP$6>=$F11,HP$6<=$G11),"."," ") | HQ11: =IF(AND(HQ$6>=$F11,HQ$6<=$G11),"."," ") | HR11: =IF(AND(HR$6>=$F11,HR$6<=$G11),"."," ") | HS11: =IF(AND(HS$6>=$F11,HS$6<=$G11),"."," ") | HV11: =IF(AND(HV$6>=$F11,HV$6<=$G11),"."," ") | HW11: =IF(AND(HW$6>=$F11,HW$6<=$G11),"."," ") | HX11: =IF(AND(HX$6>=$F11,HX$6<=$G11),"."," ") | HY11: =IF(AND(HY$6>=$F11,HY$6<=$G11),"."," ") | HZ11: =IF(AND(HZ$6>=$F11,HZ$6<=$G11),"."," ") | IC11: =IF(AND(IC$6>=$F11,IC$6<=$G11),"."," ") | ID11: =IF(AND(ID$6>=$F11,ID$6<=$G11),"."," ") | IE11: =IF(AND(IE$6>=$F11,IE$6<=$G11),"."," ") | IF11: =IF(AND(IF$6>=$F11,IF$6<=$G11),"."," ") | IG11: =IF(AND(IG$6>=$F11,IG$6<=$G11),"."," ") | IJ11: =IF(AND(IJ$6>=$F11,IJ$6<=$G11),"."," ") | IK11: =IF(AND(IK$6>=$F11,IK$6<=$G11),"."," ") | IL11: =IF(AND(IL$6>=$F11,IL$6<=$G11),"."," ") | IM11: =IF(AND(IM$6>=$F11,IM$6<=$G11),"."," ") | IN11: =IF(AND(IN$6>=$F11,IN$6<=$G11),"."," ") | IQ11: =IF(AND(IQ$6>=$F11,IQ$6<=$G11),"."," ") | IR11: =IF(AND(IR$6>=$F11,IR$6<=$G11),"."," ") | IS11: =IF(AND(IS$6>=$F11,IS$6<=$G11),"."," ") | IT11: =IF(AND(IT$6>=$F11,IT$6<=$G11),"."," ") | IU11: =IF(AND(IU$6>=$F11,IU$6<=$G11),"."," ") | IX11: =IF(AND(IX$6>=$F11,IX$6<=$G11),"."," ") | IY11: =IF(AND(IY$6>=$F11,IY$6<=$G11),"."," ") | IZ11: =IF(AND(IZ$6>=$F11,IZ$6<=$G11),"."," ") | JA11: =IF(AND(JA$6>=$F11,JA$6<=$G11),"."," ") | JB11: =IF(AND(JB$6>=$F11,JB$6<=$G11),"."," ") | JE11: =IF(AND(JE$6>=$F11,JE$6<=$G11),"."," ") | JF11: =IF(AND(JF$6>=$F11,JF$6<=$G11),"."," ") | JG11: =IF(AND(JG$6>=$F11,JG$6<=$G11),"."," ") | JH11: =IF(AND(JH$6>=$F11,JH$6<=$G11),"."," ") | JI11: =IF(AND(JI$6>=$F11,JI$6<=$G11),"."," ")
B12: =B11+1 -> 4 | C12: Draft Functional Requirements | D12: John | E12: 3 | F12: =VLOOKUP(E12,$B$6:$G$150,6,FALSE) + 1 -> 42508 | G12: =WORKDAY(F12,H12-1,Config!D10:D29) -> 42509 | H12: 2 | I12: 1 | J12: =IF(((NETWORKDAYS(F12,TODAY(),Data!C5:C24)*100)/H12)/100 > 0,((NETWORKDAYS(F12,TODAY(),Data!C5:C24)*100)/H12)/100,0) -> 831.5 | K12: =IF(J12>1, "100%",$J12) -> 100% | L12: =K12-I12 -> 0 | M12: =IF(AND(M$6>=$F12,M$6<=$G12),"."," ") | N12: =IF(AND(N$6>=$F12,N$6<=$G12),"."," ") | O12: =IF(AND(O$6>=$F12,O$6<=$G12),"."," ") | P12: =IF(AND(P$6>=$F12,P$6<=$G12),"."," ") | Q12: =IF(AND(Q$6>=$F12,Q$6<=$G12),"."," ") | T12: =IF(AND(T$6>=$F12,T$6<=$G12),"."," ") | U12: =IF(AND(U$6>=$F12,U$6<=$G12),"."," ") | V12: =IF(AND(V$6>=$F12,V$6<=$G12),"."," ") | W12: =IF(AND(W$6>=$F12,W$6<=$G12),"."," ") | X12: =IF(AND(X$6>=$F12,X$6<=$G12),"."," ") | AA12: =IF(AND(AA$6>=$F12,AA$6<=$G12),"."," ") -> . | AB12: =IF(AND(AB$6>=$F12,AB$6<=$G12),"."," ") | AC12: =IF(AND(AC$6>=$F12,AC$6<=$G12),"."," ") | AD12: =IF(AND(AD$6>=$F12,AD$6<=$G12),"."," ") | AE12: =IF(AND(AE$6>=$F12,AE$6<=$G12),"."," ") | AH12: =IF(AND(AH$6>=$F12,AH$6<=$G12),"."," ") | AI12: =IF(AND(AI$6>=$F12,AI$6<=$G12),"."," ") | AJ12: =IF(AND(AJ$6>=$F12,AJ$6<=$G12),"."," ") | AK12: =IF(AND(AK$6>=$F12,AK$6<=$G12),"."," ") | AL12: =IF(AND(AL$6>=$F12,AL$6<=$G12),"."," ") | AO12: =IF(AND(AO$6>=$F12,AO$6<=$G12),"."," ") | AP12: =IF(AND(AP$6>=$F12,AP$6<=$G12),"."," ") | AQ12: =IF(AND(AQ$6>=$F12,AQ$6<=$G12),"."," ") | AR12: =IF(AND(AR$6>=$F12,AR$6<=$G12),"."," ") | AS12: =IF(AND(AS$6>=$F12,AS$6<=$G12),"."," ") | AV12: =IF(AND(AV$6>=$F12,AV$6<=$G12),"."," ") | AW12: =IF(AND(AW$6>=$F12,AW$6<=$G12),"."," ") | AX12: =IF(AND(AX$6>=$F12,AX$6<=$G12),"."," ") | AY12: =IF(AND(AY$6>=$F12,AY$6<=$G12),"."," ") | AZ12: =IF(AND(AZ$6>=$F12,AZ$6<=$G12),"."," ") | BC12: =IF(AND(BC$6>=$F12,BC$6<=$G12),"."," ") | BD12: =IF(AND(BD$6>=$F12,BD$6<=$G12),"."," ") | BE12: =IF(AND(BE$6>=$F12,BE$6<=$G12),"."," ") | BF12: =IF(AND(BF$6>=$F12,BF$6<=$G12),"."," ") | BG12: =IF(AND(BG$6>=$F12,BG$6<=$G12),"."," ") | BJ12: =IF(AND(BJ$6>=$F12,BJ$6<=$G12),"."," ") | BK12: =IF(AND(BK$6>=$F12,BK$6<=$G12),"."," ") | BL12: =IF(AND(BL$6>=$F12,BL$6<=$G12),"."," ") | BM12: =IF(AND(BM$6>=$F12,BM$6<=$G12),"."," ") | BN12: =IF(AND(BN$6>=$F12,BN$6<=$G12),"."," ") | BQ12: =IF(AND(BQ$6>=$F12,BQ$6<=$G12),"."," ") | BR12: =IF(AND(BR$6>=$F12,BR$6<=$G12),"."," ") | BS12: =IF(AND(BS$6>=$F12,BS$6<=$G12),"."," ") | BT12: =IF(AND(BT$6>=$F12,BT$6<=$G12),"."," ") | BU12: =IF(AND(BU$6>=$F12,BU$6<=$G12),"."," ") | BX12: =IF(AND(BX$6>=$F12,BX$6<=$G12),"."," ") | BY12: =IF(AND(BY$6>=$F12,BY$6<=$G12),"."," ") | BZ12: =IF(AND(BZ$6>=$F12,BZ$6<=$G12),"."," ") | CA12: =IF(AND(CA$6>=$F12,CA$6<=$G12),"."," ") | CB12: =IF(AND(CB$6>=$F12,CB$6<=$G12),"."," ") | CE12: =IF(AND(CE$6>=$F12,CE$6<=$G12),"."," ") | CF12: =IF(AND(CF$6>=$F12,CF$6<=$G12),"."," ") | CG12: =IF(AND(CG$6>=$F12,CG$6<=$G12),"."," ") | CH12: =IF(AND(CH$6>=$F12,CH$6<=$G12),"."," ") | CI12: =IF(AND(CI$6>=$F12,CI$6<=$G12),"."," ") | CL12: =IF(AND(CL$6>=$F12,CL$6<=$G12),"."," ") | CM12: =IF(AND(CM$6>=$F12,CM$6<=$G12),"."," ") | CN12: =IF(AND(CN$6>=$F12,CN$6<=$G12),"."," ") | CO12: =IF(AND(CO$6>=$F12,CO$6<=$G12),"."," ") | CP12: =IF(AND(CP$6>=$F12,CP$6<=$G12),"."," ") | CS12: =IF(AND(CS$6>=$F12,CS$6<=$G12),"."," ") | CT12: =IF(AND(CT$6>=$F12,CT$6<=$G12),"."," ") | CU12: =IF(AND(CU$6>=$F12,CU$6<=$G12),"."," ") | CV12: =IF(AND(CV$6>=$F12,CV$6<=$G12),"."," ") | CW12: =IF(AND(CW$6>=$F12,CW$6<=$G12),"."," ") | CZ12: =IF(AND(CZ$6>=$F12,CZ$6<=$G12),"."," ") | DA12: =IF(AND(DA$6>=$F12,DA$6<=$G12),"."," ") | DB12: =IF(AND(DB$6>=$F12,DB$6<=$G12),"."," ") | DC12: =IF(AND(DC$6>=$F12,DC$6<=$G12),"."," ") | DD12: =IF(AND(DD$6>=$F12,DD$6<=$G12),"."," ") | DG12: =IF(AND(DG$6>=$F12,DG$6<=$G12),"."," ") | DH12: =IF(AND(DH$6>=$F12,DH$6<=$G12),"."," ") | DI12: =IF(AND(DI$6>=$F12,DI$6<=$G12),"."," ") | DJ12: =IF(AND(DJ$6>=$F12,DJ$6<=$G12),"."," ") | DK12: =IF(AND(DK$6>=$F12,DK$6<=$G12),"."," ") | DN12: =IF(AND(DN$6>=$F12,DN$6<=$G12),"."," ") | DO12: =IF(AND(DO$6>=$F12,DO$6<=$G12),"."," ") | DP12: =IF(AND(DP$6>=$F12,DP$6<=$G12),"."," ") | DQ12: =IF(AND(DQ$6>=$F12,DQ$6<=$G12),"."," ") | DR12: =IF(AND(DR$6>=$F12,DR$6<=$G12),"."," ") | DU12: =IF(AND(DU$6>=$F12,DU$6<=$G12),"."," ") | DV12: =IF(AND(DV$6>=$F12,DV$6<=$G12),"."," ") | DW12: =IF(AND(DW$6>=$F12,DW$6<=$G12),"."," ") | DX12: =IF(AND(DX$6>=$F12,DX$6<=$G12),"."," ") | DY12: =IF(AND(DY$6>=$F12,DY$6<=$G12),"."," ") | EB12: =IF(AND(EB$6>=$F12,EB$6<=$G12),"."," ") | EC12: =IF(AND(EC$6>=$F12,EC$6<=$G12),"."," ") | ED12: =IF(AND(ED$6>=$F12,ED$6<=$G12),"."," ") | EE12: =IF(AND(EE$6>=$F12,EE$6<=$G12),"."," ") | EF12: =IF(AND(EF$6>=$F12,EF$6<=$G12),"."," ") | EI12: =IF(AND(EI$6>=$F12,EI$6<=$G12),"."," ") | EJ12: =IF(AND(EJ$6>=$F12,EJ$6<=$G12),"."," ") | EK12: =IF(AND(EK$6>=$F12,EK$6<=$G12),"."," ") | EL12: =IF(AND(EL$6>=$F12,EL$6<=$G12),"."," ") | EM12: =IF(AND(EM$6>=$F12,EM$6<=$G12),"."," ") | EP12: =IF(AND(EP$6>=$F12,EP$6<=$G12),"."," ") | EQ12: =IF(AND(EQ$6>=$F12,EQ$6<=$G12),"."," ") | ER12: =IF(AND(ER$6>=$F12,ER$6<=$G12),"."," ") | ES12: =IF(AND(ES$6>=$F12,ES$6<=$G12),"."," ") | ET12: =IF(AND(ET$6>=$F12,ET$6<=$G12),"."," ") | EW12: =IF(AND(EW$6>=$F12,EW$6<=$G12),"."," ") | EX12: =IF(AND(EX$6>=$F12,EX$6<=$G12),"."," ") | EY12: =IF(AND(EY$6>=$F12,EY$6<=$G12),"."," ") | EZ12: =IF(AND(EZ$6>=$F12,EZ$6<=$G12),"."," ") | FA12: =IF(AND(FA$6>=$F12,FA$6<=$G12),"."," ") | FD12: =IF(AND(FD$6>=$F12,FD$6<=$G12),"."," ") | FE12: =IF(AND(FE$6>=$F12,FE$6<=$G12),"."," ") | FF12: =IF(AND(FF$6>=$F12,FF$6<=$G12),"."," ") | FG12: =IF(AND(FG$6>=$F12,FG$6<=$G12),"."," ") | FH12: =IF(AND(FH$6>=$F12,FH$6<=$G12),"."," ") | FK12: =IF(AND(FK$6>=$F12,FK$6<=$G12),"."," ") | FL12: =IF(AND(FL$6>=$F12,FL$6<=$G12),"."," ") | FM12: =IF(AND(FM$6>=$F12,FM$6<=$G12),"."," ") | FN12: =IF(AND(FN$6>=$F12,FN$6<=$G12),"."," ") | FO12: =IF(AND(FO$6>=$F12,FO$6<=$G12),"."," ") | FR12: =IF(AND(FR$6>=$F12,FR$6<=$G12),"."," ") | FS12: =IF(AND(FS$6>=$F12,FS$6<=$G12),"."," ") | FT12: =IF(AND(FT$6>=$F12,FT$6<=$G12),"."," ") | FU12: =IF(AND(FU$6>=$F12,FU$6<=$G12),"."," ") | FV12: =IF(AND(FV$6>=$F12,FV$6<=$G12),"."," ") | FY12: =IF(AND(FY$6>=$F12,FY$6<=$G12),"."," ") | FZ12: =IF(AND(FZ$6>=$F12,FZ$6<=$G12),"."," ") | GA12: =IF(AND(GA$6>=$F12,GA$6<=$G12),"."," ") | GB12: =IF(AND(GB$6>=$F12,GB$6<=$G12),"."," ") | GC12: =IF(AND(GC$6>=$F12,GC$6<=$G12),"."," ") | GF12: =IF(AND(GF$6>=$F12,GF$6<=$G12),"."," ") | GG12: =IF(AND(GG$6>=$F12,GG$6<=$G12),"."," ") | GH12: =IF(AND(GH$6>=$F12,GH$6<=$G12),"."," ") | GI12: =IF(AND(GI$6>=$F12,GI$6<=$G12),"."," ") | GJ12: =IF(AND(GJ$6>=$F12,GJ$6<=$G12),"."," ") | GM12: =IF(AND(GM$6>=$F12,GM$6<=$G12),"."," ") | GN12: =IF(AND(GN$6>=$F12,GN$6<=$G12),"."," ") | GO12: =IF(AND(GO$6>=$F12,GO$6<=$G12),"."," ") | GP12: =IF(AND(GP$6>=$F12,GP$6<=$G12),"."," ") | GQ12: =IF(AND(GQ$6>=$F12,GQ$6<=$G12),"."," ") | GT12: =IF(AND(GT$6>=$F12,GT$6<=$G12),"."," ") | GU12: =IF(AND(GU$6>=$F12,GU$6<=$G12),"."," ") | GV12: =IF(AND(GV$6>=$F12,GV$6<=$G12),"."," ") | GW12: =IF(AND(GW$6>=$F12,GW$6<=$G12),"."," ") | GX12: =IF(AND(GX$6>=$F12,GX$6<=$G12),"."," ") | HA12: =IF(AND(HA$6>=$F12,HA$6<=$G12),"."," ") | HB12: =IF(AND(HB$6>=$F12,HB$6<=$G12),"."," ") | HC12: =IF(AND(HC$6>=$F12,HC$6<=$G12),"."," ") | HD12: =IF(AND(HD$6>=$F12,HD$6<=$G12),"."," ") | HE12: =IF(AND(HE$6>=$F12,HE$6<=$G12),"."," ") | HH12: =IF(AND(HH$6>=$F12,HH$6<=$G12),"."," ") | HI12: =IF(AND(HI$6>=$F12,HI$6<=$G12),"."," ") | HJ12: =IF(AND(HJ$6>=$F12,HJ$6<=$G12),"."," ") | HK12: =IF(AND(HK$6>=$F12,HK$6<=$G12),"."," ") | HL12: =IF(AND(HL$6>=$F12,HL$6<=$G12),"."," ") | HO12: =IF(AND(HO$6>=$F12,HO$6<=$G12),"."," ") | HP12: =IF(AND(HP$6>=$F12,HP$6<=$G12),"."," ") | HQ12: =IF(AND(HQ$6>=$F12,HQ$6<=$G12),"."," ") | HR12: =IF(AND(HR$6>=$F12,HR$6<=$G12),"."," ") | HS12: =IF(AND(HS$6>=$F12,HS$6<=$G12),"."," ") | HV12: =IF(AND(HV$6>=$F12,HV$6<=$G12),"."," ") | HW12: =IF(AND(HW$6>=$F12,HW$6<=$G12),"."," ") | HX12: =IF(AND(HX$6>=$F12,HX$6<=$G12),"."," ") | HY12: =IF(AND(HY$6>=$F12,HY$6<=$G12),"."," ") | HZ12: =IF(AND(HZ$6>=$F12,HZ$6<=$G12),"."," ") | IC12: =IF(AND(IC$6>=$F12,IC$6<=$G12),"."," ") | ID12: =IF(AND(ID$6>=$F12,ID$6<=$G12),"."," ") | IE12: =IF(AND(IE$6>=$F12,IE$6<=$G12),"."," ") | IF12: =IF(AND(IF$6>=$F12,IF$6<=$G12),"."," ") | IG12: =IF(AND(IG$6>=$F12,IG$6<=$G12),"."," ") | IJ12: =IF(AND(IJ$6>=$F12,IJ$6<=$G12),"."," ") | IK12: =IF(AND(IK$6>=$F12,IK$6<=$G12),"."," ") | IL12: =IF(AND(IL$6>=$F12,IL$6<=$G12),"."," ") | IM12: =IF(AND(IM$6>=$F12,IM$6<=$G12),"."," ") | IN12: =IF(AND(IN$6>=$F12,IN$6<=$G12),"."," ") | IQ12: =IF(AND(IQ$6>=$F12,IQ$6<=$G12),"."," ") | IR12: =IF(AND(IR$6>=$F12,IR$6<=$G12),"."," ") | IS12: =IF(AND(IS$6>=$F12,IS$6<=$G12),"."," ") | IT12: =IF(AND(IT$6>=$F12,IT$6<=$G12),"."," ") | IU12: =IF(AND(IU$6>=$F12,IU$6<=$G12),"."," ") | IX12: =IF(AND(IX$6>=$F12,IX$6<=$G12),"."," ") | IY12: =IF(AND(IY$6>=$F12,IY$6<=$G12),"."," ") | IZ12: =IF(AND(IZ$6>=$F12,IZ$6<=$G12),"."," ") | JA12: =IF(AND(JA$6>=$F12,JA$6<=$G12),"."," ") | JB12: =IF(AND(JB$6>=$F12,JB$6<=$G12),"."," ") | JE12: =IF(AND(JE$6>=$F12,JE$6<=$G12),"."," ") | JF12: =IF(AND(JF$6>=$F12,JF$6<=$G12),"."," ") | JG12: =IF(AND(JG$6>=$F12,JG$6<=$G12),"."," ") | JH12: =IF(AND(JH$6>=$F12,JH$6<=$G12),"."," ") | JI12: =IF(AND(JI$6>=$F12,JI$6<=$G12),"."," ")
B13: =B12+1 -> 5 | C13: Sign Off Functional Requirements | D13: John | E13: 4 | F13: =VLOOKUP(E13,$B$6:$G$150,6,FALSE) + 1 -> 42510 | G13: =WORKDAY(F13,H13-1,Config!D11:D30) -> 42514 | H13: 3 | I13: 0.9 | J13: =IF(((NETWORKDAYS(F13,TODAY(),Data!C6:C25)*100)/H13)/100 > 0,((NETWORKDAYS(F13,TODAY(),Data!C6:C25)*100)/H13)/100,0) -> 553.66667 | K13: =IF(J13>1, "100%",$J13) -> 100% | L13: =K13-I13 -> 0.1 | M13: =IF(AND(M$6>=$F13,M$6<=$G13),"."," ") | N13: =IF(AND(N$6>=$F13,N$6<=$G13),"."," ") | O13: =IF(AND(O$6>=$F13,O$6<=$G13),"."," ") | P13: =IF(AND(P$6>=$F13,P$6<=$G13),"."," ") | Q13: =IF(AND(Q$6>=$F13,Q$6<=$G13),"."," ") | T13: =IF(AND(T$6>=$F13,T$6<=$G13),"."," ") | U13: =IF(AND(U$6>=$F13,U$6<=$G13),"."," ") | V13: =IF(AND(V$6>=$F13,V$6<=$G13),"."," ") | W13: =IF(AND(W$6>=$F13,W$6<=$G13),"."," ") | X13: =IF(AND(X$6>=$F13,X$6<=$G13),"."," ") | AA13: =IF(AND(AA$6>=$F13,AA$6<=$G13),"."," ") | AB13: =IF(AND(AB$6>=$F13,AB$6<=$G13),"."," ") -> . | AC13: =IF(AND(AC$6>=$F13,AC$6<=$G13),"."," ") -> . | AD13: =IF(AND(AD$6>=$F13,AD$6<=$G13),"."," ") -> . | AE13: =IF(AND(AE$6>=$F13,AE$6<=$G13),"."," ") -> . | AH13: =IF(AND(AH$6>=$F13,AH$6<=$G13),"."," ") | AI13: =IF(AND(AI$6>=$F13,AI$6<=$G13),"."," ") | AJ13: =IF(AND(AJ$6>=$F13,AJ$6<=$G13),"."," ") | AK13: =IF(AND(AK$6>=$F13,AK$6<=$G13),"."," ") | AL13: =IF(AND(AL$6>=$F13,AL$6<=$G13),"."," ") | AO13: =IF(AND(AO$6>=$F13,AO$6<=$G13),"."," ") | AP13: =IF(AND(AP$6>=$F13,AP$6<=$G13),"."," ") | AQ13: =IF(AND(AQ$6>=$F13,AQ$6<=$G13),"."," ") | AR13: =IF(AND(AR$6>=$F13,AR$6<=$G13),"."," ") | AS13: =IF(AND(AS$6>=$F13,AS$6<=$G13),"."," ") | AV13: =IF(AND(AV$6>=$F13,AV$6<=$G13),"."," ") | AW13: =IF(AND(AW$6>=$F13,AW$6<=$G13),"."," ") | AX13: =IF(AND(AX$6>=$F13,AX$6<=$G13),"."," ") | AY13: =IF(AND(AY$6>=$F13,AY$6<=$G13),"."," ") | AZ13: =IF(AND(AZ$6>=$F13,AZ$6<=$G13),"."," ") | BC13: =IF(AND(BC$6>=$F13,BC$6<=$G13),"."," ") | BD13: =IF(AND(BD$6>=$F13,BD$6<=$G13),"."," ") | BE13: =IF(AND(BE$6>=$F13,BE$6<=$G13),"."," ") | BF13: =IF(AND(BF$6>=$F13,BF$6<=$G13),"."," ") | BG13: =IF(AND(BG$6>=$F13,BG$6<=$G13),"."," ") | BJ13: =IF(AND(BJ$6>=$F13,BJ$6<=$G13),"."," ") | BK13: =IF(AND(BK$6>=$F13,BK$6<=$G13),"."," ") | BL13: =IF(AND(BL$6>=$F13,BL$6<=$G13),"."," ") | BM13: =IF(AND(BM$6>=$F13,BM$6<=$G13),"."," ") | BN13: =IF(AND(BN$6>=$F13,BN$6<=$G13),"."," ") | BQ13: =IF(AND(BQ$6>=$F13,BQ$6<=$G13),"."," ") | BR13: =IF(AND(BR$6>=$F13,BR$6<=$G13),"."," ") | BS13: =IF(AND(BS$6>=$F13,BS$6<=$G13),"."," ") | BT13: =IF(AND(BT$6>=$F13,BT$6<=$G13),"."," ") | BU13: =IF(AND(BU$6>=$F13,BU$6<=$G13),"."," ") | BX13: =IF(AND(BX$6>=$F13,BX$6<=$G13),"."," ") | BY13: =IF(AND(BY$6>=$F13,BY$6<=$G13),"."," ") | BZ13: =IF(AND(BZ$6>=$F13,BZ$6<=$G13),"."," ") | CA13: =IF(AND(CA$6>=$F13,CA$6<=$G13),"."," ") | CB13: =IF(AND(CB$6>=$F13,CB$6<=$G13),"."," ") | CE13: =IF(AND(CE$6>=$F13,CE$6<=$G13),"."," ") | CF13: =IF(AND(CF$6>=$F13,CF$6<=$G13),"."," ") | CG13: =IF(AND(CG$6>=$F13,CG$6<=$G13),"."," ") | CH13: =IF(AND(CH$6>=$F13,CH$6<=$G13),"."," ") | CI13: =IF(AND(CI$6>=$F13,CI$6<=$G13),"."," ") | CL13: =IF(AND(CL$6>=$F13,CL$6<=$G13),"."," ") | CM13: =IF(AND(CM$6>=$F13,CM$6<=$G13),"."," ") | CN13: =IF(AND(CN$6>=$F13,CN$6<=$G13),"."," ") | CO13: =IF(AND(CO$6>=$F13,CO$6<=$G13),"."," ") | CP13: =IF(AND(CP$6>=$F13,CP$6<=$G13),"."," ") | CS13: =IF(AND(CS$6>=$F13,CS$6<=$G13),"."," ") | CT13: =IF(AND(CT$6>=$F13,CT$6<=$G13),"."," ") | CU13: =IF(AND(CU$6>=$F13,CU$6<=$G13),"."," ") | CV13: =IF(AND(CV$6>=$F13,CV$6<=$G13),"."," ") | CW13: =IF(AND(CW$6>=$F13,CW$6<=$G13),"."," ") | CZ13: =IF(AND(CZ$6>=$F13,CZ$6<=$G13),"."," ") | DA13: =IF(AND(DA$6>=$F13,DA$6<=$G13),"."," ") | DB13: =IF(AND(DB$6>=$F13,DB$6<=$G13),"."," ") | DC13: =IF(AND(DC$6>=$F13,DC$6<=$G13),"."," ") | DD13: =IF(AND(DD$6>=$F13,DD$6<=$G13),"."," ") | DG13: =IF(AND(DG$6>=$F13,DG$6<=$G13),"."," ") | DH13: =IF(AND(DH$6>=$F13,DH$6<=$G13),"."," ") | DI13: =IF(AND(DI$6>=$F13,DI$6<=$G13),"."," ") | DJ13: =IF(AND(DJ$6>=$F13,DJ$6<=$G13),"."," ") | DK13: =IF(AND(DK$6>=$F13,DK$6<=$G13),"."," ") | DN13: =IF(AND(DN$6>=$F13,DN$6<=$G13),"."," ") | DO13: =IF(AND(DO$6>=$F13,DO$6<=$G13),"."," ") | DP13: =IF(AND(DP$6>=$F13,DP$6<=$G13),"."," ") | DQ13: =IF(AND(DQ$6>=$F13,DQ$6<=$G13),"."," ") | DR13: =IF(AND(DR$6>=$F13,DR$6<=$G13),"."," ") | DU13: =IF(AND(DU$6>=$F13,DU$6<=$G13),"."," ") | DV13: =IF(AND(DV$6>=$F13,DV$6<=$G13),"."," ") | DW13: =IF(AND(DW$6>=$F13,DW$6<=$G13),"."," ") | DX13: =IF(AND(DX$6>=$F13,DX$6<=$G13),"."," ") | DY13: =IF(AND(DY$6>=$F13,DY$6<=$G13),"."," ") | EB13: =IF(AND(EB$6>=$F13,EB$6<=$G13),"."," ") | EC13: =IF(AND(EC$6>=$F13,EC$6<=$G13),"."," ") | ED13: =IF(AND(ED$6>=$F13,ED$6<=$G13),"."," ") | EE13: =IF(AND(EE$6>=$F13,EE$6<=$G13),"."," ") | EF13: =IF(AND(EF$6>=$F13,EF$6<=$G13),"."," ") | EI13: =IF(AND(EI$6>=$F13,EI$6<=$G13),"."," ") | EJ13: =IF(AND(EJ$6>=$F13,EJ$6<=$G13),"."," ") | EK13: =IF(AND(EK$6>=$F13,EK$6<=$G13),"."," ") | EL13: =IF(AND(EL$6>=$F13,EL$6<=$G13),"."," ") | EM13: =IF(AND(EM$6>=$F13,EM$6<=$G13),"."," ") | EP13: =IF(AND(EP$6>=$F13,EP$6<=$G13),"."," ") | EQ13: =IF(AND(EQ$6>=$F13,EQ$6<=$G13),"."," ") | ER13: =IF(AND(ER$6>=$F13,ER$6<=$G13),"."," ") | ES13: =IF(AND(ES$6>=$F13,ES$6<=$G13),"."," ") | ET13: =IF(AND(ET$6>=$F13,ET$6<=$G13),"."," ") | EW13: =IF(AND(EW$6>=$F13,EW$6<=$G13),"."," ") | EX13: =IF(AND(EX$6>=$F13,EX$6<=$G13),"."," ") | EY13: =IF(AND(EY$6>=$F13,EY$6<=$G13),"."," ") | EZ13: =IF(AND(EZ$6>=$F13,EZ$6<=$G13),"."," ") | FA13: =IF(AND(FA$6>=$F13,FA$6<=$G13),"."," ") | FD13: =IF(AND(FD$6>=$F13,FD$6<=$G13),"."," ") | FE13: =IF(AND(FE$6>=$F13,FE$6<=$G13),"."," ") | FF13: =IF(AND(FF$6>=$F13,FF$6<=$G13),"."," ") | FG13: =IF(AND(FG$6>=$F13,FG$6<=$G13),"."," ") | FH13: =IF(AND(FH$6>=$F13,FH$6<=$G13),"."," ") | FK13: =IF(AND(FK$6>=$F13,FK$6<=$G13),"."," ") | FL13: =IF(AND(FL$6>=$F13,FL$6<=$G13),"."," ") | FM13: =IF(AND(FM$6>=$F13,FM$6<=$G13),"."," ") | FN13: =IF(AND(FN$6>=$F13,FN$6<=$G13),"."," ") | FO13: =IF(AND(FO$6>=$F13,FO$6<=$G13),"."," ") | FR13: =IF(AND(FR$6>=$F13,FR$6<=$G13),"."," ") | FS13: =IF(AND(FS$6>=$F13,FS$6<=$G13),"."," ") | FT13: =IF(AND(FT$6>=$F13,FT$6<=$G13),"."," ") | FU13: =IF(AND(FU$6>=$F13,FU$6<=$G13),"."," ") | FV13: =IF(AND(FV$6>=$F13,FV$6<=$G13),"."," ") | FY13: =IF(AND(FY$6>=$F13,FY$6<=$G13),"."," ") | FZ13: =IF(AND(FZ$6>=$F13,FZ$6<=$G13),"."," ") | GA13: =IF(AND(GA$6>=$F13,GA$6<=$G13),"."," ") | GB13: =IF(AND(GB$6>=$F13,GB$6<=$G13),"."," ") | GC13: =IF(AND(GC$6>=$F13,GC$6<=$G13),"."," ") | GF13: =IF(AND(GF$6>=$F13,GF$6<=$G13),"."," ") | GG13: =IF(AND(GG$6>=$F13,GG$6<=$G13),"."," ") | GH13: =IF(AND(GH$6>=$F13,GH$6<=$G13),"."," ") | GI13: =IF(AND(GI$6>=$F13,GI$6<=$G13),"."," ") | GJ13: =IF(AND(GJ$6>=$F13,GJ$6<=$G13),"."," ") | GM13: =IF(AND(GM$6>=$F13,GM$6<=$G13),"."," ") | GN13: =IF(AND(GN$6>=$F13,GN$6<=$G13),"."," ") | GO13: =IF(AND(GO$6>=$F13,GO$6<=$G13),"."," ") | GP13: =IF(AND(GP$6>=$F13,GP$6<=$G13),"."," ") | GQ13: =IF(AND(GQ$6>=$F13,GQ$6<=$G13),"."," ") | GT13: =IF(AND(GT$6>=$F13,GT$6<=$G13),"."," ") | GU13: =IF(AND(GU$6>=$F13,GU$6<=$G13),"."," ") | GV13: =IF(AND(GV$6>=$F13,GV$6<=$G13),"."," ") | GW13: =IF(AND(GW$6>=$F13,GW$6<=$G13),"."," ") | GX13: =IF(AND(GX$6>=$F13,GX$6<=$G13),"."," ") | HA13: =IF(AND(HA$6>=$F13,HA$6<=$G13),"."," ") | HB13: =IF(AND(HB$6>=$F13,HB$6<=$G13),"."," ") | HC13: =IF(AND(HC$6>=$F13,HC$6<=$G13),"."," ") | HD13: =IF(AND(HD$6>=$F13,HD$6<=$G13),"."," ") | HE13: =IF(AND(HE$6>=$F13,HE$6<=$G13),"."," ") | HH13: =IF(AND(HH$6>=$F13,HH$6<=$G13),"."," ") | HI13: =IF(AND(HI$6>=$F13,HI$6<=$G13),"."," ") | HJ13: =IF(AND(HJ$6>=$F13,HJ$6<=$G13),"."," ") | HK13: =IF(AND(HK$6>=$F13,HK$6<=$G13),"."," ") | HL13: =IF(AND(HL$6>=$F13,HL$6<=$G13),"."," ") | HO13: =IF(AND(HO$6>=$F13,HO$6<=$G13),"."," ") | HP13: =IF(AND(HP$6>=$F13,HP$6<=$G13),"."," ") | HQ13: =IF(AND(HQ$6>=$F13,HQ$6<=$G13),"."," ") | HR13: =IF(AND(HR$6>=$F13,HR$6<=$G13),"."," ") | HS13: =IF(AND(HS$6>=$F13,HS$6<=$G13),"."," ") | HV13: =IF(AND(HV$6>=$F13,HV$6<=$G13),"."," ") | HW13: =IF(AND(HW$6>=$F13,HW$6<=$G13),"."," ") | HX13: =IF(AND(HX$6>=$F13,HX$6<=$G13),"."," ") | HY13: =IF(AND(HY$6>=$F13,HY$6<=$G13),"."," ") | HZ13: =IF(AND(HZ$6>=$F13,HZ$6<=$G13),"."," ") | IC13: =IF(AND(IC$6>=$F13,IC$6<=$G13),"."," ") | ID13: =IF(AND(ID$6>=$F13,ID$6<=$G13),"."," ") | IE13: =IF(AND(IE$6>=$F13,IE$6<=$G13),"."," ") | IF13: =IF(AND(IF$6>=$F13,IF$6<=$G13),"."," ") | IG13: =IF(AND(IG$6>=$F13,IG$6<=$G13),"."," ") | IJ13: =IF(AND(IJ$6>=$F13,IJ$6<=$G13),"."," ") | IK13: =IF(AND(IK$6>=$F13,IK$6<=$G13),"."," ") | IL13: =IF(AND(IL$6>=$F13,IL$6<=$G13),"."," ") | IM13: =IF(AND(IM$6>=$F13,IM$6<=$G13),"."," ") | IN13: =IF(AND(IN$6>=$F13,IN$6<=$G13),"."," ") | IQ13: =IF(AND(IQ$6>=$F13,IQ$6<=$G13),"."," ") | IR13: =IF(AND(IR$6>=$F13,IR$6<=$G13),"."," ") | IS13: =IF(AND(IS$6>=$F13,IS$6<=$G13),"."," ") | IT13: =IF(AND(IT$6>=$F13,IT$6<=$G13),"."," ") | IU13: =IF(AND(IU$6>=$F13,IU$6<=$G13),"."," ") | IX13: =IF(AND(IX$6>=$F13,IX$6<=$G13),"."," ") | IY13: =IF(AND(IY$6>=$F13,IY$6<=$G13),"."," ") | IZ13: =IF(AND(IZ$6>=$F13,IZ$6<=$G13),"."," ") | JA13: =IF(AND(JA$6>=$F13,JA$6<=$G13),"."," ") | JB13: =IF(AND(JB$6>=$F13,JB$6<=$G13),"."," ") | JE13: =IF(AND(JE$6>=$F13,JE$6<=$G13),"."," ") | JF13: =IF(AND(JF$6>=$F13,JF$6<=$G13),"."," ") | JG13: =IF(AND(JG$6>=$F13,JG$6<=$G13),"."," ") | JH13: =IF(AND(JH$6>=$F13,JH$6<=$G13),"."," ") | JI13: =IF(AND(JI$6>=$F13,JI$6<=$G13),"."," ")
B14: =B13+1 -> 6 | C14: Requirements Discussions | D14: John | E14: 5 | F14: =VLOOKUP(E14,$B$6:$G$150,6,FALSE) + 1 -> 42515 | G14: =WORKDAY(F14,H14-1,Config!D12:D31) -> 42516 | H14: 2 | I14: 1 | J14: =IF(((NETWORKDAYS(F14,TODAY(),Data!C7:C26)*100)/H14)/100 > 0,((NETWORKDAYS(F14,TODAY(),Data!C7:C26)*100)/H14)/100,0) -> 829 | K14: =IF(J14>1, "100%",$J14) -> 100% | L14: =K14-I14 -> 0 | M14: =IF(AND(M$6>=$F14,M$6<=$G14),"."," ") | N14: =IF(AND(N$6>=$F14,N$6<=$G14),"."," ") | O14: =IF(AND(O$6>=$F14,O$6<=$G14),"."," ") | P14: =IF(AND(P$6>=$F14,P$6<=$G14),"."," ") | Q14: =IF(AND(Q$6>=$F14,Q$6<=$G14),"."," ") | T14: =IF(AND(T$6>=$F14,T$6<=$G14),"."," ") | U14: =IF(AND(U$6>=$F14,U$6<=$G14),"."," ") | V14: =IF(AND(V$6>=$F14,V$6<=$G14),"."," ") | W14: =IF(AND(W$6>=$F14,W$6<=$G14),"."," ") | X14: =IF(AND(X$6>=$F14,X$6<=$G14),"."," ") | AA14: =IF(AND(AA$6>=$F14,AA$6<=$G14),"."," ") | AB14: =IF(AND(AB$6>=$F14,AB$6<=$G14),"."," ") | AC14: =IF(AND(AC$6>=$F14,AC$6<=$G14),"."," ") | AD14: =IF(AND(AD$6>=$F14,AD$6<=$G14),"."," ") | AE14: =IF(AND(AE$6>=$F14,AE$6<=$G14),"."," ") | AH14: =IF(AND(AH$6>=$F14,AH$6<=$G14),"."," ") -> . | AI14: =IF(AND(AI$6>=$F14,AI$6<=$G14),"."," ") | AJ14: =IF(AND(AJ$6>=$F14,AJ$6<=$G14),"."," ") | AK14: =IF(AND(AK$6>=$F14,AK$6<=$G14),"."," ") | AL14: =IF(AND(AL$6>=$F14,AL$6<=$G14),"."," ") | AO14: =IF(AND(AO$6>=$F14,AO$6<=$G14),"."," ") | AP14: =IF(AND(AP$6>=$F14,AP$6<=$G14),"."," ") | AQ14: =IF(AND(AQ$6>=$F14,AQ$6<=$G14),"."," ") | AR14: =IF(AND(AR$6>=$F14,AR$6<=$G14),"."," ") | AS14: =IF(AND(AS$6>=$F14,AS$6<=$G14),"."," ") | AV14: =IF(AND(AV$6>=$F14,AV$6<=$G14),"."," ") | AW14: =IF(AND(AW$6>=$F14,AW$6<=$G14),"."," ") | AX14: =IF(AND(AX$6>=$F14,AX$6<=$G14),"."," ") | AY14: =IF(AND(AY$6>=$F14,AY$6<=$G14),"."," ") | AZ14: =IF(AND(AZ$6>=$F14,AZ$6<=$G14),"."," ") | BC14: =IF(AND(BC$6>=$F14,BC$6<=$G14),"."," ") | BD14: =IF(AND(BD$6>=$F14,BD$6<=$G14),"."," ") | BE14: =IF(AND(BE$6>=$F14,BE$6<=$G14),"."," ") | BF14: =IF(AND(BF$6>=$F14,BF$6<=$G14),"."," ") | BG14: =IF(AND(BG$6>=$F14,BG$6<=$G14),"."," ") | BJ14: =IF(AND(BJ$6>=$F14,BJ$6<=$G14),"."," ") | BK14: =IF(AND(BK$6>=$F14,BK$6<=$G14),"."," ") | BL14: =IF(AND(BL$6>=$F14,BL$6<=$G14),"."," ") | BM14: =IF(AND(BM$6>=$F14,BM$6<=$G14),"."," ") | BN14: =IF(AND(BN$6>=$F14,BN$6<=$G14),"."," ") | BQ14: =IF(AND(BQ$6>=$F14,BQ$6<=$G14),"."," ") | BR14: =IF(AND(BR$6>=$F14,BR$6<=$G14),"."," ") | BS14: =IF(AND(BS$6>=$F14,BS$6<=$G14),"."," ") | BT14: =IF(AND(BT$6>=$F14,BT$6<=$G14),"."," ") | BU14: =IF(AND(BU$6>=$F14,BU$6<=$G14),"."," ") | BX14: =IF(AND(BX$6>=$F14,BX$6<=$G14),"."," ") | BY14: =IF(AND(BY$6>=$F14,BY$6<=$G14),"."," ") | BZ14: =IF(AND(BZ$6>=$F14,BZ$6<=$G14),"."," ") | CA14: =IF(AND(CA$6>=$F14,CA$6<=$G14),"."," ") | CB14: =IF(AND(CB$6>=$F14,CB$6<=$G14),"."," ") | CE14: =IF(AND(CE$6>=$F14,CE$6<=$G14),"."," ") | CF14: =IF(AND(CF$6>=$F14,CF$6<=$G14),"."," ") | CG14: =IF(AND(CG$6>=$F14,CG$6<=$G14),"."," ") | CH14: =IF(AND(CH$6>=$F14,CH$6<=$G14),"."," ") | CI14: =IF(AND(CI$6>=$F14,CI$6<=$G14),"."," ") | CL14: =IF(AND(CL$6>=$F14,CL$6<=$G14),"."," ") | CM14: =IF(AND(CM$6>=$F14,CM$6<=$G14),"."," ") | CN14: =IF(AND(CN$6>=$F14,CN$6<=$G14),"."," ") | CO14: =IF(AND(CO$6>=$F14,CO$6<=$G14),"."," ") | CP14: =IF(AND(CP$6>=$F14,CP$6<=$G14),"."," ") | CS14: =IF(AND(CS$6>=$F14,CS$6<=$G14),"."," ") | CT14: =IF(AND(CT$6>=$F14,CT$6<=$G14),"."," ") | CU14: =IF(AND(CU$6>=$F14,CU$6<=$G14),"."," ") | CV14: =IF(AND(CV$6>=$F14,CV$6<=$G14),"."," ") | CW14: =IF(AND(CW$6>=$F14,CW$6<=$G14),"."," ") | CZ14: =IF(AND(CZ$6>=$F14,CZ$6<=$G14),"."," ") | DA14: =IF(AND(DA$6>=$F14,DA$6<=$G14),"."," ") | DB14: =IF(AND(DB$6>=$F14,DB$6<=$G14),"."," ") | DC14: =IF(AND(DC$6>=$F14,DC$6<=$G14),"."," ") | DD14: =IF(AND(DD$6>=$F14,DD$6<=$G14),"."," ") | DG14: =IF(AND(DG$6>=$F14,DG$6<=$G14),"."," ") | DH14: =IF(AND(DH$6>=$F14,DH$6<=$G14),"."," ") | DI14: =IF(AND(DI$6>=$F14,DI$6<=$G14),"."," ") | DJ14: =IF(AND(DJ$6>=$F14,DJ$6<=$G14),"."," ") | DK14: =IF(AND(DK$6>=$F14,DK$6<=$G14),"."," ") | DN14: =IF(AND(DN$6>=$F14,DN$6<=$G14),"."," ") | DO14: =IF(AND(DO$6>=$F14,DO$6<=$G14),"."," ") | DP14: =IF(AND(DP$6>=$F14,DP$6<=$G14),"."," ") | DQ14: =IF(AND(DQ$6>=$F14,DQ$6<=$G14),"."," ") | DR14: =IF(AND(DR$6>=$F14,DR$6<=$G14),"."," ") | DU14: =IF(AND(DU$6>=$F14,DU$6<=$G14),"."," ") | DV14: =IF(AND(DV$6>=$F14,DV$6<=$G14),"."," ") | DW14: =IF(AND(DW$6>=$F14,DW$6<=$G14),"."," ") | DX14: =IF(AND(DX$6>=$F14,DX$6<=$G14),"."," ") | DY14: =IF(AND(DY$6>=$F14,DY$6<=$G14),"."," ") | EB14: =IF(AND(EB$6>=$F14,EB$6<=$G14),"."," ") | EC14: =IF(AND(EC$6>=$F14,EC$6<=$G14),"."," ") | ED14: =IF(AND(ED$6>=$F14,ED$6<=$G14),"."," ") | EE14: =IF(AND(EE$6>=$F14,EE$6<=$G14),"."," ") | EF14: =IF(AND(EF$6>=$F14,EF$6<=$G14),"."," ") | EI14: =IF(AND(EI$6>=$F14,EI$6<=$G14),"."," ") | EJ14: =IF(AND(EJ$6>=$F14,EJ$6<=$G14),"."," ") | EK14: =IF(AND(EK$6>=$F14,EK$6<=$G14),"."," ") | EL14: =IF(AND(EL$6>=$F14,EL$6<=$G14),"."," ") | EM14: =IF(AND(EM$6>=$F14,EM$6<=$G14),"."," ") | EP14: =IF(AND(EP$6>=$F14,EP$6<=$G14),"."," ") | EQ14: =IF(AND(EQ$6>=$F14,EQ$6<=$G14),"."," ") | ER14: =IF(AND(ER$6>=$F14,ER$6<=$G14),"."," ") | ES14: =IF(AND(ES$6>=$F14,ES$6<=$G14),"."," ") | ET14: =IF(AND(ET$6>=$F14,ET$6<=$G14),"."," ") | EW14: =IF(AND(EW$6>=$F14,EW$6<=$G14),"."," ") | EX14: =IF(AND(EX$6>=$F14,EX$6<=$G14),"."," ") | EY14: =IF(AND(EY$6>=$F14,EY$6<=$G14),"."," ") | EZ14: =IF(AND(EZ$6>=$F14,EZ$6<=$G14),"."," ") | FA14: =IF(AND(FA$6>=$F14,FA$6<=$G14),"."," ") | FD14: =IF(AND(FD$6>=$F14,FD$6<=$G14),"."," ") | FE14: =IF(AND(FE$6>=$F14,FE$6<=$G14),"."," ") | FF14: =IF(AND(FF$6>=$F14,FF$6<=$G14),"."," ") | FG14: =IF(AND(FG$6>=$F14,FG$6<=$G14),"."," ") | FH14: =IF(AND(FH$6>=$F14,FH$6<=$G14),"."," ") | FK14: =IF(AND(FK$6>=$F14,FK$6<=$G14),"."," ") | FL14: =IF(AND(FL$6>=$F14,FL$6<=$G14),"."," ") | FM14: =IF(AND(FM$6>=$F14,FM$6<=$G14),"."," ") | FN14: =IF(AND(FN$6>=$F14,FN$6<=$G14),"."," ") | FO14: =IF(AND(FO$6>=$F14,FO$6<=$G14),"."," ") | FR14: =IF(AND(FR$6>=$F14,FR$6<=$G14),"."," ") | FS14: =IF(AND(FS$6>=$F14,FS$6<=$G14),"."," ") | FT14: =IF(AND(FT$6>=$F14,FT$6<=$G14),"."," ") | FU14: =IF(AND(FU$6>=$F14,FU$6<=$G14),"."," ") | FV14: =IF(AND(FV$6>=$F14,FV$6<=$G14),"."," ") | FY14: =IF(AND(FY$6>=$F14,FY$6<=$G14),"."," ") | FZ14: =IF(AND(FZ$6>=$F14,FZ$6<=$G14),"."," ") | GA14: =IF(AND(GA$6>=$F14,GA$6<=$G14),"."," ") | GB14: =IF(AND(GB$6>=$F14,GB$6<=$G14),"."," ") | GC14: =IF(AND(GC$6>=$F14,GC$6<=$G14),"."," ") | GF14: =IF(AND(GF$6>=$F14,GF$6<=$G14),"."," ") | GG14: =IF(AND(GG$6>=$F14,GG$6<=$G14),"."," ") | GH14: =IF(AND(GH$6>=$F14,GH$6<=$G14),"."," ") | GI14: =IF(AND(GI$6>=$F14,GI$6<=$G14),"."," ") | GJ14: =IF(AND(GJ$6>=$F14,GJ$6<=$G14),"."," ") | GM14: =IF(AND(GM$6>=$F14,GM$6<=$G14),"."," ") | GN14: =IF(AND(GN$6>=$F14,GN$6<=$G14),"."," ") | GO14: =IF(AND(GO$6>=$F14,GO$6<=$G14),"."," ") | GP14: =IF(AND(GP$6>=$F14,GP$6<=$G14),"."," ") | GQ14: =IF(AND(GQ$6>=$F14,GQ$6<=$G14),"."," ") | GT14: =IF(AND(GT$6>=$F14,GT$6<=$G14),"."," ") | GU14: =IF(AND(GU$6>=$F14,GU$6<=$G14),"."," ") | GV14: =IF(AND(GV$6>=$F14,GV$6<=$G14),"."," ") | GW14: =IF(AND(GW$6>=$F14,GW$6<=$G14),"."," ") | GX14: =IF(AND(GX$6>=$F14,GX$6<=$G14),"."," ") | HA14: =IF(AND(HA$6>=$F14,HA$6<=$G14),"."," ") | HB14: =IF(AND(HB$6>=$F14,HB$6<=$G14),"."," ") | HC14: =IF(AND(HC$6>=$F14,HC$6<=$G14),"."," ") | HD14: =IF(AND(HD$6>=$F14,HD$6<=$G14),"."," ") | HE14: =IF(AND(HE$6>=$F14,HE$6<=$G14),"."," ") | HH14: =IF(AND(HH$6>=$F14,HH$6<=$G14),"."," ") | HI14: =IF(AND(HI$6>=$F14,HI$6<=$G14),"."," ") | HJ14: =IF(AND(HJ$6>=$F14,HJ$6<=$G14),"."," ") | HK14: =IF(AND(HK$6>=$F14,HK$6<=$G14),"."," ") | HL14: =IF(AND(HL$6>=$F14,HL$6<=$G14),"."," ") | HO14: =IF(AND(HO$6>=$F14,HO$6<=$G14),"."," ") | HP14: =IF(AND(HP$6>=$F14,HP$6<=$G14),"."," ") | HQ14: =IF(AND(HQ$6>=$F14,HQ$6<=$G14),"."," ") | HR14: =IF(AND(HR$6>=$F14,HR$6<=$G14),"."," ") | HS14: =IF(AND(HS$6>=$F14,HS$6<=$G14),"."," ") | HV14: =IF(AND(HV$6>=$F14,HV$6<=$G14),"."," ") | HW14: =IF(AND(HW$6>=$F14,HW$6<=$G14),"."," ") | HX14: =IF(AND(HX$6>=$F14,HX$6<=$G14),"."," ") | HY14: =IF(AND(HY$6>=$F14,HY$6<=$G14),"."," ") | HZ14: =IF(AND(HZ$6>=$F14,HZ$6<=$G14),"."," ") | IC14: =IF(AND(IC$6>=$F14,IC$6<=$G14),"."," ") | ID14: =IF(AND(ID$6>=$F14,ID$6<=$G14),"."," ") | IE14: =IF(AND(IE$6>=$F14,IE$6<=$G14),"."," ") | IF14: =IF(AND(IF$6>=$F14,IF$6<=$G14),"."," ") | IG14: =IF(AND(IG$6>=$F14,IG$6<=$G14),"."," ") | IJ14: =IF(AND(IJ$6>=$F14,IJ$6<=$G14),"."," ") | IK14: =IF(AND(IK$6>=$F14,IK$6<=$G14),"."," ") | IL14: =IF(AND(IL$6>=$F14,IL$6<=$G14),"."," ") | IM14: =IF(AND(IM$6>=$F14,IM$6<=$G14),"."," ") | IN14: =IF(AND(IN$6>=$F14,IN$6<=$G14),"."," ") | IQ14: =IF(AND(IQ$6>=$F14,IQ$6<=$G14),"."," ") | IR14: =IF(AND(IR$6>=$F14,IR$6<=$G14),"."," ") | IS14: =IF(AND(IS$6>=$F14,IS$6<=$G14),"."," ") | IT14: =IF(AND(IT$6>=$F14,IT$6<=$G14),"."," ") | IU14: =IF(AND(IU$6>=$F14,IU$6<=$G14),"."," ") | IX14: =IF(AND(IX$6>=$F14,IX$6<=$G14),"."," ") | IY14: =IF(AND(IY$6>=$F14,IY$6<=$G14),"."," ") | IZ14: =IF(AND(IZ$6>=$F14,IZ$6<=$G14),"."," ") | JA14: =IF(AND(JA$6>=$F14,JA$6<=$G14),"."," ") | JB14: =IF(AND(JB$6>=$F14,JB$6<=$G14),"."," ") | JE14: =IF(AND(JE$6>=$F14,JE$6<=$G14),"."," ") | JF14: =IF(AND(JF$6>=$F14,JF$6<=$G14),"."," ") | JG14: =IF(AND(JG$6>=$F14,JG$6<=$G14),"."," ") | JH14: =IF(AND(JH$6>=$F14,JH$6<=$G14),"."," ") | JI14: =IF(AND(JI$6>=$F14,JI$6<=$G14),"."," ")
B15: =B14+1 -> 7 | C15: High Level Design | D15: Developer | E15: 6 | F15: =VLOOKUP(E15,$B$6:$G$150,6,FALSE) + 1 -> 42517 | G15: =WORKDAY(F15,H15-1,Config!D14:D33) -> 42520 | H15: 2 | I15: 0.98 | J15: =IF(((NETWORKDAYS(F15,TODAY(),Data!C9:C28)*100)/H15)/100 > 0,((NETWORKDAYS(F15,TODAY(),Data!C9:C28)*100)/H15)/100,0) -> 828 | K15: =IF(J15>1, "100%",$J15) -> 100% | L15: =K15-I15 -> 0.02 | M15: =IF(AND(M$6>=$F15,M$6<=$G15),"."," ") | N15: =IF(AND(N$6>=$F15,N$6<=$G15),"."," ") | O15: =IF(AND(O$6>=$F15,O$6<=$G15),"."," ") | P15: =IF(AND(P$6>=$F15,P$6<=$G15),"."," ") | Q15: =IF(AND(Q$6>=$F15,Q$6<=$G15),"."," ") | T15: =IF(AND(T$6>=$F15,T$6<=$G15),"."," ") | U15: =IF(AND(U$6>=$F15,U$6<=$G15),"."," ") | V15: =IF(AND(V$6>=$F15,V$6<=$G15),"."," ") | W15: =IF(AND(W$6>=$F15,W$6<=$G15),"."," ") | X15: =IF(AND(X$6>=$F15,X$6<=$G15),"."," ") | AA15: =IF(AND(AA$6>=$F15,AA$6<=$G15),"."," ") | AB15: =IF(AND(AB$6>=$F15,AB$6<=$G15),"."," ") | AC15: =IF(AND(AC$6>=$F15,AC$6<=$G15),"."," ") | AD15: =IF(AND(AD$6>=$F15,AD$6<=$G15),"."," ") | AE15: =IF(AND(AE$6>=$F15,AE$6<=$G15),"."," ") | AH15: =IF(AND(AH$6>=$F15,AH$6<=$G15),"."," ") | AI15: =IF(AND(AI$6>=$F15,AI$6<=$G15),"."," ") -> . | AJ15: =IF(AND(AJ$6>=$F15,AJ$6<=$G15),"."," ") -> . | AK15: =IF(AND(AK$6>=$F15,AK$6<=$G15),"."," ") -> . | AL15: =IF(AND(AL$6>=$F15,AL$6<=$G15),"."," ") -> . | AO15: =IF(AND(AO$6>=$F15,AO$6<=$G15),"."," ") | AP15: =IF(AND(AP$6>=$F15,AP$6<=$G15),"."," ") | AQ15: =IF(AND(AQ$6>=$F15,AQ$6<=$G15),"."," ") | AR15: =IF(AND(AR$6>=$F15,AR$6<=$G15),"."," ") | AS15: =IF(AND(AS$6>=$F15,AS$6<=$G15),"."," ") | AV15: =IF(AND(AV$6>=$F15,AV$6<=$G15),"."," ") | AW15: =IF(AND(AW$6>=$F15,AW$6<=$G15),"."," ") | AX15: =IF(AND(AX$6>=$F15,AX$6<=$G15),"."," ") | AY15: =IF(AND(AY$6>=$F15,AY$6<=$G15),"."," ") | AZ15: =IF(AND(AZ$6>=$F15,AZ$6<=$G15),"."," ") | BC15: =IF(AND(BC$6>=$F15,BC$6<=$G15),"."," ") | BD15: =IF(AND(BD$6>=$F15,BD$6<=$G15),"."," ") | BE15: =IF(AND(BE$6>=$F15,BE$6<=$G15),"."," ") | BF15: =IF(AND(BF$6>=$F15,BF$6<=$G15),"."," ") | BG15: =IF(AND(BG$6>=$F15,BG$6<=$G15),"."," ") | BJ15: =IF(AND(BJ$6>=$F15,BJ$6<=$G15),"."," ") | BK15: =IF(AND(BK$6>=$F15,BK$6<=$G15),"."," ") | BL15: =IF(AND(BL$6>=$F15,BL$6<=$G15),"."," ") | BM15: =IF(AND(BM$6>=$F15,BM$6<=$G15),"."," ") | BN15: =IF(AND(BN$6>=$F15,BN$6<=$G15),"."," ") | BQ15: =IF(AND(BQ$6>=$F15,BQ$6<=$G15),"."," ") | BR15: =IF(AND(BR$6>=$F15,BR$6<=$G15),"."," ") | BS15: =IF(AND(BS$6>=$F15,BS$6<=$G15),"."," ") | BT15: =IF(AND(BT$6>=$F15,BT$6<=$G15),"."," ") | BU15: =IF(AND(BU$6>=$F15,BU$6<=$G15),"."," ") | BX15: =IF(AND(BX$6>=$F15,BX$6<=$G15),"."," ") | BY15: =IF(AND(BY$6>=$F15,BY$6<=$G15),"."," ") | BZ15: =IF(AND(BZ$6>=$F15,BZ$6<=$G15),"."," ") | CA15: =IF(AND(CA$6>=$F15,CA$6<=$G15),"."," ") | CB15: =IF(AND(CB$6>=$F15,CB$6<=$G15),"."," ") | CE15: =IF(AND(CE$6>=$F15,CE$6<=$G15),"."," ") | CF15: =IF(AND(CF$6>=$F15,CF$6<=$G15),"."," ") | CG15: =IF(AND(CG$6>=$F15,CG$6<=$G15),"."," ") | CH15: =IF(AND(CH$6>=$F15,CH$6<=$G15),"."," ") | CI15: =IF(AND(CI$6>=$F15,CI$6<=$G15),"."," ") | CL15: =IF(AND(CL$6>=$F15,CL$6<=$G15),"."," ") | CM15: =IF(AND(CM$6>=$F15,CM$6<=$G15),"."," ") | CN15: =IF(AND(CN$6>=$F15,CN$6<=$G15),"."," ") | CO15: =IF(AND(CO$6>=$F15,CO$6<=$G15),"."," ") | CP15: =IF(AND(CP$6>=$F15,CP$6<=$G15),"."," ") | CS15: =IF(AND(CS$6>=$F15,CS$6<=$G15),"."," ") | CT15: =IF(AND(CT$6>=$F15,CT$6<=$G15),"."," ") | CU15: =IF(AND(CU$6>=$F15,CU$6<=$G15),"."," ") | CV15: =IF(AND(CV$6>=$F15,CV$6<=$G15),"."," ") | CW15: =IF(AND(CW$6>=$F15,CW$6<=$G15),"."," ") | CZ15: =IF(AND(CZ$6>=$F15,CZ$6<=$G15),"."," ") | DA15: =IF(AND(DA$6>=$F15,DA$6<=$G15),"."," ") | DB15: =IF(AND(DB$6>=$F15,DB$6<=$G15),"."," ") | DC15: =IF(AND(DC$6>=$F15,DC$6<=$G15),"."," ") | DD15: =IF(AND(DD$6>=$F15,DD$6<=$G15),"."," ") | DG15: =IF(AND(DG$6>=$F15,DG$6<=$G15),"."," ") | DH15: =IF(AND(DH$6>=$F15,DH$6<=$G15),"."," ") | DI15: =IF(AND(DI$6>=$F15,DI$6<=$G15),"."," ") | DJ15: =IF(AND(DJ$6>=$F15,DJ$6<=$G15),"."," ") | DK15: =IF(AND(DK$6>=$F15,DK$6<=$G15),"."," ") | DN15: =IF(AND(DN$6>=$F15,DN$6<=$G15),"."," ") | DO15: =IF(AND(DO$6>=$F15,DO$6<=$G15),"."," ") | DP15: =IF(AND(DP$6>=$F15,DP$6<=$G15),"."," ") | DQ15: =IF(AND(DQ$6>=$F15,DQ$6<=$G15),"."," ") | DR15: =IF(AND(DR$6>=$F15,DR$6<=$G15),"."," ") | DU15: =IF(AND(DU$6>=$F15,DU$6<=$G15),"."," ") | DV15: =IF(AND(DV$6>=$F15,DV$6<=$G15),"."," ") | DW15: =IF(AND(DW$6>=$F15,DW$6<=$G15),"."," ") | DX15: =IF(AND(DX$6>=$F15,DX$6<=$G15),"."," ") | DY15: =IF(AND(DY$6>=$F15,DY$6<=$G15),"."," ") | EB15: =IF(AND(EB$6>=$F15,EB$6<=$G15),"."," ") | EC15: =IF(AND(EC$6>=$F15,EC$6<=$G15),"."," ") | ED15: =IF(AND(ED$6>=$F15,ED$6<=$G15),"."," ") | EE15: =IF(AND(EE$6>=$F15,EE$6<=$G15),"."," ") | EF15: =IF(AND(EF$6>=$F15,EF$6<=$G15),"."," ") | EI15: =IF(AND(EI$6>=$F15,EI$6<=$G15),"."," ") | EJ15: =IF(AND(EJ$6>=$F15,EJ$6<=$G15),"."," ") | EK15: =IF(AND(EK$6>=$F15,EK$6<=$G15),"."," ") | EL15: =IF(AND(EL$6>=$F15,EL$6<=$G15),"."," ") | EM15: =IF(AND(EM$6>=$F15,EM$6<=$G15),"."," ") | EP15: =IF(AND(EP$6>=$F15,EP$6<=$G15),"."," ") | EQ15: =IF(AND(EQ$6>=$F15,EQ$6<=$G15),"."," ") | ER15: =IF(AND(ER$6>=$F15,ER$6<=$G15),"."," ") | ES15: =IF(AND(ES$6>=$F15,ES$6<=$G15),"."," ") | ET15: =IF(AND(ET$6>=$F15,ET$6<=$G15),"."," ") | EW15: =IF(AND(EW$6>=$F15,EW$6<=$G15),"."," ") | EX15: =IF(AND(EX$6>=$F15,EX$6<=$G15),"."," ") | EY15: =IF(AND(EY$6>=$F15,EY$6<=$G15),"."," ") | EZ15: =IF(AND(EZ$6>=$F15,EZ$6<=$G15),"."," ") | FA15: =IF(AND(FA$6>=$F15,FA$6<=$G15),"."," ") | FD15: =IF(AND(FD$6>=$F15,FD$6<=$G15),"."," ") | FE15: =IF(AND(FE$6>=$F15,FE$6<=$G15),"."," ") | FF15: =IF(AND(FF$6>=$F15,FF$6<=$G15),"."," ") | FG15: =IF(AND(FG$6>=$F15,FG$6<=$G15),"."," ") | FH15: =IF(AND(FH$6>=$F15,FH$6<=$G15),"."," ") | FK15: =IF(AND(FK$6>=$F15,FK$6<=$G15),"."," ") | FL15: =IF(AND(FL$6>=$F15,FL$6<=$G15),"."," ") | FM15: =IF(AND(FM$6>=$F15,FM$6<=$G15),"."," ") | FN15: =IF(AND(FN$6>=$F15,FN$6<=$G15),"."," ") | FO15: =IF(AND(FO$6>=$F15,FO$6<=$G15),"."," ") | FR15: =IF(AND(FR$6>=$F15,FR$6<=$G15),"."," ") | FS15: =IF(AND(FS$6>=$F15,FS$6<=$G15),"."," ") | FT15: =IF(AND(FT$6>=$F15,FT$6<=$G15),"."," ") | FU15: =IF(AND(FU$6>=$F15,FU$6<=$G15),"."," ") | FV15: =IF(AND(FV$6>=$F15,FV$6<=$G15),"."," ") | FY15: =IF(AND(FY$6>=$F15,FY$6<=$G15),"."," ") | FZ15: =IF(AND(FZ$6>=$F15,FZ$6<=$G15),"."," ") | GA15: =IF(AND(GA$6>=$F15,GA$6<=$G15),"."," ") | GB15: =IF(AND(GB$6>=$F15,GB$6<=$G15),"."," ") | GC15: =IF(AND(GC$6>=$F15,GC$6<=$G15),"."," ") | GF15: =IF(AND(GF$6>=$F15,GF$6<=$G15),"."," ") | GG15: =IF(AND(GG$6>=$F15,GG$6<=$G15),"."," ") | GH15: =IF(AND(GH$6>=$F15,GH$6<=$G15),"."," ") | GI15: =IF(AND(GI$6>=$F15,GI$6<=$G15),"."," ") | GJ15: =IF(AND(GJ$6>=$F15,GJ$6<=$G15),"."," ") | GM15: =IF(AND(GM$6>=$F15,GM$6<=$G15),"."," ") | GN15: =IF(AND(GN$6>=$F15,GN$6<=$G15),"."," ") | GO15: =IF(AND(GO$6>=$F15,GO$6<=$G15),"."," ") | GP15: =IF(AND(GP$6>=$F15,GP$6<=$G15),"."," ") | GQ15: =IF(AND(GQ$6>=$F15,GQ$6<=$G15),"."," ") | GT15: =IF(AND(GT$6>=$F15,GT$6<=$G15),"."," ") | GU15: =IF(AND(GU$6>=$F15,GU$6<=$G15),"."," ") | GV15: =IF(AND(GV$6>=$F15,GV$6<=$G15),"."," ") | GW15: =IF(AND(GW$6>=$F15,GW$6<=$G15),"."," ") | GX15: =IF(AND(GX$6>=$F15,GX$6<=$G15),"."," ") | HA15: =IF(AND(HA$6>=$F15,HA$6<=$G15),"."," ") | HB15: =IF(AND(HB$6>=$F15,HB$6<=$G15),"."," ") | HC15: =IF(AND(HC$6>=$F15,HC$6<=$G15),"."," ") | HD15: =IF(AND(HD$6>=$F15,HD$6<=$G15),"."," ") | HE15: =IF(AND(HE$6>=$F15,HE$6<=$G15),"."," ") | HH15: =IF(AND(HH$6>=$F15,HH$6<=$G15),"."," ") | HI15: =IF(AND(HI$6>=$F15,HI$6<=$G15),"."," ") | HJ15: =IF(AND(HJ$6>=$F15,HJ$6<=$G15),"."," ") | HK15: =IF(AND(HK$6>=$F15,HK$6<=$G15),"."," ") | HL15: =IF(AND(HL$6>=$F15,HL$6<=$G15),"."," ") | HO15: =IF(AND(HO$6>=$F15,HO$6<=$G15),"."," ") | HP15: =IF(AND(HP$6>=$F15,HP$6<=$G15),"."," ") | HQ15: =IF(AND(HQ$6>=$F15,HQ$6<=$G15),"."," ") | HR15: =IF(AND(HR$6>=$F15,HR$6<=$G15),"."," ") | HS15: =IF(AND(HS$6>=$F15,HS$6<=$G15),"."," ") | HV15: =IF(AND(HV$6>=$F15,HV$6<=$G15),"."," ") | HW15: =IF(AND(HW$6>=$F15,HW$6<=$G15),"."," ") | HX15: =IF(AND(HX$6>=$F15,HX$6<=$G15),"."," ") | HY15: =IF(AND(HY$6>=$F15,HY$6<=$G15),"."," ") | HZ15: =IF(AND(HZ$6>=$F15,HZ$6<=$G15),"."," ") | IC15: =IF(AND(IC$6>=$F15,IC$6<=$G15),"."," ") | ID15: =IF(AND(ID$6>=$F15,ID$6<=$G15),"."," ") | IE15: =IF(AND(IE$6>=$F15,IE$6<=$G15),"."," ") | IF15: =IF(AND(IF$6>=$F15,IF$6<=$G15),"."," ") | IG15: =IF(AND(IG$6>=$F15,IG$6<=$G15),"."," ") | IJ15: =IF(AND(IJ$6>=$F15,IJ$6<=$G15),"."," ") | IK15: =IF(AND(IK$6>=$F15,IK$6<=$G15),"."," ") | IL15: =IF(AND(IL$6>=$F15,IL$6<=$G15),"."," ") | IM15: =IF(AND(IM$6>=$F15,IM$6<=$G15),"."," ") | IN15: =IF(AND(IN$6>=$F15,IN$6<=$G15),"."," ") | IQ15: =IF(AND(IQ$6>=$F15,IQ$6<=$G15),"."," ") | IR15: =IF(AND(IR$6>=$F15,IR$6<=$G15),"."," ") | IS15: =IF(AND(IS$6>=$F15,IS$6<=$G15),"."," ") | IT15: =IF(AND(IT$6>=$F15,IT$6<=$G15),"."," ") | IU15: =IF(AND(IU$6>=$F15,IU$6<=$G15),"."," ") | IX15: =IF(AND(IX$6>=$F15,IX$6<=$G15),"."," ") | IY15: =IF(AND(IY$6>=$F15,IY$6<=$G15),"."," ") | IZ15: =IF(AND(IZ$6>=$F15,IZ$6<=$G15),"."," ") | JA15: =IF(AND(JA$6>=$F15,JA$6<=$G15),"."," ") | JB15: =IF(AND(JB$6>=$F15,JB$6<=$G15),"."," ") | JE15: =IF(AND(JE$6>=$F15,JE$6<=$G15),"."," ") | JF15: =IF(AND(JF$6>=$F15,JF$6<=$G15),"."," ") | JG15: =IF(AND(JG$6>=$F15,JG$6<=$G15),"."," ") | JH15: =IF(AND(JH$6>=$F15,JH$6<=$G15),"."," ") | JI15: =IF(AND(JI$6>=$F15,JI$6<=$G15),"."," ")
B16: 8 | C16: Detailed Design | D16: Mich | E16: 7 | F16: =VLOOKUP(E16,$B$6:$G$150,6,FALSE) + 1 -> 42521 | G16: =WORKDAY(F16,H16-1,Config!D15:D34) -> 42523 | H16: 3 | I16: 0.65 | J16: =IF(((NETWORKDAYS(F16,TODAY(),Data!C10:C29)*100)/H16)/100 > 0,((NETWORKDAYS(F16,TODAY(),Data!C10:C29)*100)/H16)/100,0) -> 551.33333 | K16: =IF(J16>1, "100%",$J16) -> 100% | L16: =K16-I16 -> 0.35 | M16: =IF(AND(M$6>=$F16,M$6<=$G16),"."," ") | N16: =IF(AND(N$6>=$F16,N$6<=$G16),"."," ") | O16: =IF(AND(O$6>=$F16,O$6<=$G16),"."," ") | P16: =IF(AND(P$6>=$F16,P$6<=$G16),"."," ") | Q16: =IF(AND(Q$6>=$F16,Q$6<=$G16),"."," ") | T16: =IF(AND(T$6>=$F16,T$6<=$G16),"."," ") | U16: =IF(AND(U$6>=$F16,U$6<=$G16),"."," ") | V16: =IF(AND(V$6>=$F16,V$6<=$G16),"."," ") | W16: =IF(AND(W$6>=$F16,W$6<=$G16),"."," ") | X16: =IF(AND(X$6>=$F16,X$6<=$G16),"."," ") | AA16: =IF(AND(AA$6>=$F16,AA$6<=$G16),"."," ") | AB16: =IF(AND(AB$6>=$F16,AB$6<=$G16),"."," ") | AC16: =IF(AND(AC$6>=$F16,AC$6<=$G16),"."," ") | AD16: =IF(AND(AD$6>=$F16,AD$6<=$G16),"."," ") | AE16: =IF(AND(AE$6>=$F16,AE$6<=$G16),"."," ") | AH16: =IF(AND(AH$6>=$F16,AH$6<=$G16),"."," ") | AI16: =IF(AND(AI$6>=$F16,AI$6<=$G16),"."," ") | AJ16: =IF(AND(AJ$6>=$F16,AJ$6<=$G16),"."," ") | AK16: =IF(AND(AK$6>=$F16,AK$6<=$G16),"."," ") | AL16: =IF(AND(AL$6>=$F16,AL$6<=$G16),"."," ") | AO16: =IF(AND(AO$6>=$F16,AO$6<=$G16),"."," ") -> . | AP16: =IF(AND(AP$6>=$F16,AP$6<=$G16),"."," ") | AQ16: =IF(AND(AQ$6>=$F16,AQ$6<=$G16),"."," ") | AR16: =IF(AND(AR$6>=$F16,AR$6<=$G16),"."," ") | AS16: =IF(AND(AS$6>=$F16,AS$6<=$G16),"."," ") | AV16: =IF(AND(AV$6>=$F16,AV$6<=$G16),"."," ") | AW16: =IF(AND(AW$6>=$F16,AW$6<=$G16),"."," ") | AX16: =IF(AND(AX$6>=$F16,AX$6<=$G16),"."," ") | AY16: =IF(AND(AY$6>=$F16,AY$6<=$G16),"."," ") | AZ16: =IF(AND(AZ$6>=$F16,AZ$6<=$G16),"."," ") | BC16: =IF(AND(BC$6>=$F16,BC$6<=$G16),"."," ") | BD16: =IF(AND(BD$6>=$F16,BD$6<=$G16),"."," ") | BE16: =IF(AND(BE$6>=$F16,BE$6<=$G16),"."," ") | BF16: =IF(AND(BF$6>=$F16,BF$6<=$G16),"."," ") | BG16: =IF(AND(BG$6>=$F16,BG$6<=$G16),"."," ") | BJ16: =IF(AND(BJ$6>=$F16,BJ$6<=$G16),"."," ") | BK16: =IF(AND(BK$6>=$F16,BK$6<=$G16),"."," ") | BL16: =IF(AND(BL$6>=$F16,BL$6<=$G16),"."," ") | BM16: =IF(AND(BM$6>=$F16,BM$6<=$G16),"."," ") | BN16: =IF(AND(BN$6>=$F16,BN$6<=$G16),"."," ") | BQ16: =IF(AND(BQ$6>=$F16,BQ$6<=$G16),"."," ") | BR16: =IF(AND(BR$6>=$F16,BR$6<=$G16),"."," ") | BS16: =IF(AND(BS$6>=$F16,BS$6<=$G16),"."," ") | BT16: =IF(AND(BT$6>=$F16,BT$6<=$G16),"."," ") | BU16: =IF(AND(BU$6>=$F16,BU$6<=$G16),"."," ") | BX16: =IF(AND(BX$6>=$F16,BX$6<=$G16),"."," ") | BY16: =IF(AND(BY$6>=$F16,BY$6<=$G16),"."," ") | BZ16: =IF(AND(BZ$6>=$F16,BZ$6<=$G16),"."," ") | CA16: =IF(AND(CA$6>=$F16,CA$6<=$G16),"."," ") | CB16: =IF(AND(CB$6>=$F16,CB$6<=$G16),"."," ") | CE16: =IF(AND(CE$6>=$F16,CE$6<=$G16),"."," ") | CF16: =IF(AND(CF$6>=$F16,CF$6<=$G16),"."," ") | CG16: =IF(AND(CG$6>=$F16,CG$6<=$G16),"."," ") | CH16: =IF(AND(CH$6>=$F16,CH$6<=$G16),"."," ") | CI16: =IF(AND(CI$6>=$F16,CI$6<=$G16),"."," ") | CL16: =IF(AND(CL$6>=$F16,CL$6<=$G16),"."," ") | CM16: =IF(AND(CM$6>=$F16,CM$6<=$G16),"."," ") | CN16: =IF(AND(CN$6>=$F16,CN$6<=$G16),"."," ") | CO16: =IF(AND(CO$6>=$F16,CO$6<=$G16),"."," ") | CP16: =IF(AND(CP$6>=$F16,CP$6<=$G16),"."," ") | CS16: =IF(AND(CS$6>=$F16,CS$6<=$G16),"."," ") | CT16: =IF(AND(CT$6>=$F16,CT$6<=$G16),"."," ") | CU16: =IF(AND(CU$6>=$F16,CU$6<=$G16),"."," ") | CV16: =IF(AND(CV$6>=$F16,CV$6<=$G16),"."," ") | CW16: =IF(AND(CW$6>=$F16,CW$6<=$G16),"."," ") | CZ16: =IF(AND(CZ$6>=$F16,CZ$6<=$G16),"."," ") | DA16: =IF(AND(DA$6>=$F16,DA$6<=$G16),"."," ") | DB16: =IF(AND(DB$6>=$F16,DB$6<=$G16),"."," ") | DC16: =IF(AND(DC$6>=$F16,DC$6<=$G16),"."," ") | DD16: =IF(AND(DD$6>=$F16,DD$6<=$G16),"."," ") | DG16: =IF(AND(DG$6>=$F16,DG$6<=$G16),"."," ") | DH16: =IF(AND(DH$6>=$F16,DH$6<=$G16),"."," ") | DI16: =IF(AND(DI$6>=$F16,DI$6<=$G16),"."," ") | DJ16: =IF(AND(DJ$6>=$F16,DJ$6<=$G16),"."," ") | DK16: =IF(AND(DK$6>=$F16,DK$6<=$G16),"."," ") | DN16: =IF(AND(DN$6>=$F16,DN$6<=$G16),"."," ") | DO16: =IF(AND(DO$6>=$F16,DO$6<=$G16),"."," ") | DP16: =IF(AND(DP$6>=$F16,DP$6<=$G16),"."," ") | DQ16: =IF(AND(DQ$6>=$F16,DQ$6<=$G16),"."," ") | DR16: =IF(AND(DR$6>=$F16,DR$6<=$G16),"."," ") | DU16: =IF(AND(DU$6>=$F16,DU$6<=$G16),"."," ") | DV16: =IF(AND(DV$6>=$F16,DV$6<=$G16),"."," ") | DW16: =IF(AND(DW$6>=$F16,DW$6<=$G16),"."," ") | DX16: =IF(AND(DX$6>=$F16,DX$6<=$G16),"."," ") | DY16: =IF(AND(DY$6>=$F16,DY$6<=$G16),"."," ") | EB16: =IF(AND(EB$6>=$F16,EB$6<=$G16),"."," ") | EC16: =IF(AND(EC$6>=$F16,EC$6<=$G16),"."," ") | ED16: =IF(AND(ED$6>=$F16,ED$6<=$G16),"."," ") | EE16: =IF(AND(EE$6>=$F16,EE$6<=$G16),"."," ") | EF16: =IF(AND(EF$6>=$F16,EF$6<=$G16),"."," ") | EI16: =IF(AND(EI$6>=$F16,EI$6<=$G16),"."," ") | EJ16: =IF(AND(EJ$6>=$F16,EJ$6<=$G16),"."," ") | EK16: =IF(AND(EK$6>=$F16,EK$6<=$G16),"."," ") | EL16: =IF(AND(EL$6>=$F16,EL$6<=$G16),"."," ") | EM16: =IF(AND(EM$6>=$F16,EM$6<=$G16),"."," ") | EP16: =IF(AND(EP$6>=$F16,EP$6<=$G16),"."," ") | EQ16: =IF(AND(EQ$6>=$F16,EQ$6<=$G16),"."," ") | ER16: =IF(AND(ER$6>=$F16,ER$6<=$G16),"."," ") | ES16: =IF(AND(ES$6>=$F16,ES$6<=$G16),"."," ") | ET16: =IF(AND(ET$6>=$F16,ET$6<=$G16),"."," ") | EW16: =IF(AND(EW$6>=$F16,EW$6<=$G16),"."," ") | EX16: =IF(AND(EX$6>=$F16,EX$6<=$G16),"."," ") | EY16: =IF(AND(EY$6>=$F16,EY$6<=$G16),"."," ") | EZ16: =IF(AND(EZ$6>=$F16,EZ$6<=$G16),"."," ") | FA16: =IF(AND(FA$6>=$F16,FA$6<=$G16),"."," ") | FD16: =IF(AND(FD$6>=$F16,FD$6<=$G16),"."," ") | FE16: =IF(AND(FE$6>=$F16,FE$6<=$G16),"."," ") | FF16: =IF(AND(FF$6>=$F16,FF$6<=$G16),"."," ") | FG16: =IF(AND(FG$6>=$F16,FG$6<=$G16),"."," ") | FH16: =IF(AND(FH$6>=$F16,FH$6<=$G16),"."," ") | FK16: =IF(AND(FK$6>=$F16,FK$6<=$G16),"."," ") | FL16: =IF(AND(FL$6>=$F16,FL$6<=$G16),"."," ") | FM16: =IF(AND(FM$6>=$F16,FM$6<=$G16),"."," ") | FN16: =IF(AND(FN$6>=$F16,FN$6<=$G16),"."," ") | FO16: =IF(AND(FO$6>=$F16,FO$6<=$G16),"."," ") | FR16: =IF(AND(FR$6>=$F16,FR$6<=$G16),"."," ") | FS16: =IF(AND(FS$6>=$F16,FS$6<=$G16),"."," ") | FT16: =IF(AND(FT$6>=$F16,FT$6<=$G16),"."," ") | FU16: =IF(AND(FU$6>=$F16,FU$6<=$G16),"."," ") | FV16: =IF(AND(FV$6>=$F16,FV$6<=$G16),"."," ") | FY16: =IF(AND(FY$6>=$F16,FY$6<=$G16),"."," ") | FZ16: =IF(AND(FZ$6>=$F16,FZ$6<=$G16),"."," ") | GA16: =IF(AND(GA$6>=$F16,GA$6<=$G16),"."," ") | GB16: =IF(AND(GB$6>=$F16,GB$6<=$G16),"."," ") | GC16: =IF(AND(GC$6>=$F16,GC$6<=$G16),"."," ") | GF16: =IF(AND(GF$6>=$F16,GF$6<=$G16),"."," ") | GG16: =IF(AND(GG$6>=$F16,GG$6<=$G16),"."," ") | GH16: =IF(AND(GH$6>=$F16,GH$6<=$G16),"."," ") | GI16: =IF(AND(GI$6>=$F16,GI$6<=$G16),"."," ") | GJ16: =IF(AND(GJ$6>=$F16,GJ$6<=$G16),"."," ") | GM16: =IF(AND(GM$6>=$F16,GM$6<=$G16),"."," ") | GN16: =IF(AND(GN$6>=$F16,GN$6<=$G16),"."," ") | GO16: =IF(AND(GO$6>=$F16,GO$6<=$G16),"."," ") | GP16: =IF(AND(GP$6>=$F16,GP$6<=$G16),"."," ") | GQ16: =IF(AND(GQ$6>=$F16,GQ$6<=$G16),"."," ") | GT16: =IF(AND(GT$6>=$F16,GT$6<=$G16),"."," ") | GU16: =IF(AND(GU$6>=$F16,GU$6<=$G16),"."," ") | GV16: =IF(AND(GV$6>=$F16,GV$6<=$G16),"."," ") | GW16: =IF(AND(GW$6>=$F16,GW$6<=$G16),"."," ") | GX16: =IF(AND(GX$6>=$F16,GX$6<=$G16),"."," ") | HA16: =IF(AND(HA$6>=$F16,HA$6<=$G16),"."," ") | HB16: =IF(AND(HB$6>=$F16,HB$6<=$G16),"."," ") | HC16: =IF(AND(HC$6>=$F16,HC$6<=$G16),"."," ") | HD16: =IF(AND(HD$6>=$F16,HD$6<=$G16),"."," ") | HE16: =IF(AND(HE$6>=$F16,HE$6<=$G16),"."," ") | HH16: =IF(AND(HH$6>=$F16,HH$6<=$G16),"."," ") | HI16: =IF(AND(HI$6>=$F16,HI$6<=$G16),"."," ") | HJ16: =IF(AND(HJ$6>=$F16,HJ$6<=$G16),"."," ") | HK16: =IF(AND(HK$6>=$F16,HK$6<=$G16),"."," ") | HL16: =IF(AND(HL$6>=$F16,HL$6<=$G16),"."," ") | HO16: =IF(AND(HO$6>=$F16,HO$6<=$G16),"."," ") | HP16: =IF(AND(HP$6>=$F16,HP$6<=$G16),"."," ") | HQ16: =IF(AND(HQ$6>=$F16,HQ$6<=$G16),"."," ") | HR16: =IF(AND(HR$6>=$F16,HR$6<=$G16),"."," ") | HS16: =IF(AND(HS$6>=$F16,HS$6<=$G16),"."," ") | HV16: =IF(AND(HV$6>=$F16,HV$6<=$G16),"."," ") | HW16: =IF(AND(HW$6>=$F16,HW$6<=$G16),"."," ") | HX16: =IF(AND(HX$6>=$F16,HX$6<=$G16),"."," ") | HY16: =IF(AND(HY$6>=$F16,HY$6<=$G16),"."," ") | HZ16: =IF(AND(HZ$6>=$F16,HZ$6<=$G16),"."," ") | IC16: =IF(AND(IC$6>=$F16,IC$6<=$G16),"."," ") | ID16: =IF(AND(ID$6>=$F16,ID$6<=$G16),"."," ") | IE16: =IF(AND(IE$6>=$F16,IE$6<=$G16),"."," ") | IF16: =IF(AND(IF$6>=$F16,IF$6<=$G16),"."," ") | IG16: =IF(AND(IG$6>=$F16,IG$6<=$G16),"."," ") | IJ16: =IF(AND(IJ$6>=$F16,IJ$6<=$G16),"."," ") | IK16: =IF(AND(IK$6>=$F16,IK$6<=$G16),"."," ") | IL16: =IF(AND(IL$6>=$F16,IL$6<=$G16),"."," ") | IM16: =IF(AND(IM$6>=$F16,IM$6<=$G16),"."," ") | IN16: =IF(AND(IN$6>=$F16,IN$6<=$G16),"."," ") | IQ16: =IF(AND(IQ$6>=$F16,IQ$6<=$G16),"."," ") | IR16: =IF(AND(IR$6>=$F16,IR$6<=$G16),"."," ") | IS16: =IF(AND(IS$6>=$F16,IS$6<=$G16),"."," ") | IT16: =IF(AND(IT$6>=$F16,IT$6<=$G16),"."," ") | IU16: =IF(AND(IU$6>=$F16,IU$6<=$G16),"."," ") | IX16: =IF(AND(IX$6>=$F16,IX$6<=$G16),"."," ") | IY16: =IF(AND(IY$6>=$F16,IY$6<=$G16),"."," ") | IZ16: =IF(AND(IZ$6>=$F16,IZ$6<=$G16),"."," ") | JA16: =IF(AND(JA$6>=$F16,JA$6<=$G16),"."," ") | JB16: =IF(AND(JB$6>=$F16,JB$6<=$G16),"."," ") | JE16: =IF(AND(JE$6>=$F16,JE$6<=$G16),"."," ") | JF16: =IF(AND(JF$6>=$F16,JF$6<=$G16),"."," ") | JG16: =IF(AND(JG$6>=$F16,JG$6<=$G16),"."," ") | JH16: =IF(AND(JH$6>=$F16,JH$6<=$G16),"."," ") | JI16: =IF(AND(JI$6>=$F16,JI$6<=$G16),"."," ")
B17: 9 | C17: Detailed Design Review | D17: Mich | E17: 8 | F17: =VLOOKUP(E17,$B$6:$G$150,6,FALSE) + 1 -> 42524 | G17: =WORKDAY(F17,H17-1,Config!D16:D35) -> 42527 | H17: 2 | I17: 0.56 | J17: =IF(((NETWORKDAYS(F17,TODAY(),Data!C11:C30)*100)/H17)/100 > 0,((NETWORKDAYS(F17,TODAY(),Data!C11:C30)*100)/H17)/100,0) -> 825.5 | K17: =IF(J17>1, "100%",$J17) -> 100% | L17: =K17-I17 -> 0.44 | M17: =IF(AND(M$6>=$F17,M$6<=$G17),"."," ") | N17: =IF(AND(N$6>=$F17,N$6<=$G17),"."," ") | O17: =IF(AND(O$6>=$F17,O$6<=$G17),"."," ") | P17: =IF(AND(P$6>=$F17,P$6<=$G17),"."," ") | Q17: =IF(AND(Q$6>=$F17,Q$6<=$G17),"."," ") | T17: =IF(AND(T$6>=$F17,T$6<=$G17),"."," ") | U17: =IF(AND(U$6>=$F17,U$6<=$G17),"."," ") | V17: =IF(AND(V$6>=$F17,V$6<=$G17),"."," ") | W17: =IF(AND(W$6>=$F17,W$6<=$G17),"."," ") | X17: =IF(AND(X$6>=$F17,X$6<=$G17),"."," ") | AA17: =IF(AND(AA$6>=$F17,AA$6<=$G17),"."," ") | AB17: =IF(AND(AB$6>=$F17,AB$6<=$G17),"."," ") | AC17: =IF(AND(AC$6>=$F17,AC$6<=$G17),"."," ") | AD17: =IF(AND(AD$6>=$F17,AD$6<=$G17),"."," ") | AE17: =IF(AND(AE$6>=$F17,AE$6<=$G17),"."," ") | AH17: =IF(AND(AH$6>=$F17,AH$6<=$G17),"."," ") | AI17: =IF(AND(AI$6>=$F17,AI$6<=$G17),"."," ") | AJ17: =IF(AND(AJ$6>=$F17,AJ$6<=$G17),"."," ") | AK17: =IF(AND(AK$6>=$F17,AK$6<=$G17),"."," ") | AL17: =IF(AND(AL$6>=$F17,AL$6<=$G17),"."," ") | AO17: =IF(AND(AO$6>=$F17,AO$6<=$G17),"."," ") | AP17: =IF(AND(AP$6>=$F17,AP$6<=$G17),"."," ") -> . | AQ17: =IF(AND(AQ$6>=$F17,AQ$6<=$G17),"."," ") -> . | AR17: =IF(AND(AR$6>=$F17,AR$6<=$G17),"."," ") -> . | AS17: =IF(AND(AS$6>=$F17,AS$6<=$G17),"."," ") -> . | AV17: =IF(AND(AV$6>=$F17,AV$6<=$G17),"."," ") | AW17: =IF(AND(AW$6>=$F17,AW$6<=$G17),"."," ") | AX17: =IF(AND(AX$6>=$F17,AX$6<=$G17),"."," ") | AY17: =IF(AND(AY$6>=$F17,AY$6<=$G17),"."," ") | AZ17: =IF(AND(AZ$6>=$F17,AZ$6<=$G17),"."," ") | BC17: =IF(AND(BC$6>=$F17,BC$6<=$G17),"."," ") | BD17: =IF(AND(BD$6>=$F17,BD$6<=$G17),"."," ") | BE17: =IF(AND(BE$6>=$F17,BE$6<=$G17),"."," ") | BF17: =IF(AND(BF$6>=$F17,BF$6<=$G17),"."," ") | BG17: =IF(AND(BG$6>=$F17,BG$6<=$G17),"."," ") | BJ17: =IF(AND(BJ$6>=$F17,BJ$6<=$G17),"."," ") | BK17: =IF(AND(BK$6>=$F17,BK$6<=$G17),"."," ") | BL17: =IF(AND(BL$6>=$F17,BL$6<=$G17),"."," ") | BM17: =IF(AND(BM$6>=$F17,BM$6<=$G17),"."," ") | BN17: =IF(AND(BN$6>=$F17,BN$6<=$G17),"."," ") | BQ17: =IF(AND(BQ$6>=$F17,BQ$6<=$G17),"."," ") | BR17: =IF(AND(BR$6>=$F17,BR$6<=$G17),"."," ") | BS17: =IF(AND(BS$6>=$F17,BS$6<=$G17),"."," ") | BT17: =IF(AND(BT$6>=$F17,BT$6<=$G17),"."," ") | BU17: =IF(AND(BU$6>=$F17,BU$6<=$G17),"."," ") | BX17: =IF(AND(BX$6>=$F17,BX$6<=$G17),"."," ") | BY17: =IF(AND(BY$6>=$F17,BY$6<=$G17),"."," ") | BZ17: =IF(AND(BZ$6>=$F17,BZ$6<=$G17),"."," ") | CA17: =IF(AND(CA$6>=$F17,CA$6<=$G17),"."," ") | CB17: =IF(AND(CB$6>=$F17,CB$6<=$G17),"."," ") | CE17: =IF(AND(CE$6>=$F17,CE$6<=$G17),"."," ") | CF17: =IF(AND(CF$6>=$F17,CF$6<=$G17),"."," ") | CG17: =IF(AND(CG$6>=$F17,CG$6<=$G17),"."," ") | CH17: =IF(AND(CH$6>=$F17,CH$6<=$G17),"."," ") | CI17: =IF(AND(CI$6>=$F17,CI$6<=$G17),"."," ") | CL17: =IF(AND(CL$6>=$F17,CL$6<=$G17),"."," ") | CM17: =IF(AND(CM$6>=$F17,CM$6<=$G17),"."," ") | CN17: =IF(AND(CN$6>=$F17,CN$6<=$G17),"."," ") | CO17: =IF(AND(CO$6>=$F17,CO$6<=$G17),"."," ") | CP17: =IF(AND(CP$6>=$F17,CP$6<=$G17),"."," ") | CS17: =IF(AND(CS$6>=$F17,CS$6<=$G17),"."," ") | CT17: =IF(AND(CT$6>=$F17,CT$6<=$G17),"."," ") | CU17: =IF(AND(CU$6>=$F17,CU$6<=$G17),"."," ") | CV17: =IF(AND(CV$6>=$F17,CV$6<=$G17),"."," ") | CW17: =IF(AND(CW$6>=$F17,CW$6<=$G17),"."," ") | CZ17: =IF(AND(CZ$6>=$F17,CZ$6<=$G17),"."," ") | DA17: =IF(AND(DA$6>=$F17,DA$6<=$G17),"."," ") | DB17: =IF(AND(DB$6>=$F17,DB$6<=$G17),"."," ") | DC17: =IF(AND(DC$6>=$F17,DC$6<=$G17),"."," ") | DD17: =IF(AND(DD$6>=$F17,DD$6<=$G17),"."," ") | DG17: =IF(AND(DG$6>=$F17,DG$6<=$G17),"."," ") | DH17: =IF(AND(DH$6>=$F17,DH$6<=$G17),"."," ") | DI17: =IF(AND(DI$6>=$F17,DI$6<=$G17),"."," ") | DJ17: =IF(AND(DJ$6>=$F17,DJ$6<=$G17),"."," ") | DK17: =IF(AND(DK$6>=$F17,DK$6<=$G17),"."," ") | DN17: =IF(AND(DN$6>=$F17,DN$6<=$G17),"."," ") | DO17: =IF(AND(DO$6>=$F17,DO$6<=$G17),"."," ") | DP17: =IF(AND(DP$6>=$F17,DP$6<=$G17),"."," ") | DQ17: =IF(AND(DQ$6>=$F17,DQ$6<=$G17),"."," ") | DR17: =IF(AND(DR$6>=$F17,DR$6<=$G17),"."," ") | DU17: =IF(AND(DU$6>=$F17,DU$6<=$G17),"."," ") | DV17: =IF(AND(DV$6>=$F17,DV$6<=$G17),"."," ") | DW17: =IF(AND(DW$6>=$F17,DW$6<=$G17),"."," ") | DX17: =IF(AND(DX$6>=$F17,DX$6<=$G17),"."," ") | DY17: =IF(AND(DY$6>=$F17,DY$6<=$G17),"."," ") | EB17: =IF(AND(EB$6>=$F17,EB$6<=$G17),"."," ") | EC17: =IF(AND(EC$6>=$F17,EC$6<=$G17),"."," ") | ED17: =IF(AND(ED$6>=$F17,ED$6<=$G17),"."," ") | EE17: =IF(AND(EE$6>=$F17,EE$6<=$G17),"."," ") | EF17: =IF(AND(EF$6>=$F17,EF$6<=$G17),"."," ") | EI17: =IF(AND(EI$6>=$F17,EI$6<=$G17),"."," ") | EJ17: =IF(AND(EJ$6>=$F17,EJ$6<=$G17),"."," ") | EK17: =IF(AND(EK$6>=$F17,EK$6<=$G17),"."," ") | EL17: =IF(AND(EL$6>=$F17,EL$6<=$G17),"."," ") | EM17: =IF(AND(EM$6>=$F17,EM$6<=$G17),"."," ") | EP17: =IF(AND(EP$6>=$F17,EP$6<=$G17),"."," ") | EQ17: =IF(AND(EQ$6>=$F17,EQ$6<=$G17),"."," ") | ER17: =IF(AND(ER$6>=$F17,ER$6<=$G17),"."," ") | ES17: =IF(AND(ES$6>=$F17,ES$6<=$G17),"."," ") | ET17: =IF(AND(ET$6>=$F17,ET$6<=$G17),"."," ") | EW17: =IF(AND(EW$6>=$F17,EW$6<=$G17),"."," ") | EX17: =IF(AND(EX$6>=$F17,EX$6<=$G17),"."," ") | EY17: =IF(AND(EY$6>=$F17,EY$6<=$G17),"."," ") | EZ17: =IF(AND(EZ$6>=$F17,EZ$6<=$G17),"."," ") | FA17: =IF(AND(FA$6>=$F17,FA$6<=$G17),"."," ") | FD17: =IF(AND(FD$6>=$F17,FD$6<=$G17),"."," ") | FE17: =IF(AND(FE$6>=$F17,FE$6<=$G17),"."," ") | FF17: =IF(AND(FF$6>=$F17,FF$6<=$G17),"."," ") | FG17: =IF(AND(FG$6>=$F17,FG$6<=$G17),"."," ") | FH17: =IF(AND(FH$6>=$F17,FH$6<=$G17),"."," ") | FK17: =IF(AND(FK$6>=$F17,FK$6<=$G17),"."," ") | FL17: =IF(AND(FL$6>=$F17,FL$6<=$G17),"."," ") | FM17: =IF(AND(FM$6>=$F17,FM$6<=$G17),"."," ") | FN17: =IF(AND(FN$6>=$F17,FN$6<=$G17),"."," ") | FO17: =IF(AND(FO$6>=$F17,FO$6<=$G17),"."," ") | FR17: =IF(AND(FR$6>=$F17,FR$6<=$G17),"."," ") | FS17: =IF(AND(FS$6>=$F17,FS$6<=$G17),"."," ") | FT17: =IF(AND(FT$6>=$F17,FT$6<=$G17),"."," ") | FU17: =IF(AND(FU$6>=$F17,FU$6<=$G17),"."," ") | FV17: =IF(AND(FV$6>=$F17,FV$6<=$G17),"."," ") | FY17: =IF(AND(FY$6>=$F17,FY$6<=$G17),"."," ") | FZ17: =IF(AND(FZ$6>=$F17,FZ$6<=$G17),"."," ") | GA17: =IF(AND(GA$6>=$F17,GA$6<=$G17),"."," ") | GB17: =IF(AND(GB$6>=$F17,GB$6<=$G17),"."," ") | GC17: =IF(AND(GC$6>=$F17,GC$6<=$G17),"."," ") | GF17: =IF(AND(GF$6>=$F17,GF$6<=$G17),"."," ") | GG17: =IF(AND(GG$6>=$F17,GG$6<=$G17),"."," ") | GH17: =IF(AND(GH$6>=$F17,GH$6<=$G17),"."," ") | GI17: =IF(AND(GI$6>=$F17,GI$6<=$G17),"."," ") | GJ17: =IF(AND(GJ$6>=$F17,GJ$6<=$G17),"."," ") | GM17: =IF(AND(GM$6>=$F17,GM$6<=$G17),"."," ") | GN17: =IF(AND(GN$6>=$F17,GN$6<=$G17),"."," ") | GO17: =IF(AND(GO$6>=$F17,GO$6<=$G17),"."," ") | GP17: =IF(AND(GP$6>=$F17,GP$6<=$G17),"."," ") | GQ17: =IF(AND(GQ$6>=$F17,GQ$6<=$G17),"."," ") | GT17: =IF(AND(GT$6>=$F17,GT$6<=$G17),"."," ") | GU17: =IF(AND(GU$6>=$F17,GU$6<=$G17),"."," ") | GV17: =IF(AND(GV$6>=$F17,GV$6<=$G17),"."," ") | GW17: =IF(AND(GW$6>=$F17,GW$6<=$G17),"."," ") | GX17: =IF(AND(GX$6>=$F17,GX$6<=$G17),"."," ") | HA17: =IF(AND(HA$6>=$F17,HA$6<=$G17),"."," ") | HB17: =IF(AND(HB$6>=$F17,HB$6<=$G17),"."," ") | HC17: =IF(AND(HC$6>=$F17,HC$6<=$G17),"."," ") | HD17: =IF(AND(HD$6>=$F17,HD$6<=$G17),"."," ") | HE17: =IF(AND(HE$6>=$F17,HE$6<=$G17),"."," ") | HH17: =IF(AND(HH$6>=$F17,HH$6<=$G17),"."," ") | HI17: =IF(AND(HI$6>=$F17,HI$6<=$G17),"."," ") | HJ17: =IF(AND(HJ$6>=$F17,HJ$6<=$G17),"."," ") | HK17: =IF(AND(HK$6>=$F17,HK$6<=$G17),"."," ") | HL17: =IF(AND(HL$6>=$F17,HL$6<=$G17),"."," ") | HO17: =IF(AND(HO$6>=$F17,HO$6<=$G17),"."," ") | HP17: =IF(AND(HP$6>=$F17,HP$6<=$G17),"."," ") | HQ17: =IF(AND(HQ$6>=$F17,HQ$6<=$G17),"."," ") | HR17: =IF(AND(HR$6>=$F17,HR$6<=$G17),"."," ") | HS17: =IF(AND(HS$6>=$F17,HS$6<=$G17),"."," ") | HV17: =IF(AND(HV$6>=$F17,HV$6<=$G17),"."," ") | HW17: =IF(AND(HW$6>=$F17,HW$6<=$G17),"."," ") | HX17: =IF(AND(HX$6>=$F17,HX$6<=$G17),"."," ") | HY17: =IF(AND(HY$6>=$F17,HY$6<=$G17),"."," ") | HZ17: =IF(AND(HZ$6>=$F17,HZ$6<=$G17),"."," ") | IC17: =IF(AND(IC$6>=$F17,IC$6<=$G17),"."," ") | ID17: =IF(AND(ID$6>=$F17,ID$6<=$G17),"."," ") | IE17: =IF(AND(IE$6>=$F17,IE$6<=$G17),"."," ") | IF17: =IF(AND(IF$6>=$F17,IF$6<=$G17),"."," ") | IG17: =IF(AND(IG$6>=$F17,IG$6<=$G17),"."," ") | IJ17: =IF(AND(IJ$6>=$F17,IJ$6<=$G17),"."," ") | IK17: =IF(AND(IK$6>=$F17,IK$6<=$G17),"."," ") | IL17: =IF(AND(IL$6>=$F17,IL$6<=$G17),"."," ") | IM17: =IF(AND(IM$6>=$F17,IM$6<=$G17),"."," ") | IN17: =IF(AND(IN$6>=$F17,IN$6<=$G17),"."," ") | IQ17: =IF(AND(IQ$6>=$F17,IQ$6<=$G17),"."," ") | IR17: =IF(AND(IR$6>=$F17,IR$6<=$G17),"."," ") | IS17: =IF(AND(IS$6>=$F17,IS$6<=$G17),"."," ") | IT17: =IF(AND(IT$6>=$F17,IT$6<=$G17),"."," ") | IU17: =IF(AND(IU$6>=$F17,IU$6<=$G17),"."," ") | IX17: =IF(AND(IX$6>=$F17,IX$6<=$G17),"."," ") | IY17: =IF(AND(IY$6>=$F17,IY$6<=$G17),"."," ") | IZ17: =IF(AND(IZ$6>=$F17,IZ$6<=$G17),"."," ") | JA17: =IF(AND(JA$6>=$F17,JA$6<=$G17),"."," ") | JB17: =IF(AND(JB$6>=$F17,JB$6<=$G17),"."," ") | JE17: =IF(AND(JE$6>=$F17,JE$6<=$G17),"."," ") | JF17: =IF(AND(JF$6>=$F17,JF$6<=$G17),"."," ") | JG17: =IF(AND(JG$6>=$F17,JG$6<=$G17),"."," ") | JH17: =IF(AND(JH$6>=$F17,JH$6<=$G17),"."," ") | JI17: =IF(AND(JI$6>=$F17,JI$6<=$G17),"."," ")
B18: 10 | C18: Design Sign Off | D18: Mich | E18: 9 | F18: =VLOOKUP(E18,$B$6:$G$150,6,FALSE) + 1 -> 42528 | G18: =WORKDAY(F18,H18-1,Config!D17:D36) -> 42528 | H18: 1 | I18: 0.78 | J18: =IF(((NETWORKDAYS(F18,TODAY(),Data!C12:C31)*100)/H18)/100 > 0,((NETWORKDAYS(F18,TODAY(),Data!C12:C31)*100)/H18)/100,0) -> 1649 | K18: =IF(J18>1, "100%",$J18) -> 100% | L18: =K18-I18 -> 0.22 | M18: =IF(AND(M$6>=$F18,M$6<=$G18),"."," ") | N18: =IF(AND(N$6>=$F18,N$6<=$G18),"."," ") | O18: =IF(AND(O$6>=$F18,O$6<=$G18),"."," ") | P18: =IF(AND(P$6>=$F18,P$6<=$G18),"."," ") | Q18: =IF(AND(Q$6>=$F18,Q$6<=$G18),"."," ") | T18: =IF(AND(T$6>=$F18,T$6<=$G18),"."," ") | U18: =IF(AND(U$6>=$F18,U$6<=$G18),"."," ") | V18: =IF(AND(V$6>=$F18,V$6<=$G18),"."," ") | W18: =IF(AND(W$6>=$F18,W$6<=$G18),"."," ") | X18: =IF(AND(X$6>=$F18,X$6<=$G18),"."," ") | AA18: =IF(AND(AA$6>=$F18,AA$6<=$G18),"."," ") | AB18: =IF(AND(AB$6>=$F18,AB$6<=$G18),"."," ") | AC18: =IF(AND(AC$6>=$F18,AC$6<=$G18),"."," ") | AD18: =IF(AND(AD$6>=$F18,AD$6<=$G18),"."," ") | AE18: =IF(AND(AE$6>=$F18,AE$6<=$G18),"."," ") | AH18: =IF(AND(AH$6>=$F18,AH$6<=$G18),"."," ") | AI18: =IF(AND(AI$6>=$F18,AI$6<=$G18),"."," ") | AJ18: =IF(AND(AJ$6>=$F18,AJ$6<=$G18),"."," ") | AK18: =IF(AND(AK$6>=$F18,AK$6<=$G18),"."," ") | AL18: =IF(AND(AL$6>=$F18,AL$6<=$G18),"."," ") | AO18: =IF(AND(AO$6>=$F18,AO$6<=$G18),"."," ") | AP18: =IF(AND(AP$6>=$F18,AP$6<=$G18),"."," ") | AQ18: =IF(AND(AQ$6>=$F18,AQ$6<=$G18),"."," ") | AR18: =IF(AND(AR$6>=$F18,AR$6<=$G18),"."," ") | AS18: =IF(AND(AS$6>=$F18,AS$6<=$G18),"."," ") | AV18: =IF(AND(AV$6>=$F18,AV$6<=$G18),"."," ") | AW18: =IF(AND(AW$6>=$F18,AW$6<=$G18),"."," ") | AX18: =IF(AND(AX$6>=$F18,AX$6<=$G18),"."," ") | AY18: =IF(AND(AY$6>=$F18,AY$6<=$G18),"."," ") | AZ18: =IF(AND(AZ$6>=$F18,AZ$6<=$G18),"."," ") | BC18: =IF(AND(BC$6>=$F18,BC$6<=$G18),"."," ") | BD18: =IF(AND(BD$6>=$F18,BD$6<=$G18),"."," ") | BE18: =IF(AND(BE$6>=$F18,BE$6<=$G18),"."," ") | BF18: =IF(AND(BF$6>=$F18,BF$6<=$G18),"."," ") | BG18: =IF(AND(BG$6>=$F18,BG$6<=$G18),"."," ") | BJ18: =IF(AND(BJ$6>=$F18,BJ$6<=$G18),"."," ") | BK18: =IF(AND(BK$6>=$F18,BK$6<=$G18),"."," ") | BL18: =IF(AND(BL$6>=$F18,BL$6<=$G18),"."," ") | BM18: =IF(AND(BM$6>=$F18,BM$6<=$G18),"."," ") | BN18: =IF(AND(BN$6>=$F18,BN$6<=$G18),"."," ") | BQ18: =IF(AND(BQ$6>=$F18,BQ$6<=$G18),"."," ") | BR18: =IF(AND(BR$6>=$F18,BR$6<=$G18),"."," ") | BS18: =IF(AND(BS$6>=$F18,BS$6<=$G18),"."," ") | BT18: =IF(AND(BT$6>=$F18,BT$6<=$G18),"."," ") | BU18: =IF(AND(BU$6>=$F18,BU$6<=$G18),"."," ") | BX18: =IF(AND(BX$6>=$F18,BX$6<=$G18),"."," ") | BY18: =IF(AND(BY$6>=$F18,BY$6<=$G18),"."," ") | BZ18: =IF(AND(BZ$6>=$F18,BZ$6<=$G18),"."," ") | CA18: =IF(AND(CA$6>=$F18,CA$6<=$G18),"."," ") | CB18: =IF(AND(CB$6>=$F18,CB$6<=$G18),"."," ") | CE18: =IF(AND(CE$6>=$F18,CE$6<=$G18),"."," ") | CF18: =IF(AND(CF$6>=$F18,CF$6<=$G18),"."," ") | CG18: =IF(AND(CG$6>=$F18,CG$6<=$G18),"."," ") | CH18: =IF(AND(CH$6>=$F18,CH$6<=$G18),"."," ") | CI18: =IF(AND(CI$6>=$F18,CI$6<=$G18),"."," ") | CL18: =IF(AND(CL$6>=$F18,CL$6<=$G18),"."," ") | CM18: =IF(AND(CM$6>=$F18,CM$6<=$G18),"."," ") | CN18: =IF(AND(CN$6>=$F18,CN$6<=$G18),"."," ") | CO18: =IF(AND(CO$6>=$F18,CO$6<=$G18),"."," ") | CP18: =IF(AND(CP$6>=$F18,CP$6<=$G18),"."," ") | CS18: =IF(AND(CS$6>=$F18,CS$6<=$G18),"."," ") | CT18: =IF(AND(CT$6>=$F18,CT$6<=$G18),"."," ") | CU18: =IF(AND(CU$6>=$F18,CU$6<=$G18),"."," ") | CV18: =IF(AND(CV$6>=$F18,CV$6<=$G18),"."," ") | CW18: =IF(AND(CW$6>=$F18,CW$6<=$G18),"."," ") | CZ18: =IF(AND(CZ$6>=$F18,CZ$6<=$G18),"."," ") | DA18: =IF(AND(DA$6>=$F18,DA$6<=$G18),"."," ") | DB18: =IF(AND(DB$6>=$F18,DB$6<=$G18),"."," ") | DC18: =IF(AND(DC$6>=$F18,DC$6<=$G18),"."," ") | DD18: =IF(AND(DD$6>=$F18,DD$6<=$G18),"."," ") | DG18: =IF(AND(DG$6>=$F18,DG$6<=$G18),"."," ") | DH18: =IF(AND(DH$6>=$F18,DH$6<=$G18),"."," ") | DI18: =IF(AND(DI$6>=$F18,DI$6<=$G18),"."," ") | DJ18: =IF(AND(DJ$6>=$F18,DJ$6<=$G18),"."," ") | DK18: =IF(AND(DK$6>=$F18,DK$6<=$G18),"."," ") | DN18: =IF(AND(DN$6>=$F18,DN$6<=$G18),"."," ") | DO18: =IF(AND(DO$6>=$F18,DO$6<=$G18),"."," ") | DP18: =IF(AND(DP$6>=$F18,DP$6<=$G18),"."," ") | DQ18: =IF(AND(DQ$6>=$F18,DQ$6<=$G18),"."," ") | DR18: =IF(AND(DR$6>=$F18,DR$6<=$G18),"."," ") | DU18: =IF(AND(DU$6>=$F18,DU$6<=$G18),"."," ") | DV18: =IF(AND(DV$6>=$F18,DV$6<=$G18),"."," ") | DW18: =IF(AND(DW$6>=$F18,DW$6<=$G18),"."," ") | DX18: =IF(AND(DX$6>=$F18,DX$6<=$G18),"."," ") | DY18: =IF(AND(DY$6>=$F18,DY$6<=$G18),"."," ") | EB18: =IF(AND(EB$6>=$F18,EB$6<=$G18),"."," ") | EC18: =IF(AND(EC$6>=$F18,EC$6<=$G18),"."," ") | ED18: =IF(AND(ED$6>=$F18,ED$6<=$G18),"."," ") | EE18: =IF(AND(EE$6>=$F18,EE$6<=$G18),"."," ") | EF18: =IF(AND(EF$6>=$F18,EF$6<=$G18),"."," ") | EI18: =IF(AND(EI$6>=$F18,EI$6<=$G18),"."," ") | EJ18: =IF(AND(EJ$6>=$F18,EJ$6<=$G18),"."," ") | EK18: =IF(AND(EK$6>=$F18,EK$6<=$G18),"."," ") | EL18: =IF(AND(EL$6>=$F18,EL$6<=$G18),"."," ") | EM18: =IF(AND(EM$6>=$F18,EM$6<=$G18),"."," ") | EP18: =IF(AND(EP$6>=$F18,EP$6<=$G18),"."," ") | EQ18: =IF(AND(EQ$6>=$F18,EQ$6<=$G18),"."," ") | ER18: =IF(AND(ER$6>=$F18,ER$6<=$G18),"."," ") | ES18: =IF(AND(ES$6>=$F18,ES$6<=$G18),"."," ") | ET18: =IF(AND(ET$6>=$F18,ET$6<=$G18),"."," ") | EW18: =IF(AND(EW$6>=$F18,EW$6<=$G18),"."," ") | EX18: =IF(AND(EX$6>=$F18,EX$6<=$G18),"."," ") | EY18: =IF(AND(EY$6>=$F18,EY$6<=$G18),"."," ") | EZ18: =IF(AND(EZ$6>=$F18,EZ$6<=$G18),"."," ") | FA18: =IF(AND(FA$6>=$F18,FA$6<=$G18),"."," ") | FD18: =IF(AND(FD$6>=$F18,FD$6<=$G18),"."," ") | FE18: =IF(AND(FE$6>=$F18,FE$6<=$G18),"."," ") | FF18: =IF(AND(FF$6>=$F18,FF$6<=$G18),"."," ") | FG18: =IF(AND(FG$6>=$F18,FG$6<=$G18),"."," ") | FH18: =IF(AND(FH$6>=$F18,FH$6<=$G18),"."," ") | FK18: =IF(AND(FK$6>=$F18,FK$6<=$G18),"."," ") | FL18: =IF(AND(FL$6>=$F18,FL$6<=$G18),"."," ") | FM18: =IF(AND(FM$6>=$F18,FM$6<=$G18),"."," ") | FN18: =IF(AND(FN$6>=$F18,FN$6<=$G18),"."," ") | FO18: =IF(AND(FO$6>=$F18,FO$6<=$G18),"."," ") | FR18: =IF(AND(FR$6>=$F18,FR$6<=$G18),"."," ") | FS18: =IF(AND(FS$6>=$F18,FS$6<=$G18),"."," ") | FT18: =IF(AND(FT$6>=$F18,FT$6<=$G18),"."," ") | FU18: =IF(AND(FU$6>=$F18,FU$6<=$G18),"."," ") | FV18: =IF(AND(FV$6>=$F18,FV$6<=$G18),"."," ") | FY18: =IF(AND(FY$6>=$F18,FY$6<=$G18),"."," ") | FZ18: =IF(AND(FZ$6>=$F18,FZ$6<=$G18),"."," ") | GA18: =IF(AND(GA$6>=$F18,GA$6<=$G18),"."," ") | GB18: =IF(AND(GB$6>=$F18,GB$6<=$G18),"."," ") | GC18: =IF(AND(GC$6>=$F18,GC$6<=$G18),"."," ") | GF18: =IF(AND(GF$6>=$F18,GF$6<=$G18),"."," ") | GG18: =IF(AND(GG$6>=$F18,GG$6<=$G18),"."," ") | GH18: =IF(AND(GH$6>=$F18,GH$6<=$G18),"."," ") | GI18: =IF(AND(GI$6>=$F18,GI$6<=$G18),"."," ") | GJ18: =IF(AND(GJ$6>=$F18,GJ$6<=$G18),"."," ") | GM18: =IF(AND(GM$6>=$F18,GM$6<=$G18),"."," ") | GN18: =IF(AND(GN$6>=$F18,GN$6<=$G18),"."," ") | GO18: =IF(AND(GO$6>=$F18,GO$6<=$G18),"."," ") | GP18: =IF(AND(GP$6>=$F18,GP$6<=$G18),"."," ") | GQ18: =IF(AND(GQ$6>=$F18,GQ$6<=$G18),"."," ") | GT18: =IF(AND(GT$6>=$F18,GT$6<=$G18),"."," ") | GU18: =IF(AND(GU$6>=$F18,GU$6<=$G18),"."," ") | GV18: =IF(AND(GV$6>=$F18,GV$6<=$G18),"."," ") | GW18: =IF(AND(GW$6>=$F18,GW$6<=$G18),"."," ") | GX18: =IF(AND(GX$6>=$F18,GX$6<=$G18),"."," ") | HA18: =IF(AND(HA$6>=$F18,HA$6<=$G18),"."," ") | HB18: =IF(AND(HB$6>=$F18,HB$6<=$G18),"."," ") | HC18: =IF(AND(HC$6>=$F18,HC$6<=$G18),"."," ") | HD18: =IF(AND(HD$6>=$F18,HD$6<=$G18),"."," ") | HE18: =IF(AND(HE$6>=$F18,HE$6<=$G18),"."," ") | HH18: =IF(AND(HH$6>=$F18,HH$6<=$G18),"."," ") | HI18: =IF(AND(HI$6>=$F18,HI$6<=$G18),"."," ") | HJ18: =IF(AND(HJ$6>=$F18,HJ$6<=$G18),"."," ") | HK18: =IF(AND(HK$6>=$F18,HK$6<=$G18),"."," ") | HL18: =IF(AND(HL$6>=$F18,HL$6<=$G18),"."," ") | HO18: =IF(AND(HO$6>=$F18,HO$6<=$G18),"."," ") | HP18: =IF(AND(HP$6>=$F18,HP$6<=$G18),"."," ") | HQ18: =IF(AND(HQ$6>=$F18,HQ$6<=$G18),"."," ") | HR18: =IF(AND(HR$6>=$F18,HR$6<=$G18),"."," ") | HS18: =IF(AND(HS$6>=$F18,HS$6<=$G18),"."," ") | HV18: =IF(AND(HV$6>=$F18,HV$6<=$G18),"."," ") | HW18: =IF(AND(HW$6>=$F18,HW$6<=$G18),"."," ") | HX18: =IF(AND(HX$6>=$F18,HX$6<=$G18),"."," ") | HY18: =IF(AND(HY$6>=$F18,HY$6<=$G18),"."," ") | HZ18: =IF(AND(HZ$6>=$F18,HZ$6<=$G18),"."," ") | IC18: =IF(AND(IC$6>=$F18,IC$6<=$G18),"."," ") | ID18: =IF(AND(ID$6>=$F18,ID$6<=$G18),"."," ") | IE18: =IF(AND(IE$6>=$F18,IE$6<=$G18),"."," ") | IF18: =IF(AND(IF$6>=$F18,IF$6<=$G18),"."," ") | IG18: =IF(AND(IG$6>=$F18,IG$6<=$G18),"."," ") | IJ18: =IF(AND(IJ$6>=$F18,IJ$6<=$G18),"."," ") | IK18: =IF(AND(IK$6>=$F18,IK$6<=$G18),"."," ") | IL18: =IF(AND(IL$6>=$F18,IL$6<=$G18),"."," ") | IM18: =IF(AND(IM$6>=$F18,IM$6<=$G18),"."," ") | IN18: =IF(AND(IN$6>=$F18,IN$6<=$G18),"."," ") | IQ18: =IF(AND(IQ$6>=$F18,IQ$6<=$G18),"."," ") | IR18: =IF(AND(IR$6>=$F18,IR$6<=$G18),"."," ") | IS18: =IF(AND(IS$6>=$F18,IS$6<=$G18),"."," ") | IT18: =IF(AND(IT$6>=$F18,IT$6<=$G18),"."," ") | IU18: =IF(AND(IU$6>=$F18,IU$6<=$G18),"."," ") | IX18: =IF(AND(IX$6>=$F18,IX$6<=$G18),"."," ") | IY18: =IF(AND(IY$6>=$F18,IY$6<=$G18),"."," ") | IZ18: =IF(AND(IZ$6>=$F18,IZ$6<=$G18),"."," ") | JA18: =IF(AND(JA$6>=$F18,JA$6<=$G18),"."," ") | JB18: =IF(AND(JB$6>=$F18,JB$6<=$G18),"."," ") | JE18: =IF(AND(JE$6>=$F18,JE$6<=$G18),"."," ") | JF18: =IF(AND(JF$6>=$F18,JF$6<=$G18),"."," ") | JG18: =IF(AND(JG$6>=$F18,JG$6<=$G18),"."," ") | JH18: =IF(AND(JH$6>=$F18,JH$6<=$G18),"."," ") | JI18: =IF(AND(JI$6>=$F18,JI$6<=$G18),"."," ")
B19: 11 | C19: Design Review | D19: Mich | E19: 10 | F19: =VLOOKUP(E19,$B$6:$G$150,6,FALSE) + 1 -> 42529 | G19: =WORKDAY(F19,H19-1,Config!D17:D36) -> 42530 | H19: 2 | I19: 0.23 | J19: =IF(((NETWORKDAYS(F19,TODAY(),Data!C13:C32)*100)/H19)/100 > 0,((NETWORKDAYS(F19,TODAY(),Data!C13:C32)*100)/H19)/100,0) -> 824 | K19: =IF(J19>1, "100%",$J19) -> 100% | L19: =K19-I19 -> 0.77 | M19: =IF(AND(M$6>=$F19,M$6<=$G19),"."," ") | N19: =IF(AND(N$6>=$F19,N$6<=$G19),"."," ") | O19: =IF(AND(O$6>=$F19,O$6<=$G19),"."," ") | P19: =IF(AND(P$6>=$F19,P$6<=$G19),"."," ") | Q19: =IF(AND(Q$6>=$F19,Q$6<=$G19),"."," ") | T19: =IF(AND(T$6>=$F19,T$6<=$G19),"."," ") | U19: =IF(AND(U$6>=$F19,U$6<=$G19),"."," ") | V19: =IF(AND(V$6>=$F19,V$6<=$G19),"."," ") | W19: =IF(AND(W$6>=$F19,W$6<=$G19),"."," ") | X19: =IF(AND(X$6>=$F19,X$6<=$G19),"."," ") | AA19: =IF(AND(AA$6>=$F19,AA$6<=$G19),"."," ") | AB19: =IF(AND(AB$6>=$F19,AB$6<=$G19),"."," ") | AC19: =IF(AND(AC$6>=$F19,AC$6<=$G19),"."," ") | AD19: =IF(AND(AD$6>=$F19,AD$6<=$G19),"."," ") | AE19: =IF(AND(AE$6>=$F19,AE$6<=$G19),"."," ") | AH19: =IF(AND(AH$6>=$F19,AH$6<=$G19),"."," ") | AI19: =IF(AND(AI$6>=$F19,AI$6<=$G19),"."," ") | AJ19: =IF(AND(AJ$6>=$F19,AJ$6<=$G19),"."," ") | AK19: =IF(AND(AK$6>=$F19,AK$6<=$G19),"."," ") | AL19: =IF(AND(AL$6>=$F19,AL$6<=$G19),"."," ") | AO19: =IF(AND(AO$6>=$F19,AO$6<=$G19),"."," ") | AP19: =IF(AND(AP$6>=$F19,AP$6<=$G19),"."," ") | AQ19: =IF(AND(AQ$6>=$F19,AQ$6<=$G19),"."," ") | AR19: =IF(AND(AR$6>=$F19,AR$6<=$G19),"."," ") | AS19: =IF(AND(AS$6>=$F19,AS$6<=$G19),"."," ") | AV19: =IF(AND(AV$6>=$F19,AV$6<=$G19),"."," ") -> . | AW19: =IF(AND(AW$6>=$F19,AW$6<=$G19),"."," ") | AX19: =IF(AND(AX$6>=$F19,AX$6<=$G19),"."," ") | AY19: =IF(AND(AY$6>=$F19,AY$6<=$G19),"."," ") | AZ19: =IF(AND(AZ$6>=$F19,AZ$6<=$G19),"."," ") | BC19: =IF(AND(BC$6>=$F19,BC$6<=$G19),"."," ") | BD19: =IF(AND(BD$6>=$F19,BD$6<=$G19),"."," ") | BE19: =IF(AND(BE$6>=$F19,BE$6<=$G19),"."," ") | BF19: =IF(AND(BF$6>=$F19,BF$6<=$G19),"."," ") | BG19: =IF(AND(BG$6>=$F19,BG$6<=$G19),"."," ") | BJ19: =IF(AND(BJ$6>=$F19,BJ$6<=$G19),"."," ") | BK19: =IF(AND(BK$6>=$F19,BK$6<=$G19),"."," ") | BL19: =IF(AND(BL$6>=$F19,BL$6<=$G19),"."," ") | BM19: =IF(AND(BM$6>=$F19,BM$6<=$G19),"."," ") | BN19: =IF(AND(BN$6>=$F19,BN$6<=$G19),"."," ") | BQ19: =IF(AND(BQ$6>=$F19,BQ$6<=$G19),"."," ") | BR19: =IF(AND(BR$6>=$F19,BR$6<=$G19),"."," ") | BS19: =IF(AND(BS$6>=$F19,BS$6<=$G19),"."," ") | BT19: =IF(AND(BT$6>=$F19,BT$6<=$G19),"."," ") | BU19: =IF(AND(BU$6>=$F19,BU$6<=$G19),"."," ") | BX19: =IF(AND(BX$6>=$F19,BX$6<=$G19),"."," ") | BY19: =IF(AND(BY$6>=$F19,BY$6<=$G19),"."," ") | BZ19: =IF(AND(BZ$6>=$F19,BZ$6<=$G19),"."," ") | CA19: =IF(AND(CA$6>=$F19,CA$6<=$G19),"."," ") | CB19: =IF(AND(CB$6>=$F19,CB$6<=$G19),"."," ") | CE19: =IF(AND(CE$6>=$F19,CE$6<=$G19),"."," ") | CF19: =IF(AND(CF$6>=$F19,CF$6<=$G19),"."," ") | CG19: =IF(AND(CG$6>=$F19,CG$6<=$G19),"."," ") | CH19: =IF(AND(CH$6>=$F19,CH$6<=$G19),"."," ") | CI19: =IF(AND(CI$6>=$F19,CI$6<=$G19),"."," ") | CL19: =IF(AND(CL$6>=$F19,CL$6<=$G19),"."," ") | CM19: =IF(AND(CM$6>=$F19,CM$6<=$G19),"."," ") | CN19: =IF(AND(CN$6>=$F19,CN$6<=$G19),"."," ") | CO19: =IF(AND(CO$6>=$F19,CO$6<=$G19),"."," ") | CP19: =IF(AND(CP$6>=$F19,CP$6<=$G19),"."," ") | CS19: =IF(AND(CS$6>=$F19,CS$6<=$G19),"."," ") | CT19: =IF(AND(CT$6>=$F19,CT$6<=$G19),"."," ") | CU19: =IF(AND(CU$6>=$F19,CU$6<=$G19),"."," ") | CV19: =IF(AND(CV$6>=$F19,CV$6<=$G19),"."," ") | CW19: =IF(AND(CW$6>=$F19,CW$6<=$G19),"."," ") | CZ19: =IF(AND(CZ$6>=$F19,CZ$6<=$G19),"."," ") | DA19: =IF(AND(DA$6>=$F19,DA$6<=$G19),"."," ") | DB19: =IF(AND(DB$6>=$F19,DB$6<=$G19),"."," ") | DC19: =IF(AND(DC$6>=$F19,DC$6<=$G19),"."," ") | DD19: =IF(AND(DD$6>=$F19,DD$6<=$G19),"."," ") | DG19: =IF(AND(DG$6>=$F19,DG$6<=$G19),"."," ") | DH19: =IF(AND(DH$6>=$F19,DH$6<=$G19),"."," ") | DI19: =IF(AND(DI$6>=$F19,DI$6<=$G19),"."," ") | DJ19: =IF(AND(DJ$6>=$F19,DJ$6<=$G19),"."," ") | DK19: =IF(AND(DK$6>=$F19,DK$6<=$G19),"."," ") | DN19: =IF(AND(DN$6>=$F19,DN$6<=$G19),"."," ") | DO19: =IF(AND(DO$6>=$F19,DO$6<=$G19),"."," ") | DP19: =IF(AND(DP$6>=$F19,DP$6<=$G19),"."," ") | DQ19: =IF(AND(DQ$6>=$F19,DQ$6<=$G19),"."," ") | DR19: =IF(AND(DR$6>=$F19,DR$6<=$G19),"."," ") | DU19: =IF(AND(DU$6>=$F19,DU$6<=$G19),"."," ") | DV19: =IF(AND(DV$6>=$F19,DV$6<=$G19),"."," ") | DW19: =IF(AND(DW$6>=$F19,DW$6<=$G19),"."," ") | DX19: =IF(AND(DX$6>=$F19,DX$6<=$G19),"."," ") | DY19: =IF(AND(DY$6>=$F19,DY$6<=$G19),"."," ") | EB19: =IF(AND(EB$6>=$F19,EB$6<=$G19),"."," ") | EC19: =IF(AND(EC$6>=$F19,EC$6<=$G19),"."," ") | ED19: =IF(AND(ED$6>=$F19,ED$6<=$G19),"."," ") | EE19: =IF(AND(EE$6>=$F19,EE$6<=$G19),"."," ") | EF19: =IF(AND(EF$6>=$F19,EF$6<=$G19),"."," ") | EI19: =IF(AND(EI$6>=$F19,EI$6<=$G19),"."," ") | EJ19: =IF(AND(EJ$6>=$F19,EJ$6<=$G19),"."," ") | EK19: =IF(AND(EK$6>=$F19,EK$6<=$G19),"."," ") | EL19: =IF(AND(EL$6>=$F19,EL$6<=$G19),"."," ") | EM19: =IF(AND(EM$6>=$F19,EM$6<=$G19),"."," ") | EP19: =IF(AND(EP$6>=$F19,EP$6<=$G19),"."," ") | EQ19: =IF(AND(EQ$6>=$F19,EQ$6<=$G19),"."," ") | ER19: =IF(AND(ER$6>=$F19,ER$6<=$G19),"."," ") | ES19: =IF(AND(ES$6>=$F19,ES$6<=$G19),"."," ") | ET19: =IF(AND(ET$6>=$F19,ET$6<=$G19),"."," ") | EW19: =IF(AND(EW$6>=$F19,EW$6<=$G19),"."," ") | EX19: =IF(AND(EX$6>=$F19,EX$6<=$G19),"."," ") | EY19: =IF(AND(EY$6>=$F19,EY$6<=$G19),"."," ") | EZ19: =IF(AND(EZ$6>=$F19,EZ$6<=$G19),"."," ") | FA19: =IF(AND(FA$6>=$F19,FA$6<=$G19),"."," ") | FD19: =IF(AND(FD$6>=$F19,FD$6<=$G19),"."," ") | FE19: =IF(AND(FE$6>=$F19,FE$6<=$G19),"."," ") | FF19: =IF(AND(FF$6>=$F19,FF$6<=$G19),"."," ") | FG19: =IF(AND(FG$6>=$F19,FG$6<=$G19),"."," ") | FH19: =IF(AND(FH$6>=$F19,FH$6<=$G19),"."," ") | FK19: =IF(AND(FK$6>=$F19,FK$6<=$G19),"."," ") | FL19: =IF(AND(FL$6>=$F19,FL$6<=$G19),"."," ") | FM19: =IF(AND(FM$6>=$F19,FM$6<=$G19),"."," ") | FN19: =IF(AND(FN$6>=$F19,FN$6<=$G19),"."," ") | FO19: =IF(AND(FO$6>=$F19,FO$6<=$G19),"."," ") | FR19: =IF(AND(FR$6>=$F19,FR$6<=$G19),"."," ") | FS19: =IF(AND(FS$6>=$F19,FS$6<=$G19),"."," ") | FT19: =IF(AND(FT$6>=$F19,FT$6<=$G19),"."," ") | FU19: =IF(AND(FU$6>=$F19,FU$6<=$G19),"."," ") | FV19: =IF(AND(FV$6>=$F19,FV$6<=$G19),"."," ") | FY19: =IF(AND(FY$6>=$F19,FY$6<=$G19),"."," ") | FZ19: =IF(AND(FZ$6>=$F19,FZ$6<=$G19),"."," ") | GA19: =IF(AND(GA$6>=$F19,GA$6<=$G19),"."," ") | GB19: =IF(AND(GB$6>=$F19,GB$6<=$G19),"."," ") | GC19: =IF(AND(GC$6>=$F19,GC$6<=$G19),"."," ") | GF19: =IF(AND(GF$6>=$F19,GF$6<=$G19),"."," ") | GG19: =IF(AND(GG$6>=$F19,GG$6<=$G19),"."," ") | GH19: =IF(AND(GH$6>=$F19,GH$6<=$G19),"."," ") | GI19: =IF(AND(GI$6>=$F19,GI$6<=$G19),"."," ") | GJ19: =IF(AND(GJ$6>=$F19,GJ$6<=$G19),"."," ") | GM19: =IF(AND(GM$6>=$F19,GM$6<=$G19),"."," ") | GN19: =IF(AND(GN$6>=$F19,GN$6<=$G19),"."," ") | GO19: =IF(AND(GO$6>=$F19,GO$6<=$G19),"."," ") | GP19: =IF(AND(GP$6>=$F19,GP$6<=$G19),"."," ") | GQ19: =IF(AND(GQ$6>=$F19,GQ$6<=$G19),"."," ") | GT19: =IF(AND(GT$6>=$F19,GT$6<=$G19),"."," ") | GU19: =IF(AND(GU$6>=$F19,GU$6<=$G19),"."," ") | GV19: =IF(AND(GV$6>=$F19,GV$6<=$G19),"."," ") | GW19: =IF(AND(GW$6>=$F19,GW$6<=$G19),"."," ") | GX19: =IF(AND(GX$6>=$F19,GX$6<=$G19),"."," ") | HA19: =IF(AND(HA$6>=$F19,HA$6<=$G19),"."," ") | HB19: =IF(AND(HB$6>=$F19,HB$6<=$G19),"."," ") | HC19: =IF(AND(HC$6>=$F19,HC$6<=$G19),"."," ") | HD19: =IF(AND(HD$6>=$F19,HD$6<=$G19),"."," ") | HE19: =IF(AND(HE$6>=$F19,HE$6<=$G19),"."," ") | HH19: =IF(AND(HH$6>=$F19,HH$6<=$G19),"."," ") | HI19: =IF(AND(HI$6>=$F19,HI$6<=$G19),"."," ") | HJ19: =IF(AND(HJ$6>=$F19,HJ$6<=$G19),"."," ") | HK19: =IF(AND(HK$6>=$F19,HK$6<=$G19),"."," ") | HL19: =IF(AND(HL$6>=$F19,HL$6<=$G19),"."," ") | HO19: =IF(AND(HO$6>=$F19,HO$6<=$G19),"."," ") | HP19: =IF(AND(HP$6>=$F19,HP$6<=$G19),"."," ") | HQ19: =IF(AND(HQ$6>=$F19,HQ$6<=$G19),"."," ") | HR19: =IF(AND(HR$6>=$F19,HR$6<=$G19),"."," ") | HS19: =IF(AND(HS$6>=$F19,HS$6<=$G19),"."," ") | HV19: =IF(AND(HV$6>=$F19,HV$6<=$G19),"."," ") | HW19: =IF(AND(HW$6>=$F19,HW$6<=$G19),"."," ") | HX19: =IF(AND(HX$6>=$F19,HX$6<=$G19),"."," ") | HY19: =IF(AND(HY$6>=$F19,HY$6<=$G19),"."," ") | HZ19: =IF(AND(HZ$6>=$F19,HZ$6<=$G19),"."," ") | IC19: =IF(AND(IC$6>=$F19,IC$6<=$G19),"."," ") | ID19: =IF(AND(ID$6>=$F19,ID$6<=$G19),"."," ") | IE19: =IF(AND(IE$6>=$F19,IE$6<=$G19),"."," ") | IF19: =IF(AND(IF$6>=$F19,IF$6<=$G19),"."," ") | IG19: =IF(AND(IG$6>=$F19,IG$6<=$G19),"."," ") | IJ19: =IF(AND(IJ$6>=$F19,IJ$6<=$G19),"."," ") | IK19: =IF(AND(IK$6>=$F19,IK$6<=$G19),"."," ") | IL19: =IF(AND(IL$6>=$F19,IL$6<=$G19),"."," ") | IM19: =IF(AND(IM$6>=$F19,IM$6<=$G19),"."," ") | IN19: =IF(AND(IN$6>=$F19,IN$6<=$G19),"."," ") | IQ19: =IF(AND(IQ$6>=$F19,IQ$6<=$G19),"."," ") | IR19: =IF(AND(IR$6>=$F19,IR$6<=$G19),"."," ") | IS19: =IF(AND(IS$6>=$F19,IS$6<=$G19),"."," ") | IT19: =IF(AND(IT$6>=$F19,IT$6<=$G19),"."," ") | IU19: =IF(AND(IU$6>=$F19,IU$6<=$G19),"."," ") | IX19: =IF(AND(IX$6>=$F19,IX$6<=$G19),"."," ") | IY19: =IF(AND(IY$6>=$F19,IY$6<=$G19),"."," ") | IZ19: =IF(AND(IZ$6>=$F19,IZ$6<=$G19),"."," ") | JA19: =IF(AND(JA$6>=$F19,JA$6<=$G19),"."," ") | JB19: =IF(AND(JB$6>=$F19,JB$6<=$G19),"."," ") | JE19: =IF(AND(JE$6>=$F19,JE$6<=$G19),"."," ") | JF19: =IF(AND(JF$6>=$F19,JF$6<=$G19),"."," ") | JG19: =IF(AND(JG$6>=$F19,JG$6<=$G19),"."," ") | JH19: =IF(AND(JH$6>=$F19,JH$6<=$G19),"."," ") | JI19: =IF(AND(JI$6>=$F19,JI$6<=$G19),"."," ")
B20: 12 | C20: Design handover | D20: Mich | E20: 10 | F20: =VLOOKUP(E20,$B$6:$G$150,6,FALSE) + 1 -> 42529 | G20: =WORKDAY(F20,H20-1,Config!D18:D37) -> 42530 | H20: 2 | I20: 0.45 | J20: =IF(((NETWORKDAYS(F20,TODAY(),Data!C14:C33)*100)/H20)/100 > 0,((NETWORKDAYS(F20,TODAY(),Data!C14:C33)*100)/H20)/100,0) -> 824 | K20: =IF(J20>1, "100%",$J20) -> 100% | L20: =K20-I20 -> 0.55 | M20: =IF(AND(M$6>=$F20,M$6<=$G20),"."," ") | N20: =IF(AND(N$6>=$F20,N$6<=$G20),"."," ") | O20: =IF(AND(O$6>=$F20,O$6<=$G20),"."," ") | P20: =IF(AND(P$6>=$F20,P$6<=$G20),"."," ") | Q20: =IF(AND(Q$6>=$F20,Q$6<=$G20),"."," ") | T20: =IF(AND(T$6>=$F20,T$6<=$G20),"."," ") | U20: =IF(AND(U$6>=$F20,U$6<=$G20),"."," ") | V20: =IF(AND(V$6>=$F20,V$6<=$G20),"."," ") | W20: =IF(AND(W$6>=$F20,W$6<=$G20),"."," ") | X20: =IF(AND(X$6>=$F20,X$6<=$G20),"."," ") | AA20: =IF(AND(AA$6>=$F20,AA$6<=$G20),"."," ") | AB20: =IF(AND(AB$6>=$F20,AB$6<=$G20),"."," ") | AC20: =IF(AND(AC$6>=$F20,AC$6<=$G20),"."," ") | AD20: =IF(AND(AD$6>=$F20,AD$6<=$G20),"."," ") | AE20: =IF(AND(AE$6>=$F20,AE$6<=$G20),"."," ") | AH20: =IF(AND(AH$6>=$F20,AH$6<=$G20),"."," ") | AI20: =IF(AND(AI$6>=$F20,AI$6<=$G20),"."," ") | AJ20: =IF(AND(AJ$6>=$F20,AJ$6<=$G20),"."," ") | AK20: =IF(AND(AK$6>=$F20,AK$6<=$G20),"."," ") | AL20: =IF(AND(AL$6>=$F20,AL$6<=$G20),"."," ") | AO20: =IF(AND(AO$6>=$F20,AO$6<=$G20),"."," ") | AP20: =IF(AND(AP$6>=$F20,AP$6<=$G20),"."," ") | AQ20: =IF(AND(AQ$6>=$F20,AQ$6<=$G20),"."," ") | AR20: =IF(AND(AR$6>=$F20,AR$6<=$G20),"."," ") | AS20: =IF(AND(AS$6>=$F20,AS$6<=$G20),"."," ") | AV20: =IF(AND(AV$6>=$F20,AV$6<=$G20),"."," ") -> . | AW20: =IF(AND(AW$6>=$F20,AW$6<=$G20),"."," ") | AX20: =IF(AND(AX$6>=$F20,AX$6<=$G20),"."," ") | AY20: =IF(AND(AY$6>=$F20,AY$6<=$G20),"."," ") | AZ20: =IF(AND(AZ$6>=$F20,AZ$6<=$G20),"."," ") | BC20: =IF(AND(BC$6>=$F20,BC$6<=$G20),"."," ") | BD20: =IF(AND(BD$6>=$F20,BD$6<=$G20),"."," ") | BE20: =IF(AND(BE$6>=$F20,BE$6<=$G20),"."," ") | BF20: =IF(AND(BF$6>=$F20,BF$6<=$G20),"."," ") | BG20: =IF(AND(BG$6>=$F20,BG$6<=$G20),"."," ") | BJ20: =IF(AND(BJ$6>=$F20,BJ$6<=$G20),"."," ") | BK20: =IF(AND(BK$6>=$F20,BK$6<=$G20),"."," ") | BL20: =IF(AND(BL$6>=$F20,BL$6<=$G20),"."," ") | BM20: =IF(AND(BM$6>=$F20,BM$6<=$G20),"."," ") | BN20: =IF(AND(BN$6>=$F20,BN$6<=$G20),"."," ") | BQ20: =IF(AND(BQ$6>=$F20,BQ$6<=$G20),"."," ") | BR20: =IF(AND(BR$6>=$F20,BR$6<=$G20),"."," ") | BS20: =IF(AND(BS$6>=$F20,BS$6<=$G20),"."," ") | BT20: =IF(AND(BT$6>=$F20,BT$6<=$G20),"."," ") | BU20: =IF(AND(BU$6>=$F20,BU$6<=$G20),"."," ") | BX20: =IF(AND(BX$6>=$F20,BX$6<=$G20),"."," ") | BY20: =IF(AND(BY$6>=$F20,BY$6<=$G20),"."," ") | BZ20: =IF(AND(BZ$6>=$F20,BZ$6<=$G20),"."," ") | CA20: =IF(AND(CA$6>=$F20,CA$6<=$G20),"."," ") | CB20: =IF(AND(CB$6>=$F20,CB$6<=$G20),"."," ") | CE20: =IF(AND(CE$6>=$F20,CE$6<=$G20),"."," ") | CF20: =IF(AND(CF$6>=$F20,CF$6<=$G20),"."," ") | CG20: =IF(AND(CG$6>=$F20,CG$6<=$G20),"."," ") | CH20: =IF(AND(CH$6>=$F20,CH$6<=$G20),"."," ") | CI20: =IF(AND(CI$6>=$F20,CI$6<=$G20),"."," ") | CL20: =IF(AND(CL$6>=$F20,CL$6<=$G20),"."," ") | CM20: =IF(AND(CM$6>=$F20,CM$6<=$G20),"."," ") | CN20: =IF(AND(CN$6>=$F20,CN$6<=$G20),"."," ") | CO20: =IF(AND(CO$6>=$F20,CO$6<=$G20),"."," ") | CP20: =IF(AND(CP$6>=$F20,CP$6<=$G20),"."," ") | CS20: =IF(AND(CS$6>=$F20,CS$6<=$G20),"."," ") | CT20: =IF(AND(CT$6>=$F20,CT$6<=$G20),"."," ") | CU20: =IF(AND(CU$6>=$F20,CU$6<=$G20),"."," ") | CV20: =IF(AND(CV$6>=$F20,CV$6<=$G20),"."," ") | CW20: =IF(AND(CW$6>=$F20,CW$6<=$G20),"."," ") | CZ20: =IF(AND(CZ$6>=$F20,CZ$6<=$G20),"."," ") | DA20: =IF(AND(DA$6>=$F20,DA$6<=$G20),"."," ") | DB20: =IF(AND(DB$6>=$F20,DB$6<=$G20),"."," ") | DC20: =IF(AND(DC$6>=$F20,DC$6<=$G20),"."," ") | DD20: =IF(AND(DD$6>=$F20,DD$6<=$G20),"."," ") | DG20: =IF(AND(DG$6>=$F20,DG$6<=$G20),"."," ") | DH20: =IF(AND(DH$6>=$F20,DH$6<=$G20),"."," ") | DI20: =IF(AND(DI$6>=$F20,DI$6<=$G20),"."," ") | DJ20: =IF(AND(DJ$6>=$F20,DJ$6<=$G20),"."," ") | DK20: =IF(AND(DK$6>=$F20,DK$6<=$G20),"."," ") | DN20: =IF(AND(DN$6>=$F20,DN$6<=$G20),"."," ") | DO20: =IF(AND(DO$6>=$F20,DO$6<=$G20),"."," ") | DP20: =IF(AND(DP$6>=$F20,DP$6<=$G20),"."," ") | DQ20: =IF(AND(DQ$6>=$F20,DQ$6<=$G20),"."," ") | DR20: =IF(AND(DR$6>=$F20,DR$6<=$G20),"."," ") | DU20: =IF(AND(DU$6>=$F20,DU$6<=$G20),"."," ") | DV20: =IF(AND(DV$6>=$F20,DV$6<=$G20),"."," ") | DW20: =IF(AND(DW$6>=$F20,DW$6<=$G20),"."," ") | DX20: =IF(AND(DX$6>=$F20,DX$6<=$G20),"."," ") | DY20: =IF(AND(DY$6>=$F20,DY$6<=$G20),"."," ") | EB20: =IF(AND(EB$6>=$F20,EB$6<=$G20),"."," ") | EC20: =IF(AND(EC$6>=$F20,EC$6<=$G20),"."," ") | ED20: =IF(AND(ED$6>=$F20,ED$6<=$G20),"."," ") | EE20: =IF(AND(EE$6>=$F20,EE$6<=$G20),"."," ") | EF20: =IF(AND(EF$6>=$F20,EF$6<=$G20),"."," ") | EI20: =IF(AND(EI$6>=$F20,EI$6<=$G20),"."," ") | EJ20: =IF(AND(EJ$6>=$F20,EJ$6<=$G20),"."," ") | EK20: =IF(AND(EK$6>=$F20,EK$6<=$G20),"."," ") | EL20: =IF(AND(EL$6>=$F20,EL$6<=$G20),"."," ") | EM20: =IF(AND(EM$6>=$F20,EM$6<=$G20),"."," ") | EP20: =IF(AND(EP$6>=$F20,EP$6<=$G20),"."," ") | EQ20: =IF(AND(EQ$6>=$F20,EQ$6<=$G20),"."," ") | ER20: =IF(AND(ER$6>=$F20,ER$6<=$G20),"."," ") | ES20: =IF(AND(ES$6>=$F20,ES$6<=$G20),"."," ") | ET20: =IF(AND(ET$6>=$F20,ET$6<=$G20),"."," ") | EW20: =IF(AND(EW$6>=$F20,EW$6<=$G20),"."," ") | EX20: =IF(AND(EX$6>=$F20,EX$6<=$G20),"."," ") | EY20: =IF(AND(EY$6>=$F20,EY$6<=$G20),"."," ") | EZ20: =IF(AND(EZ$6>=$F20,EZ$6<=$G20),"."," ") | FA20: =IF(AND(FA$6>=$F20,FA$6<=$G20),"."," ") | FD20: =IF(AND(FD$6>=$F20,FD$6<=$G20),"."," ") | FE20: =IF(AND(FE$6>=$F20,FE$6<=$G20),"."," ") | FF20: =IF(AND(FF$6>=$F20,FF$6<=$G20),"."," ") | FG20: =IF(AND(FG$6>=$F20,FG$6<=$G20),"."," ") | FH20: =IF(AND(FH$6>=$F20,FH$6<=$G20),"."," ") | FK20: =IF(AND(FK$6>=$F20,FK$6<=$G20),"."," ") | FL20: =IF(AND(FL$6>=$F20,FL$6<=$G20),"."," ") | FM20: =IF(AND(FM$6>=$F20,FM$6<=$G20),"."," ") | FN20: =IF(AND(FN$6>=$F20,FN$6<=$G20),"."," ") | FO20: =IF(AND(FO$6>=$F20,FO$6<=$G20),"."," ") | FR20: =IF(AND(FR$6>=$F20,FR$6<=$G20),"."," ") | FS20: =IF(AND(FS$6>=$F20,FS$6<=$G20),"."," ") | FT20: =IF(AND(FT$6>=$F20,FT$6<=$G20),"."," ") | FU20: =IF(AND(FU$6>=$F20,FU$6<=$G20),"."," ") | FV20: =IF(AND(FV$6>=$F20,FV$6<=$G20),"."," ") | FY20: =IF(AND(FY$6>=$F20,FY$6<=$G20),"."," ") | FZ20: =IF(AND(FZ$6>=$F20,FZ$6<=$G20),"."," ") | GA20: =IF(AND(GA$6>=$F20,GA$6<=$G20),"."," ") | GB20: =IF(AND(GB$6>=$F20,GB$6<=$G20),"."," ") | GC20: =IF(AND(GC$6>=$F20,GC$6<=$G20),"."," ") | GF20: =IF(AND(GF$6>=$F20,GF$6<=$G20),"."," ") | GG20: =IF(AND(GG$6>=$F20,GG$6<=$G20),"."," ") | GH20: =IF(AND(GH$6>=$F20,GH$6<=$G20),"."," ") | GI20: =IF(AND(GI$6>=$F20,GI$6<=$G20),"."," ") | GJ20: =IF(AND(GJ$6>=$F20,GJ$6<=$G20),"."," ") | GM20: =IF(AND(GM$6>=$F20,GM$6<=$G20),"."," ") | GN20: =IF(AND(GN$6>=$F20,GN$6<=$G20),"."," ") | GO20: =IF(AND(GO$6>=$F20,GO$6<=$G20),"."," ") | GP20: =IF(AND(GP$6>=$F20,GP$6<=$G20),"."," ") | GQ20: =IF(AND(GQ$6>=$F20,GQ$6<=$G20),"."," ") | GT20: =IF(AND(GT$6>=$F20,GT$6<=$G20),"."," ") | GU20: =IF(AND(GU$6>=$F20,GU$6<=$G20),"."," ") | GV20: =IF(AND(GV$6>=$F20,GV$6<=$G20),"."," ") | GW20: =IF(AND(GW$6>=$F20,GW$6<=$G20),"."," ") | GX20: =IF(AND(GX$6>=$F20,GX$6<=$G20),"."," ") | HA20: =IF(AND(HA$6>=$F20,HA$6<=$G20),"."," ") | HB20: =IF(AND(HB$6>=$F20,HB$6<=$G20),"."," ") | HC20: =IF(AND(HC$6>=$F20,HC$6<=$G20),"."," ") | HD20: =IF(AND(HD$6>=$F20,HD$6<=$G20),"."," ") | HE20: =IF(AND(HE$6>=$F20,HE$6<=$G20),"."," ") | HH20: =IF(AND(HH$6>=$F20,HH$6<=$G20),"."," ") | HI20: =IF(AND(HI$6>=$F20,HI$6<=$G20),"."," ") | HJ20: =IF(AND(HJ$6>=$F20,HJ$6<=$G20),"."," ") | HK20: =IF(AND(HK$6>=$F20,HK$6<=$G20),"."," ") | HL20: =IF(AND(HL$6>=$F20,HL$6<=$G20),"."," ") | HO20: =IF(AND(HO$6>=$F20,HO$6<=$G20),"."," ") | HP20: =IF(AND(HP$6>=$F20,HP$6<=$G20),"."," ") | HQ20: =IF(AND(HQ$6>=$F20,HQ$6<=$G20),"."," ") | HR20: =IF(AND(HR$6>=$F20,HR$6<=$G20),"."," ") | HS20: =IF(AND(HS$6>=$F20,HS$6<=$G20),"."," ") | HV20: =IF(AND(HV$6>=$F20,HV$6<=$G20),"."," ") | HW20: =IF(AND(HW$6>=$F20,HW$6<=$G20),"."," ") | HX20: =IF(AND(HX$6>=$F20,HX$6<=$G20),"."," ") | HY20: =IF(AND(HY$6>=$F20,HY$6<=$G20),"."," ") | HZ20: =IF(AND(HZ$6>=$F20,HZ$6<=$G20),"."," ") | IC20: =IF(AND(IC$6>=$F20,IC$6<=$G20),"."," ") | ID20: =IF(AND(ID$6>=$F20,ID$6<=$G20),"."," ") | IE20: =IF(AND(IE$6>=$F20,IE$6<=$G20),"."," ") | IF20: =IF(AND(IF$6>=$F20,IF$6<=$G20),"."," ") | IG20: =IF(AND(IG$6>=$F20,IG$6<=$G20),"."," ") | IJ20: =IF(AND(IJ$6>=$F20,IJ$6<=$G20),"."," ") | IK20: =IF(AND(IK$6>=$F20,IK$6<=$G20),"."," ") | IL20: =IF(AND(IL$6>=$F20,IL$6<=$G20),"."," ") | IM20: =IF(AND(IM$6>=$F20,IM$6<=$G20),"."," ") | IN20: =IF(AND(IN$6>=$F20,IN$6<=$G20),"."," ") | IQ20: =IF(AND(IQ$6>=$F20,IQ$6<=$G20),"."," ") | IR20: =IF(AND(IR$6>=$F20,IR$6<=$G20),"."," ") | IS20: =IF(AND(IS$6>=$F20,IS$6<=$G20),"."," ") | IT20: =IF(AND(IT$6>=$F20,IT$6<=$G20),"."," ") | IU20: =IF(AND(IU$6>=$F20,IU$6<=$G20),"."," ") | IX20: =IF(AND(IX$6>=$F20,IX$6<=$G20),"."," ") | IY20: =IF(AND(IY$6>=$F20,IY$6<=$G20),"."," ") | IZ20: =IF(AND(IZ$6>=$F20,IZ$6<=$G20),"."," ") | JA20: =IF(AND(JA$6>=$F20,JA$6<=$G20),"."," ") | JB20: =IF(AND(JB$6>=$F20,JB$6<=$G20),"."," ") | JE20: =IF(AND(JE$6>=$F20,JE$6<=$G20),"."," ") | JF20: =IF(AND(JF$6>=$F20,JF$6<=$G20),"."," ") | JG20: =IF(AND(JG$6>=$F20,JG$6<=$G20),"."," ") | JH20: =IF(AND(JH$6>=$F20,JH$6<=$G20),"."," ") | JI20: =IF(AND(JI$6>=$F20,JI$6<=$G20),"."," ")
B21: 13 | C21: Analysis | D21: Bob | E21: 11 | F21: =VLOOKUP(E21,$B$6:$G$150,6,FALSE) + 1 -> 42531 | G21: =WORKDAY(F21,H21-1,Config!D20:D39) -> 42534 | H21: 2 | I21: 0 | J21: =IF(((NETWORKDAYS(F21,TODAY(),Data!C16:C35)*100)/H21)/100 > 0,((NETWORKDAYS(F21,TODAY(),Data!C16:C35)*100)/H21)/100,0) -> 823 | K21: =IF(J21>1, "100%",$J21) -> 100% | L21: =K21-I21 -> 1 | M21: =IF(AND(M$6>=$F21,M$6<=$G21),"."," ") | N21: =IF(AND(N$6>=$F21,N$6<=$G21),"."," ") | O21: =IF(AND(O$6>=$F21,O$6<=$G21),"."," ") | P21: =IF(AND(P$6>=$F21,P$6<=$G21),"."," ") | Q21: =IF(AND(Q$6>=$F21,Q$6<=$G21),"."," ") | T21: =IF(AND(T$6>=$F21,T$6<=$G21),"."," ") | U21: =IF(AND(U$6>=$F21,U$6<=$G21),"."," ") | V21: =IF(AND(V$6>=$F21,V$6<=$G21),"."," ") | W21: =IF(AND(W$6>=$F21,W$6<=$G21),"."," ") | X21: =IF(AND(X$6>=$F21,X$6<=$G21),"."," ") | AA21: =IF(AND(AA$6>=$F21,AA$6<=$G21),"."," ") | AB21: =IF(AND(AB$6>=$F21,AB$6<=$G21),"."," ") | AC21: =IF(AND(AC$6>=$F21,AC$6<=$G21),"."," ") | AD21: =IF(AND(AD$6>=$F21,AD$6<=$G21),"."," ") | AE21: =IF(AND(AE$6>=$F21,AE$6<=$G21),"."," ") | AH21: =IF(AND(AH$6>=$F21,AH$6<=$G21),"."," ") | AI21: =IF(AND(AI$6>=$F21,AI$6<=$G21),"."," ") | AJ21: =IF(AND(AJ$6>=$F21,AJ$6<=$G21),"."," ") | AK21: =IF(AND(AK$6>=$F21,AK$6<=$G21),"."," ") | AL21: =IF(AND(AL$6>=$F21,AL$6<=$G21),"."," ") | AO21: =IF(AND(AO$6>=$F21,AO$6<=$G21),"."," ") | AP21: =IF(AND(AP$6>=$F21,AP$6<=$G21),"."," ") | AQ21: =IF(AND(AQ$6>=$F21,AQ$6<=$G21),"."," ") | AR21: =IF(AND(AR$6>=$F21,AR$6<=$G21),"."," ") | AS21: =IF(AND(AS$6>=$F21,AS$6<=$G21),"."," ") | AV21: =IF(AND(AV$6>=$F21,AV$6<=$G21),"."," ") | AW21: =IF(AND(AW$6>=$F21,AW$6<=$G21),"."," ") -> . | AX21: =IF(AND(AX$6>=$F21,AX$6<=$G21),"."," ") -> . | AY21: =IF(AND(AY$6>=$F21,AY$6<=$G21),"."," ") -> . | AZ21: =IF(AND(AZ$6>=$F21,AZ$6<=$G21),"."," ") -> . | BC21: =IF(AND(BC$6>=$F21,BC$6<=$G21),"."," ") | BD21: =IF(AND(BD$6>=$F21,BD$6<=$G21),"."," ") | BE21: =IF(AND(BE$6>=$F21,BE$6<=$G21),"."," ") | BF21: =IF(AND(BF$6>=$F21,BF$6<=$G21),"."," ") | BG21: =IF(AND(BG$6>=$F21,BG$6<=$G21),"."," ") | BJ21: =IF(AND(BJ$6>=$F21,BJ$6<=$G21),"."," ") | BK21: =IF(AND(BK$6>=$F21,BK$6<=$G21),"."," ") | BL21: =IF(AND(BL$6>=$F21,BL$6<=$G21),"."," ") | BM21: =IF(AND(BM$6>=$F21,BM$6<=$G21),"."," ") | BN21: =IF(AND(BN$6>=$F21,BN$6<=$G21),"."," ") | BQ21: =IF(AND(BQ$6>=$F21,BQ$6<=$G21),"."," ") | BR21: =IF(AND(BR$6>=$F21,BR$6<=$G21),"."," ") | BS21: =IF(AND(BS$6>=$F21,BS$6<=$G21),"."," ") | BT21: =IF(AND(BT$6>=$F21,BT$6<=$G21),"."," ") | BU21: =IF(AND(BU$6>=$F21,BU$6<=$G21),"."," ") | BX21: =IF(AND(BX$6>=$F21,BX$6<=$G21),"."," ") | BY21: =IF(AND(BY$6>=$F21,BY$6<=$G21),"."," ") | BZ21: =IF(AND(BZ$6>=$F21,BZ$6<=$G21),"."," ") | CA21: =IF(AND(CA$6>=$F21,CA$6<=$G21),"."," ") | CB21: =IF(AND(CB$6>=$F21,CB$6<=$G21),"."," ") | CE21: =IF(AND(CE$6>=$F21,CE$6<=$G21),"."," ") | CF21: =IF(AND(CF$6>=$F21,CF$6<=$G21),"."," ") | CG21: =IF(AND(CG$6>=$F21,CG$6<=$G21),"."," ") | CH21: =IF(AND(CH$6>=$F21,CH$6<=$G21),"."," ") | CI21: =IF(AND(CI$6>=$F21,CI$6<=$G21),"."," ") | CL21: =IF(AND(CL$6>=$F21,CL$6<=$G21),"."," ") | CM21: =IF(AND(CM$6>=$F21,CM$6<=$G21),"."," ") | CN21: =IF(AND(CN$6>=$F21,CN$6<=$G21),"."," ") | CO21: =IF(AND(CO$6>=$F21,CO$6<=$G21),"."," ") | CP21: =IF(AND(CP$6>=$F21,CP$6<=$G21),"."," ") | CS21: =IF(AND(CS$6>=$F21,CS$6<=$G21),"."," ") | CT21: =IF(AND(CT$6>=$F21,CT$6<=$G21),"."," ") | CU21: =IF(AND(CU$6>=$F21,CU$6<=$G21),"."," ") | CV21: =IF(AND(CV$6>=$F21,CV$6<=$G21),"."," ") | CW21: =IF(AND(CW$6>=$F21,CW$6<=$G21),"."," ") | CZ21: =IF(AND(CZ$6>=$F21,CZ$6<=$G21),"."," ") | DA21: =IF(AND(DA$6>=$F21,DA$6<=$G21),"."," ") | DB21: =IF(AND(DB$6>=$F21,DB$6<=$G21),"."," ") | DC21: =IF(AND(DC$6>=$F21,DC$6<=$G21),"."," ") | DD21: =IF(AND(DD$6>=$F21,DD$6<=$G21),"."," ") | DG21: =IF(AND(DG$6>=$F21,DG$6<=$G21),"."," ") | DH21: =IF(AND(DH$6>=$F21,DH$6<=$G21),"."," ") | DI21: =IF(AND(DI$6>=$F21,DI$6<=$G21),"."," ") | DJ21: =IF(AND(DJ$6>=$F21,DJ$6<=$G21),"."," ") | DK21: =IF(AND(DK$6>=$F21,DK$6<=$G21),"."," ") | DN21: =IF(AND(DN$6>=$F21,DN$6<=$G21),"."," ") | DO21: =IF(AND(DO$6>=$F21,DO$6<=$G21),"."," ") | DP21: =IF(AND(DP$6>=$F21,DP$6<=$G21),"."," ") | DQ21: =IF(AND(DQ$6>=$F21,DQ$6<=$G21),"."," ") | DR21: =IF(AND(DR$6>=$F21,DR$6<=$G21),"."," ") | DU21: =IF(AND(DU$6>=$F21,DU$6<=$G21),"."," ") | DV21: =IF(AND(DV$6>=$F21,DV$6<=$G21),"."," ") | DW21: =IF(AND(DW$6>=$F21,DW$6<=$G21),"."," ") | DX21: =IF(AND(DX$6>=$F21,DX$6<=$G21),"."," ") | DY21: =IF(AND(DY$6>=$F21,DY$6<=$G21),"."," ") | EB21: =IF(AND(EB$6>=$F21,EB$6<=$G21),"."," ") | EC21: =IF(AND(EC$6>=$F21,EC$6<=$G21),"."," ") | ED21: =IF(AND(ED$6>=$F21,ED$6<=$G21),"."," ") | EE21: =IF(AND(EE$6>=$F21,EE$6<=$G21),"."," ") | EF21: =IF(AND(EF$6>=$F21,EF$6<=$G21),"."," ") | EI21: =IF(AND(EI$6>=$F21,EI$6<=$G21),"."," ") | EJ21: =IF(AND(EJ$6>=$F21,EJ$6<=$G21),"."," ") | EK21: =IF(AND(EK$6>=$F21,EK$6<=$G21),"."," ") | EL21: =IF(AND(EL$6>=$F21,EL$6<=$G21),"."," ") | EM21: =IF(AND(EM$6>=$F21,EM$6<=$G21),"."," ") | EP21: =IF(AND(EP$6>=$F21,EP$6<=$G21),"."," ") | EQ21: =IF(AND(EQ$6>=$F21,EQ$6<=$G21),"."," ") | ER21: =IF(AND(ER$6>=$F21,ER$6<=$G21),"."," ") | ES21: =IF(AND(ES$6>=$F21,ES$6<=$G21),"."," ") | ET21: =IF(AND(ET$6>=$F21,ET$6<=$G21),"."," ") | EW21: =IF(AND(EW$6>=$F21,EW$6<=$G21),"."," ") | EX21: =IF(AND(EX$6>=$F21,EX$6<=$G21),"."," ") | EY21: =IF(AND(EY$6>=$F21,EY$6<=$G21),"."," ") | EZ21: =IF(AND(EZ$6>=$F21,EZ$6<=$G21),"."," ") | FA21: =IF(AND(FA$6>=$F21,FA$6<=$G21),"."," ") | FD21: =IF(AND(FD$6>=$F21,FD$6<=$G21),"."," ") | FE21: =IF(AND(FE$6>=$F21,FE$6<=$G21),"."," ") | FF21: =IF(AND(FF$6>=$F21,FF$6<=$G21),"."," ") | FG21: =IF(AND(FG$6>=$F21,FG$6<=$G21),"."," ") | FH21: =IF(AND(FH$6>=$F21,FH$6<=$G21),"."," ") | FK21: =IF(AND(FK$6>=$F21,FK$6<=$G21),"."," ") | FL21: =IF(AND(FL$6>=$F21,FL$6<=$G21),"."," ") | FM21: =IF(AND(FM$6>=$F21,FM$6<=$G21),"."," ") | FN21: =IF(AND(FN$6>=$F21,FN$6<=$G21),"."," ") | FO21: =IF(AND(FO$6>=$F21,FO$6<=$G21),"."," ") | FR21: =IF(AND(FR$6>=$F21,FR$6<=$G21),"."," ") | FS21: =IF(AND(FS$6>=$F21,FS$6<=$G21),"."," ") | FT21: =IF(AND(FT$6>=$F21,FT$6<=$G21),"."," ") | FU21: =IF(AND(FU$6>=$F21,FU$6<=$G21),"."," ") | FV21: =IF(AND(FV$6>=$F21,FV$6<=$G21),"."," ") | FY21: =IF(AND(FY$6>=$F21,FY$6<=$G21),"."," ") | FZ21: =IF(AND(FZ$6>=$F21,FZ$6<=$G21),"."," ") | GA21: =IF(AND(GA$6>=$F21,GA$6<=$G21),"."," ") | GB21: =IF(AND(GB$6>=$F21,GB$6<=$G21),"."," ") | GC21: =IF(AND(GC$6>=$F21,GC$6<=$G21),"."," ") | GF21: =IF(AND(GF$6>=$F21,GF$6<=$G21),"."," ") | GG21: =IF(AND(GG$6>=$F21,GG$6<=$G21),"."," ") | GH21: =IF(AND(GH$6>=$F21,GH$6<=$G21),"."," ") | GI21: =IF(AND(GI$6>=$F21,GI$6<=$G21),"."," ") | GJ21: =IF(AND(GJ$6>=$F21,GJ$6<=$G21),"."," ") | GM21: =IF(AND(GM$6>=$F21,GM$6<=$G21),"."," ") | GN21: =IF(AND(GN$6>=$F21,GN$6<=$G21),"."," ") | GO21: =IF(AND(GO$6>=$F21,GO$6<=$G21),"."," ") | GP21: =IF(AND(GP$6>=$F21,GP$6<=$G21),"."," ") | GQ21: =IF(AND(GQ$6>=$F21,GQ$6<=$G21),"."," ") | GT21: =IF(AND(GT$6>=$F21,GT$6<=$G21),"."," ") | GU21: =IF(AND(GU$6>=$F21,GU$6<=$G21),"."," ") | GV21: =IF(AND(GV$6>=$F21,GV$6<=$G21),"."," ") | GW21: =IF(AND(GW$6>=$F21,GW$6<=$G21),"."," ") | GX21: =IF(AND(GX$6>=$F21,GX$6<=$G21),"."," ") | HA21: =IF(AND(HA$6>=$F21,HA$6<=$G21),"."," ") | HB21: =IF(AND(HB$6>=$F21,HB$6<=$G21),"."," ") | HC21: =IF(AND(HC$6>=$F21,HC$6<=$G21),"."," ") | HD21: =IF(AND(HD$6>=$F21,HD$6<=$G21),"."," ") | HE21: =IF(AND(HE$6>=$F21,HE$6<=$G21),"."," ") | HH21: =IF(AND(HH$6>=$F21,HH$6<=$G21),"."," ") | HI21: =IF(AND(HI$6>=$F21,HI$6<=$G21),"."," ") | HJ21: =IF(AND(HJ$6>=$F21,HJ$6<=$G21),"."," ") | HK21: =IF(AND(HK$6>=$F21,HK$6<=$G21),"."," ") | HL21: =IF(AND(HL$6>=$F21,HL$6<=$G21),"."," ") | HO21: =IF(AND(HO$6>=$F21,HO$6<=$G21),"."," ") | HP21: =IF(AND(HP$6>=$F21,HP$6<=$G21),"."," ") | HQ21: =IF(AND(HQ$6>=$F21,HQ$6<=$G21),"."," ") | HR21: =IF(AND(HR$6>=$F21,HR$6<=$G21),"."," ") | HS21: =IF(AND(HS$6>=$F21,HS$6<=$G21),"."," ") | HV21: =IF(AND(HV$6>=$F21,HV$6<=$G21),"."," ") | HW21: =IF(AND(HW$6>=$F21,HW$6<=$G21),"."," ") | HX21: =IF(AND(HX$6>=$F21,HX$6<=$G21),"."," ") | HY21: =IF(AND(HY$6>=$F21,HY$6<=$G21),"."," ") | HZ21: =IF(AND(HZ$6>=$F21,HZ$6<=$G21),"."," ") | IC21: =IF(AND(IC$6>=$F21,IC$6<=$G21),"."," ") | ID21: =IF(AND(ID$6>=$F21,ID$6<=$G21),"."," ") | IE21: =IF(AND(IE$6>=$F21,IE$6<=$G21),"."," ") | IF21: =IF(AND(IF$6>=$F21,IF$6<=$G21),"."," ") | IG21: =IF(AND(IG$6>=$F21,IG$6<=$G21),"."," ") | IJ21: =IF(AND(IJ$6>=$F21,IJ$6<=$G21),"."," ") | IK21: =IF(AND(IK$6>=$F21,IK$6<=$G21),"."," ") | IL21: =IF(AND(IL$6>=$F21,IL$6<=$G21),"."," ") | IM21: =IF(AND(IM$6>=$F21,IM$6<=$G21),"."," ") | IN21: =IF(AND(IN$6>=$F21,IN$6<=$G21),"."," ") | IQ21: =IF(AND(IQ$6>=$F21,IQ$6<=$G21),"."," ") | IR21: =IF(AND(IR$6>=$F21,IR$6<=$G21),"."," ") | IS21: =IF(AND(IS$6>=$F21,IS$6<=$G21),"."," ") | IT21: =IF(AND(IT$6>=$F21,IT$6<=$G21),"."," ") | IU21: =IF(AND(IU$6>=$F21,IU$6<=$G21),"."," ") | IX21: =IF(AND(IX$6>=$F21,IX$6<=$G21),"."," ") | IY21: =IF(AND(IY$6>=$F21,IY$6<=$G21),"."," ") | IZ21: =IF(AND(IZ$6>=$F21,IZ$6<=$G21),"."," ") | JA21: =IF(AND(JA$6>=$F21,JA$6<=$G21),"."," ") | JB21: =IF(AND(JB$6>=$F21,JB$6<=$G21),"."," ") | JE21: =IF(AND(JE$6>=$F21,JE$6<=$G21),"."," ") | JF21: =IF(AND(JF$6>=$F21,JF$6<=$G21),"."," ") | JG21: =IF(AND(JG$6>=$F21,JG$6<=$G21),"."," ") | JH21: =IF(AND(JH$6>=$F21,JH$6<=$G21),"."," ") | JI21: =IF(AND(JI$6>=$F21,JI$6<=$G21),"."," ")
B22: 14 | C22: Build Component 1 | D22: Bob | E22: 12 | F22: =VLOOKUP(E22,$B$6:$G$150,6,FALSE) + 1 -> 42531 | G22: =WORKDAY(F22,H22-1,Config!D21:D40) -> 42536 | H22: 4 | I22: 0 | J22: =IF(((NETWORKDAYS(F22,TODAY(),Data!C17:C36)*100)/H22)/100 > 0,((NETWORKDAYS(F22,TODAY(),Data!C17:C36)*100)/H22)/100,0) -> 411.5 | K22: =IF(J22>1, "100%",$J22) -> 100% | L22: =K22-I22 -> 1 | M22: =IF(AND(M$6>=$F22,M$6<=$G22),"."," ") | N22: =IF(AND(N$6>=$F22,N$6<=$G22),"."," ") | O22: =IF(AND(O$6>=$F22,O$6<=$G22),"."," ") | P22: =IF(AND(P$6>=$F22,P$6<=$G22),"."," ") | Q22: =IF(AND(Q$6>=$F22,Q$6<=$G22),"."," ") | T22: =IF(AND(T$6>=$F22,T$6<=$G22),"."," ") | U22: =IF(AND(U$6>=$F22,U$6<=$G22),"."," ") | V22: =IF(AND(V$6>=$F22,V$6<=$G22),"."," ") | W22: =IF(AND(W$6>=$F22,W$6<=$G22),"."," ") | X22: =IF(AND(X$6>=$F22,X$6<=$G22),"."," ") | AA22: =IF(AND(AA$6>=$F22,AA$6<=$G22),"."," ") | AB22: =IF(AND(AB$6>=$F22,AB$6<=$G22),"."," ") | AC22: =IF(AND(AC$6>=$F22,AC$6<=$G22),"."," ") | AD22: =IF(AND(AD$6>=$F22,AD$6<=$G22),"."," ") | AE22: =IF(AND(AE$6>=$F22,AE$6<=$G22),"."," ") | AH22: =IF(AND(AH$6>=$F22,AH$6<=$G22),"."," ") | AI22: =IF(AND(AI$6>=$F22,AI$6<=$G22),"."," ") | AJ22: =IF(AND(AJ$6>=$F22,AJ$6<=$G22),"."," ") | AK22: =IF(AND(AK$6>=$F22,AK$6<=$G22),"."," ") | AL22: =IF(AND(AL$6>=$F22,AL$6<=$G22),"."," ") | AO22: =IF(AND(AO$6>=$F22,AO$6<=$G22),"."," ") | AP22: =IF(AND(AP$6>=$F22,AP$6<=$G22),"."," ") | AQ22: =IF(AND(AQ$6>=$F22,AQ$6<=$G22),"."," ") | AR22: =IF(AND(AR$6>=$F22,AR$6<=$G22),"."," ") | AS22: =IF(AND(AS$6>=$F22,AS$6<=$G22),"."," ") | AV22: =IF(AND(AV$6>=$F22,AV$6<=$G22),"."," ") | AW22: =IF(AND(AW$6>=$F22,AW$6<=$G22),"."," ") -> . | AX22: =IF(AND(AX$6>=$F22,AX$6<=$G22),"."," ") -> . | AY22: =IF(AND(AY$6>=$F22,AY$6<=$G22),"."," ") -> . | AZ22: =IF(AND(AZ$6>=$F22,AZ$6<=$G22),"."," ") -> . | BC22: =IF(AND(BC$6>=$F22,BC$6<=$G22),"."," ") | BD22: =IF(AND(BD$6>=$F22,BD$6<=$G22),"."," ") | BE22: =IF(AND(BE$6>=$F22,BE$6<=$G22),"."," ") | BF22: =IF(AND(BF$6>=$F22,BF$6<=$G22),"."," ") | BG22: =IF(AND(BG$6>=$F22,BG$6<=$G22),"."," ") | BJ22: =IF(AND(BJ$6>=$F22,BJ$6<=$G22),"."," ") | BK22: =IF(AND(BK$6>=$F22,BK$6<=$G22),"."," ") | BL22: =IF(AND(BL$6>=$F22,BL$6<=$G22),"."," ") | BM22: =IF(AND(BM$6>=$F22,BM$6<=$G22),"."," ") | BN22: =IF(AND(BN$6>=$F22,BN$6<=$G22),"."," ") | BQ22: =IF(AND(BQ$6>=$F22,BQ$6<=$G22),"."," ") | BR22: =IF(AND(BR$6>=$F22,BR$6<=$G22),"."," ") | BS22: =IF(AND(BS$6>=$F22,BS$6<=$G22),"."," ") | BT22: =IF(AND(BT$6>=$F22,BT$6<=$G22),"."," ") | BU22: =IF(AND(BU$6>=$F22,BU$6<=$G22),"."," ") | BX22: =IF(AND(BX$6>=$F22,BX$6<=$G22),"."," ") | BY22: =IF(AND(BY$6>=$F22,BY$6<=$G22),"."," ") | BZ22: =IF(AND(BZ$6>=$F22,BZ$6<=$G22),"."," ") | CA22: =IF(AND(CA$6>=$F22,CA$6<=$G22),"."," ") | CB22: =IF(AND(CB$6>=$F22,CB$6<=$G22),"."," ") | CE22: =IF(AND(CE$6>=$F22,CE$6<=$G22),"."," ") | CF22: =IF(AND(CF$6>=$F22,CF$6<=$G22),"."," ") | CG22: =IF(AND(CG$6>=$F22,CG$6<=$G22),"."," ") | CH22: =IF(AND(CH$6>=$F22,CH$6<=$G22),"."," ") | CI22: =IF(AND(CI$6>=$F22,CI$6<=$G22),"."," ") | CL22: =IF(AND(CL$6>=$F22,CL$6<=$G22),"."," ") | CM22: =IF(AND(CM$6>=$F22,CM$6<=$G22),"."," ") | CN22: =IF(AND(CN$6>=$F22,CN$6<=$G22),"."," ") | CO22: =IF(AND(CO$6>=$F22,CO$6<=$G22),"."," ") | CP22: =IF(AND(CP$6>=$F22,CP$6<=$G22),"."," ") | CS22: =IF(AND(CS$6>=$F22,CS$6<=$G22),"."," ") | CT22: =IF(AND(CT$6>=$F22,CT$6<=$G22),"."," ") | CU22: =IF(AND(CU$6>=$F22,CU$6<=$G22),"."," ") | CV22: =IF(AND(CV$6>=$F22,CV$6<=$G22),"."," ") | CW22: =IF(AND(CW$6>=$F22,CW$6<=$G22),"."," ") | CZ22: =IF(AND(CZ$6>=$F22,CZ$6<=$G22),"."," ") | DA22: =IF(AND(DA$6>=$F22,DA$6<=$G22),"."," ") | DB22: =IF(AND(DB$6>=$F22,DB$6<=$G22),"."," ") | DC22: =IF(AND(DC$6>=$F22,DC$6<=$G22),"."," ") | DD22: =IF(AND(DD$6>=$F22,DD$6<=$G22),"."," ") | DG22: =IF(AND(DG$6>=$F22,DG$6<=$G22),"."," ") | DH22: =IF(AND(DH$6>=$F22,DH$6<=$G22),"."," ") | DI22: =IF(AND(DI$6>=$F22,DI$6<=$G22),"."," ") | DJ22: =IF(AND(DJ$6>=$F22,DJ$6<=$G22),"."," ") | DK22: =IF(AND(DK$6>=$F22,DK$6<=$G22),"."," ") | DN22: =IF(AND(DN$6>=$F22,DN$6<=$G22),"."," ") | DO22: =IF(AND(DO$6>=$F22,DO$6<=$G22),"."," ") | DP22: =IF(AND(DP$6>=$F22,DP$6<=$G22),"."," ") | DQ22: =IF(AND(DQ$6>=$F22,DQ$6<=$G22),"."," ") | DR22: =IF(AND(DR$6>=$F22,DR$6<=$G22),"."," ") | DU22: =IF(AND(DU$6>=$F22,DU$6<=$G22),"."," ") | DV22: =IF(AND(DV$6>=$F22,DV$6<=$G22),"."," ") | DW22: =IF(AND(DW$6>=$F22,DW$6<=$G22),"."," ") | DX22: =IF(AND(DX$6>=$F22,DX$6<=$G22),"."," ") | DY22: =IF(AND(DY$6>=$F22,DY$6<=$G22),"."," ") | EB22: =IF(AND(EB$6>=$F22,EB$6<=$G22),"."," ") | EC22: =IF(AND(EC$6>=$F22,EC$6<=$G22),"."," ") | ED22: =IF(AND(ED$6>=$F22,ED$6<=$G22),"."," ") | EE22: =IF(AND(EE$6>=$F22,EE$6<=$G22),"."," ") | EF22: =IF(AND(EF$6>=$F22,EF$6<=$G22),"."," ") | EI22: =IF(AND(EI$6>=$F22,EI$6<=$G22),"."," ") | EJ22: =IF(AND(EJ$6>=$F22,EJ$6<=$G22),"."," ") | EK22: =IF(AND(EK$6>=$F22,EK$6<=$G22),"."," ") | EL22: =IF(AND(EL$6>=$F22,EL$6<=$G22),"."," ") | EM22: =IF(AND(EM$6>=$F22,EM$6<=$G22),"."," ") | EP22: =IF(AND(EP$6>=$F22,EP$6<=$G22),"."," ") | EQ22: =IF(AND(EQ$6>=$F22,EQ$6<=$G22),"."," ") | ER22: =IF(AND(ER$6>=$F22,ER$6<=$G22),"."," ") | ES22: =IF(AND(ES$6>=$F22,ES$6<=$G22),"."," ") | ET22: =IF(AND(ET$6>=$F22,ET$6<=$G22),"."," ") | EW22: =IF(AND(EW$6>=$F22,EW$6<=$G22),"."," ") | EX22: =IF(AND(EX$6>=$F22,EX$6<=$G22),"."," ") | EY22: =IF(AND(EY$6>=$F22,EY$6<=$G22),"."," ") | EZ22: =IF(AND(EZ$6>=$F22,EZ$6<=$G22),"."," ") | FA22: =IF(AND(FA$6>=$F22,FA$6<=$G22),"."," ") | FD22: =IF(AND(FD$6>=$F22,FD$6<=$G22),"."," ") | FE22: =IF(AND(FE$6>=$F22,FE$6<=$G22),"."," ") | FF22: =IF(AND(FF$6>=$F22,FF$6<=$G22),"."," ") | FG22: =IF(AND(FG$6>=$F22,FG$6<=$G22),"."," ") | FH22: =IF(AND(FH$6>=$F22,FH$6<=$G22),"."," ") | FK22: =IF(AND(FK$6>=$F22,FK$6<=$G22),"."," ") | FL22: =IF(AND(FL$6>=$F22,FL$6<=$G22),"."," ") | FM22: =IF(AND(FM$6>=$F22,FM$6<=$G22),"."," ") | FN22: =IF(AND(FN$6>=$F22,FN$6<=$G22),"."," ") | FO22: =IF(AND(FO$6>=$F22,FO$6<=$G22),"."," ") | FR22: =IF(AND(FR$6>=$F22,FR$6<=$G22),"."," ") | FS22: =IF(AND(FS$6>=$F22,FS$6<=$G22),"."," ") | FT22: =IF(AND(FT$6>=$F22,FT$6<=$G22),"."," ") | FU22: =IF(AND(FU$6>=$F22,FU$6<=$G22),"."," ") | FV22: =IF(AND(FV$6>=$F22,FV$6<=$G22),"."," ") | FY22: =IF(AND(FY$6>=$F22,FY$6<=$G22),"."," ") | FZ22: =IF(AND(FZ$6>=$F22,FZ$6<=$G22),"."," ") | GA22: =IF(AND(GA$6>=$F22,GA$6<=$G22),"."," ") | GB22: =IF(AND(GB$6>=$F22,GB$6<=$G22),"."," ") | GC22: =IF(AND(GC$6>=$F22,GC$6<=$G22),"."," ") | GF22: =IF(AND(GF$6>=$F22,GF$6<=$G22),"."," ") | GG22: =IF(AND(GG$6>=$F22,GG$6<=$G22),"."," ") | GH22: =IF(AND(GH$6>=$F22,GH$6<=$G22),"."," ") | GI22: =IF(AND(GI$6>=$F22,GI$6<=$G22),"."," ") | GJ22: =IF(AND(GJ$6>=$F22,GJ$6<=$G22),"."," ") | GM22: =IF(AND(GM$6>=$F22,GM$6<=$G22),"."," ") | GN22: =IF(AND(GN$6>=$F22,GN$6<=$G22),"."," ") | GO22: =IF(AND(GO$6>=$F22,GO$6<=$G22),"."," ") | GP22: =IF(AND(GP$6>=$F22,GP$6<=$G22),"."," ") | GQ22: =IF(AND(GQ$6>=$F22,GQ$6<=$G22),"."," ") | GT22: =IF(AND(GT$6>=$F22,GT$6<=$G22),"."," ") | GU22: =IF(AND(GU$6>=$F22,GU$6<=$G22),"."," ") | GV22: =IF(AND(GV$6>=$F22,GV$6<=$G22),"."," ") | GW22: =IF(AND(GW$6>=$F22,GW$6<=$G22),"."," ") | GX22: =IF(AND(GX$6>=$F22,GX$6<=$G22),"."," ") | HA22: =IF(AND(HA$6>=$F22,HA$6<=$G22),"."," ") | HB22: =IF(AND(HB$6>=$F22,HB$6<=$G22),"."," ") | HC22: =IF(AND(HC$6>=$F22,HC$6<=$G22),"."," ") | HD22: =IF(AND(HD$6>=$F22,HD$6<=$G22),"."," ") | HE22: =IF(AND(HE$6>=$F22,HE$6<=$G22),"."," ") | HH22: =IF(AND(HH$6>=$F22,HH$6<=$G22),"."," ") | HI22: =IF(AND(HI$6>=$F22,HI$6<=$G22),"."," ") | HJ22: =IF(AND(HJ$6>=$F22,HJ$6<=$G22),"."," ") | HK22: =IF(AND(HK$6>=$F22,HK$6<=$G22),"."," ") | HL22: =IF(AND(HL$6>=$F22,HL$6<=$G22),"."," ") | HO22: =IF(AND(HO$6>=$F22,HO$6<=$G22),"."," ") | HP22: =IF(AND(HP$6>=$F22,HP$6<=$G22),"."," ") | HQ22: =IF(AND(HQ$6>=$F22,HQ$6<=$G22),"."," ") | HR22: =IF(AND(HR$6>=$F22,HR$6<=$G22),"."," ") | HS22: =IF(AND(HS$6>=$F22,HS$6<=$G22),"."," ") | HV22: =IF(AND(HV$6>=$F22,HV$6<=$G22),"."," ") | HW22: =IF(AND(HW$6>=$F22,HW$6<=$G22),"."," ") | HX22: =IF(AND(HX$6>=$F22,HX$6<=$G22),"."," ") | HY22: =IF(AND(HY$6>=$F22,HY$6<=$G22),"."," ") | HZ22: =IF(AND(HZ$6>=$F22,HZ$6<=$G22),"."," ") | IC22: =IF(AND(IC$6>=$F22,IC$6<=$G22),"."," ") | ID22: =IF(AND(ID$6>=$F22,ID$6<=$G22),"."," ") | IE22: =IF(AND(IE$6>=$F22,IE$6<=$G22),"."," ") | IF22: =IF(AND(IF$6>=$F22,IF$6<=$G22),"."," ") | IG22: =IF(AND(IG$6>=$F22,IG$6<=$G22),"."," ") | IJ22: =IF(AND(IJ$6>=$F22,IJ$6<=$G22),"."," ") | IK22: =IF(AND(IK$6>=$F22,IK$6<=$G22),"."," ") | IL22: =IF(AND(IL$6>=$F22,IL$6<=$G22),"."," ") | IM22: =IF(AND(IM$6>=$F22,IM$6<=$G22),"."," ") | IN22: =IF(AND(IN$6>=$F22,IN$6<=$G22),"."," ") | IQ22: =IF(AND(IQ$6>=$F22,IQ$6<=$G22),"."," ") | IR22: =IF(AND(IR$6>=$F22,IR$6<=$G22),"."," ") | IS22: =IF(AND(IS$6>=$F22,IS$6<=$G22),"."," ") | IT22: =IF(AND(IT$6>=$F22,IT$6<=$G22),"."," ") | IU22: =IF(AND(IU$6>=$F22,IU$6<=$G22),"."," ") | IX22: =IF(AND(IX$6>=$F22,IX$6<=$G22),"."," ") | IY22: =IF(AND(IY$6>=$F22,IY$6<=$G22),"."," ") | IZ22: =IF(AND(IZ$6>=$F22,IZ$6<=$G22),"."," ") | JA22: =IF(AND(JA$6>=$F22,JA$6<=$G22),"."," ") | JB22: =IF(AND(JB$6>=$F22,JB$6<=$G22),"."," ") | JE22: =IF(AND(JE$6>=$F22,JE$6<=$G22),"."," ") | JF22: =IF(AND(JF$6>=$F22,JF$6<=$G22),"."," ") | JG22: =IF(AND(JG$6>=$F22,JG$6<=$G22),"."," ") | JH22: =IF(AND(JH$6>=$F22,JH$6<=$G22),"."," ") | JI22: =IF(AND(JI$6>=$F22,JI$6<=$G22),"."," ")
B23: 15 | C23: Build Component 1 | D23: Bob | E23: 13 | F23: =VLOOKUP(E23,$B$6:$G$150,6,FALSE) + 1 -> 42535 | G23: =WORKDAY(F23,H23-1,Config!D22:D41) -> 42535 | H23: 1 | I23: 0 | J23: =IF(((NETWORKDAYS(F23,TODAY(),Data!C18:C37)*100)/H23)/100 > 0,((NETWORKDAYS(F23,TODAY(),Data!C18:C37)*100)/H23)/100,0) -> 1644 | K23: =IF(J23>1, "100%",$J23) -> 100% | L23: =K23-I23 -> 1 | M23: =IF(AND(M$6>=$F23,M$6<=$G23),"."," ") | N23: =IF(AND(N$6>=$F23,N$6<=$G23),"."," ") | O23: =IF(AND(O$6>=$F23,O$6<=$G23),"."," ") | P23: =IF(AND(P$6>=$F23,P$6<=$G23),"."," ") | Q23: =IF(AND(Q$6>=$F23,Q$6<=$G23),"."," ") | T23: =IF(AND(T$6>=$F23,T$6<=$G23),"."," ") | U23: =IF(AND(U$6>=$F23,U$6<=$G23),"."," ") | V23: =IF(AND(V$6>=$F23,V$6<=$G23),"."," ") | W23: =IF(AND(W$6>=$F23,W$6<=$G23),"."," ") | X23: =IF(AND(X$6>=$F23,X$6<=$G23),"."," ") | AA23: =IF(AND(AA$6>=$F23,AA$6<=$G23),"."," ") | AB23: =IF(AND(AB$6>=$F23,AB$6<=$G23),"."," ") | AC23: =IF(AND(AC$6>=$F23,AC$6<=$G23),"."," ") | AD23: =IF(AND(AD$6>=$F23,AD$6<=$G23),"."," ") | AE23: =IF(AND(AE$6>=$F23,AE$6<=$G23),"."," ") | AH23: =IF(AND(AH$6>=$F23,AH$6<=$G23),"."," ") | AI23: =IF(AND(AI$6>=$F23,AI$6<=$G23),"."," ") | AJ23: =IF(AND(AJ$6>=$F23,AJ$6<=$G23),"."," ") | AK23: =IF(AND(AK$6>=$F23,AK$6<=$G23),"."," ") | AL23: =IF(AND(AL$6>=$F23,AL$6<=$G23),"."," ") | AO23: =IF(AND(AO$6>=$F23,AO$6<=$G23),"."," ") | AP23: =IF(AND(AP$6>=$F23,AP$6<=$G23),"."," ") | AQ23: =IF(AND(AQ$6>=$F23,AQ$6<=$G23),"."," ") | AR23: =IF(AND(AR$6>=$F23,AR$6<=$G23),"."," ") | AS23: =IF(AND(AS$6>=$F23,AS$6<=$G23),"."," ") | AV23: =IF(AND(AV$6>=$F23,AV$6<=$G23),"."," ") | AW23: =IF(AND(AW$6>=$F23,AW$6<=$G23),"."," ") | AX23: =IF(AND(AX$6>=$F23,AX$6<=$G23),"."," ") | AY23: =IF(AND(AY$6>=$F23,AY$6<=$G23),"."," ") | AZ23: =IF(AND(AZ$6>=$F23,AZ$6<=$G23),"."," ") | BC23: =IF(AND(BC$6>=$F23,BC$6<=$G23),"."," ") | BD23: =IF(AND(BD$6>=$F23,BD$6<=$G23),"."," ") | BE23: =IF(AND(BE$6>=$F23,BE$6<=$G23),"."," ") | BF23: =IF(AND(BF$6>=$F23,BF$6<=$G23),"."," ") | BG23: =IF(AND(BG$6>=$F23,BG$6<=$G23),"."," ") | BJ23: =IF(AND(BJ$6>=$F23,BJ$6<=$G23),"."," ") | BK23: =IF(AND(BK$6>=$F23,BK$6<=$G23),"."," ") | BL23: =IF(AND(BL$6>=$F23,BL$6<=$G23),"."," ") | BM23: =IF(AND(BM$6>=$F23,BM$6<=$G23),"."," ") | BN23: =IF(AND(BN$6>=$F23,BN$6<=$G23),"."," ") | BQ23: =IF(AND(BQ$6>=$F23,BQ$6<=$G23),"."," ") | BR23: =IF(AND(BR$6>=$F23,BR$6<=$G23),"."," ") | BS23: =IF(AND(BS$6>=$F23,BS$6<=$G23),"."," ") | BT23: =IF(AND(BT$6>=$F23,BT$6<=$G23),"."," ") | BU23: =IF(AND(BU$6>=$F23,BU$6<=$G23),"."," ") | BX23: =IF(AND(BX$6>=$F23,BX$6<=$G23),"."," ") | BY23: =IF(AND(BY$6>=$F23,BY$6<=$G23),"."," ") | BZ23: =IF(AND(BZ$6>=$F23,BZ$6<=$G23),"."," ") | CA23: =IF(AND(CA$6>=$F23,CA$6<=$G23),"."," ") | CB23: =IF(AND(CB$6>=$F23,CB$6<=$G23),"."," ") | CE23: =IF(AND(CE$6>=$F23,CE$6<=$G23),"."," ") | CF23: =IF(AND(CF$6>=$F23,CF$6<=$G23),"."," ") | CG23: =IF(AND(CG$6>=$F23,CG$6<=$G23),"."," ") | CH23: =IF(AND(CH$6>=$F23,CH$6<=$G23),"."," ") | CI23: =IF(AND(CI$6>=$F23,CI$6<=$G23),"."," ") | CL23: =IF(AND(CL$6>=$F23,CL$6<=$G23),"."," ") | CM23: =IF(AND(CM$6>=$F23,CM$6<=$G23),"."," ") | CN23: =IF(AND(CN$6>=$F23,CN$6<=$G23),"."," ") | CO23: =IF(AND(CO$6>=$F23,CO$6<=$G23),"."," ") | CP23: =IF(AND(CP$6>=$F23,CP$6<=$G23),"."," ") | CS23: =IF(AND(CS$6>=$F23,CS$6<=$G23),"."," ") | CT23: =IF(AND(CT$6>=$F23,CT$6<=$G23),"."," ") | CU23: =IF(AND(CU$6>=$F23,CU$6<=$G23),"."," ") | CV23: =IF(AND(CV$6>=$F23,CV$6<=$G23),"."," ") | CW23: =IF(AND(CW$6>=$F23,CW$6<=$G23),"."," ") | CZ23: =IF(AND(CZ$6>=$F23,CZ$6<=$G23),"."," ") | DA23: =IF(AND(DA$6>=$F23,DA$6<=$G23),"."," ") | DB23: =IF(AND(DB$6>=$F23,DB$6<=$G23),"."," ") | DC23: =IF(AND(DC$6>=$F23,DC$6<=$G23),"."," ") | DD23: =IF(AND(DD$6>=$F23,DD$6<=$G23),"."," ") | DG23: =IF(AND(DG$6>=$F23,DG$6<=$G23),"."," ") | DH23: =IF(AND(DH$6>=$F23,DH$6<=$G23),"."," ") | DI23: =IF(AND(DI$6>=$F23,DI$6<=$G23),"."," ") | DJ23: =IF(AND(DJ$6>=$F23,DJ$6<=$G23),"."," ") | DK23: =IF(AND(DK$6>=$F23,DK$6<=$G23),"."," ") | DN23: =IF(AND(DN$6>=$F23,DN$6<=$G23),"."," ") | DO23: =IF(AND(DO$6>=$F23,DO$6<=$G23),"."," ") | DP23: =IF(AND(DP$6>=$F23,DP$6<=$G23),"."," ") | DQ23: =IF(AND(DQ$6>=$F23,DQ$6<=$G23),"."," ") | DR23: =IF(AND(DR$6>=$F23,DR$6<=$G23),"."," ") | DU23: =IF(AND(DU$6>=$F23,DU$6<=$G23),"."," ") | DV23: =IF(AND(DV$6>=$F23,DV$6<=$G23),"."," ") | DW23: =IF(AND(DW$6>=$F23,DW$6<=$G23),"."," ") | DX23: =IF(AND(DX$6>=$F23,DX$6<=$G23),"."," ") | DY23: =IF(AND(DY$6>=$F23,DY$6<=$G23),"."," ") | EB23: =IF(AND(EB$6>=$F23,EB$6<=$G23),"."," ") | EC23: =IF(AND(EC$6>=$F23,EC$6<=$G23),"."," ") | ED23: =IF(AND(ED$6>=$F23,ED$6<=$G23),"."," ") | EE23: =IF(AND(EE$6>=$F23,EE$6<=$G23),"."," ") | EF23: =IF(AND(EF$6>=$F23,EF$6<=$G23),"."," ") | EI23: =IF(AND(EI$6>=$F23,EI$6<=$G23),"."," ") | EJ23: =IF(AND(EJ$6>=$F23,EJ$6<=$G23),"."," ") | EK23: =IF(AND(EK$6>=$F23,EK$6<=$G23),"."," ") | EL23: =IF(AND(EL$6>=$F23,EL$6<=$G23),"."," ") | EM23: =IF(AND(EM$6>=$F23,EM$6<=$G23),"."," ") | EP23: =IF(AND(EP$6>=$F23,EP$6<=$G23),"."," ") | EQ23: =IF(AND(EQ$6>=$F23,EQ$6<=$G23),"."," ") | ER23: =IF(AND(ER$6>=$F23,ER$6<=$G23),"."," ") | ES23: =IF(AND(ES$6>=$F23,ES$6<=$G23),"."," ") | ET23: =IF(AND(ET$6>=$F23,ET$6<=$G23),"."," ") | EW23: =IF(AND(EW$6>=$F23,EW$6<=$G23),"."," ") | EX23: =IF(AND(EX$6>=$F23,EX$6<=$G23),"."," ") | EY23: =IF(AND(EY$6>=$F23,EY$6<=$G23),"."," ") | EZ23: =IF(AND(EZ$6>=$F23,EZ$6<=$G23),"."," ") | FA23: =IF(AND(FA$6>=$F23,FA$6<=$G23),"."," ") | FD23: =IF(AND(FD$6>=$F23,FD$6<=$G23),"."," ") | FE23: =IF(AND(FE$6>=$F23,FE$6<=$G23),"."," ") | FF23: =IF(AND(FF$6>=$F23,FF$6<=$G23),"."," ") | FG23: =IF(AND(FG$6>=$F23,FG$6<=$G23),"."," ") | FH23: =IF(AND(FH$6>=$F23,FH$6<=$G23),"."," ") | FK23: =IF(AND(FK$6>=$F23,FK$6<=$G23),"."," ") | FL23: =IF(AND(FL$6>=$F23,FL$6<=$G23),"."," ") | FM23: =IF(AND(FM$6>=$F23,FM$6<=$G23),"."," ") | FN23: =IF(AND(FN$6>=$F23,FN$6<=$G23),"."," ") | FO23: =IF(AND(FO$6>=$F23,FO$6<=$G23),"."," ") | FR23: =IF(AND(FR$6>=$F23,FR$6<=$G23),"."," ") | FS23: =IF(AND(FS$6>=$F23,FS$6<=$G23),"."," ") | FT23: =IF(AND(FT$6>=$F23,FT$6<=$G23),"."," ") | FU23: =IF(AND(FU$6>=$F23,FU$6<=$G23),"."," ") | FV23: =IF(AND(FV$6>=$F23,FV$6<=$G23),"."," ") | FY23: =IF(AND(FY$6>=$F23,FY$6<=$G23),"."," ") | FZ23: =IF(AND(FZ$6>=$F23,FZ$6<=$G23),"."," ") | GA23: =IF(AND(GA$6>=$F23,GA$6<=$G23),"."," ") | GB23: =IF(AND(GB$6>=$F23,GB$6<=$G23),"."," ") | GC23: =IF(AND(GC$6>=$F23,GC$6<=$G23),"."," ") | GF23: =IF(AND(GF$6>=$F23,GF$6<=$G23),"."," ") | GG23: =IF(AND(GG$6>=$F23,GG$6<=$G23),"."," ") | GH23: =IF(AND(GH$6>=$F23,GH$6<=$G23),"."," ") | GI23: =IF(AND(GI$6>=$F23,GI$6<=$G23),"."," ") | GJ23: =IF(AND(GJ$6>=$F23,GJ$6<=$G23),"."," ") | GM23: =IF(AND(GM$6>=$F23,GM$6<=$G23),"."," ") | GN23: =IF(AND(GN$6>=$F23,GN$6<=$G23),"."," ") | GO23: =IF(AND(GO$6>=$F23,GO$6<=$G23),"."," ") | GP23: =IF(AND(GP$6>=$F23,GP$6<=$G23),"."," ") | GQ23: =IF(AND(GQ$6>=$F23,GQ$6<=$G23),"."," ") | GT23: =IF(AND(GT$6>=$F23,GT$6<=$G23),"."," ") | GU23: =IF(AND(GU$6>=$F23,GU$6<=$G23),"."," ") | GV23: =IF(AND(GV$6>=$F23,GV$6<=$G23),"."," ") | GW23: =IF(AND(GW$6>=$F23,GW$6<=$G23),"."," ") | GX23: =IF(AND(GX$6>=$F23,GX$6<=$G23),"."," ") | HA23: =IF(AND(HA$6>=$F23,HA$6<=$G23),"."," ") | HB23: =IF(AND(HB$6>=$F23,HB$6<=$G23),"."," ") | HC23: =IF(AND(HC$6>=$F23,HC$6<=$G23),"."," ") | HD23: =IF(AND(HD$6>=$F23,HD$6<=$G23),"."," ") | HE23: =IF(AND(HE$6>=$F23,HE$6<=$G23),"."," ") | HH23: =IF(AND(HH$6>=$F23,HH$6<=$G23),"."," ") | HI23: =IF(AND(HI$6>=$F23,HI$6<=$G23),"."," ") | HJ23: =IF(AND(HJ$6>=$F23,HJ$6<=$G23),"."," ") | HK23: =IF(AND(HK$6>=$F23,HK$6<=$G23),"."," ") | HL23: =IF(AND(HL$6>=$F23,HL$6<=$G23),"."," ") | HO23: =IF(AND(HO$6>=$F23,HO$6<=$G23),"."," ") | HP23: =IF(AND(HP$6>=$F23,HP$6<=$G23),"."," ") | HQ23: =IF(AND(HQ$6>=$F23,HQ$6<=$G23),"."," ") | HR23: =IF(AND(HR$6>=$F23,HR$6<=$G23),"."," ") | HS23: =IF(AND(HS$6>=$F23,HS$6<=$G23),"."," ") | HV23: =IF(AND(HV$6>=$F23,HV$6<=$G23),"."," ") | HW23: =IF(AND(HW$6>=$F23,HW$6<=$G23),"."," ") | HX23: =IF(AND(HX$6>=$F23,HX$6<=$G23),"."," ") | HY23: =IF(AND(HY$6>=$F23,HY$6<=$G23),"."," ") | HZ23: =IF(AND(HZ$6>=$F23,HZ$6<=$G23),"."," ") | IC23: =IF(AND(IC$6>=$F23,IC$6<=$G23),"."," ") | ID23: =IF(AND(ID$6>=$F23,ID$6<=$G23),"."," ") | IE23: =IF(AND(IE$6>=$F23,IE$6<=$G23),"."," ") | IF23: =IF(AND(IF$6>=$F23,IF$6<=$G23),"."," ") | IG23: =IF(AND(IG$6>=$F23,IG$6<=$G23),"."," ") | IJ23: =IF(AND(IJ$6>=$F23,IJ$6<=$G23),"."," ") | IK23: =IF(AND(IK$6>=$F23,IK$6<=$G23),"."," ") | IL23: =IF(AND(IL$6>=$F23,IL$6<=$G23),"."," ") | IM23: =IF(AND(IM$6>=$F23,IM$6<=$G23),"."," ") | IN23: =IF(AND(IN$6>=$F23,IN$6<=$G23),"."," ") | IQ23: =IF(AND(IQ$6>=$F23,IQ$6<=$G23),"."," ") | IR23: =IF(AND(IR$6>=$F23,IR$6<=$G23),"."," ") | IS23: =IF(AND(IS$6>=$F23,IS$6<=$G23),"."," ") | IT23: =IF(AND(IT$6>=$F23,IT$6<=$G23),"."," ") | IU23: =IF(AND(IU$6>=$F23,IU$6<=$G23),"."," ") | IX23: =IF(AND(IX$6>=$F23,IX$6<=$G23),"."," ") | IY23: =IF(AND(IY$6>=$F23,IY$6<=$G23),"."," ") | IZ23: =IF(AND(IZ$6>=$F23,IZ$6<=$G23),"."," ") | JA23: =IF(AND(JA$6>=$F23,JA$6<=$G23),"."," ") | JB23: =IF(AND(JB$6>=$F23,JB$6<=$G23),"."," ") | JE23: =IF(AND(JE$6>=$F23,JE$6<=$G23),"."," ") | JF23: =IF(AND(JF$6>=$F23,JF$6<=$G23),"."," ") | JG23: =IF(AND(JG$6>=$F23,JG$6<=$G23),"."," ") | JH23: =IF(AND(JH$6>=$F23,JH$6<=$G23),"."," ") | JI23: =IF(AND(JI$6>=$F23,JI$6<=$G23),"."," ")
B24: 16 | C24: Build Component 2 | D24: Bob | E24: 14 | F24: =VLOOKUP(E24,$B$6:$G$150,6,FALSE) + 1 -> 42537 | G24: =WORKDAY(F24,H24-1,Config!D23:D42) -> 42541 | H24: 3 | I24: 0 | J24: =IF(((NETWORKDAYS(F24,TODAY(),Data!C19:C38)*100)/H24)/100 > 0,((NETWORKDAYS(F24,TODAY(),Data!C19:C38)*100)/H24)/100,0) -> 547.33333 | K24: =IF(J24>1, "100%",$J24) -> 100% | L24: =K24-I24 -> 1 | M24: =IF(AND(M$6>=$F24,M$6<=$G24),"."," ") | N24: =IF(AND(N$6>=$F24,N$6<=$G24),"."," ") | O24: =IF(AND(O$6>=$F24,O$6<=$G24),"."," ") | P24: =IF(AND(P$6>=$F24,P$6<=$G24),"."," ") | Q24: =IF(AND(Q$6>=$F24,Q$6<=$G24),"."," ") | T24: =IF(AND(T$6>=$F24,T$6<=$G24),"."," ") | U24: =IF(AND(U$6>=$F24,U$6<=$G24),"."," ") | V24: =IF(AND(V$6>=$F24,V$6<=$G24),"."," ") | W24: =IF(AND(W$6>=$F24,W$6<=$G24),"."," ") | X24: =IF(AND(X$6>=$F24,X$6<=$G24),"."," ") | AA24: =IF(AND(AA$6>=$F24,AA$6<=$G24),"."," ") | AB24: =IF(AND(AB$6>=$F24,AB$6<=$G24),"."," ") | AC24: =IF(AND(AC$6>=$F24,AC$6<=$G24),"."," ") | AD24: =IF(AND(AD$6>=$F24,AD$6<=$G24),"."," ") | AE24: =IF(AND(AE$6>=$F24,AE$6<=$G24),"."," ") | AH24: =IF(AND(AH$6>=$F24,AH$6<=$G24),"."," ") | AI24: =IF(AND(AI$6>=$F24,AI$6<=$G24),"."," ") | AJ24: =IF(AND(AJ$6>=$F24,AJ$6<=$G24),"."," ") | AK24: =IF(AND(AK$6>=$F24,AK$6<=$G24),"."," ") | AL24: =IF(AND(AL$6>=$F24,AL$6<=$G24),"."," ") | AO24: =IF(AND(AO$6>=$F24,AO$6<=$G24),"."," ") | AP24: =IF(AND(AP$6>=$F24,AP$6<=$G24),"."," ") | AQ24: =IF(AND(AQ$6>=$F24,AQ$6<=$G24),"."," ") | AR24: =IF(AND(AR$6>=$F24,AR$6<=$G24),"."," ") | AS24: =IF(AND(AS$6>=$F24,AS$6<=$G24),"."," ") | AV24: =IF(AND(AV$6>=$F24,AV$6<=$G24),"."," ") | AW24: =IF(AND(AW$6>=$F24,AW$6<=$G24),"."," ") | AX24: =IF(AND(AX$6>=$F24,AX$6<=$G24),"."," ") | AY24: =IF(AND(AY$6>=$F24,AY$6<=$G24),"."," ") | AZ24: =IF(AND(AZ$6>=$F24,AZ$6<=$G24),"."," ") | BC24: =IF(AND(BC$6>=$F24,BC$6<=$G24),"."," ") -> . | BD24: =IF(AND(BD$6>=$F24,BD$6<=$G24),"."," ") -> . | BE24: =IF(AND(BE$6>=$F24,BE$6<=$G24),"."," ") -> . | BF24: =IF(AND(BF$6>=$F24,BF$6<=$G24),"."," ") -> . | BG24: =IF(AND(BG$6>=$F24,BG$6<=$G24),"."," ") -> . | BJ24: =IF(AND(BJ$6>=$F24,BJ$6<=$G24),"."," ") | BK24: =IF(AND(BK$6>=$F24,BK$6<=$G24),"."," ") | BL24: =IF(AND(BL$6>=$F24,BL$6<=$G24),"."," ") | BM24: =IF(AND(BM$6>=$F24,BM$6<=$G24),"."," ") | BN24: =IF(AND(BN$6>=$F24,BN$6<=$G24),"."," ") | BQ24: =IF(AND(BQ$6>=$F24,BQ$6<=$G24),"."," ") | BR24: =IF(AND(BR$6>=$F24,BR$6<=$G24),"."," ") | BS24: =IF(AND(BS$6>=$F24,BS$6<=$G24),"."," ") | BT24: =IF(AND(BT$6>=$F24,BT$6<=$G24),"."," ") | BU24: =IF(AND(BU$6>=$F24,BU$6<=$G24),"."," ") | BX24: =IF(AND(BX$6>=$F24,BX$6<=$G24),"."," ") | BY24: =IF(AND(BY$6>=$F24,BY$6<=$G24),"."," ") | BZ24: =IF(AND(BZ$6>=$F24,BZ$6<=$G24),"."," ") | CA24: =IF(AND(CA$6>=$F24,CA$6<=$G24),"."," ") | CB24: =IF(AND(CB$6>=$F24,CB$6<=$G24),"."," ") | CE24: =IF(AND(CE$6>=$F24,CE$6<=$G24),"."," ") | CF24: =IF(AND(CF$6>=$F24,CF$6<=$G24),"."," ") | CG24: =IF(AND(CG$6>=$F24,CG$6<=$G24),"."," ") | CH24: =IF(AND(CH$6>=$F24,CH$6<=$G24),"."," ") | CI24: =IF(AND(CI$6>=$F24,CI$6<=$G24),"."," ") | CL24: =IF(AND(CL$6>=$F24,CL$6<=$G24),"."," ") | CM24: =IF(AND(CM$6>=$F24,CM$6<=$G24),"."," ") | CN24: =IF(AND(CN$6>=$F24,CN$6<=$G24),"."," ") | CO24: =IF(AND(CO$6>=$F24,CO$6<=$G24),"."," ") | CP24: =IF(AND(CP$6>=$F24,CP$6<=$G24),"."," ") | CS24: =IF(AND(CS$6>=$F24,CS$6<=$G24),"."," ") | CT24: =IF(AND(CT$6>=$F24,CT$6<=$G24),"."," ") | CU24: =IF(AND(CU$6>=$F24,CU$6<=$G24),"."," ") | CV24: =IF(AND(CV$6>=$F24,CV$6<=$G24),"."," ") | CW24: =IF(AND(CW$6>=$F24,CW$6<=$G24),"."," ") | CZ24: =IF(AND(CZ$6>=$F24,CZ$6<=$G24),"."," ") | DA24: =IF(AND(DA$6>=$F24,DA$6<=$G24),"."," ") | DB24: =IF(AND(DB$6>=$F24,DB$6<=$G24),"."," ") | DC24: =IF(AND(DC$6>=$F24,DC$6<=$G24),"."," ") | DD24: =IF(AND(DD$6>=$F24,DD$6<=$G24),"."," ") | DG24: =IF(AND(DG$6>=$F24,DG$6<=$G24),"."," ") | DH24: =IF(AND(DH$6>=$F24,DH$6<=$G24),"."," ") | DI24: =IF(AND(DI$6>=$F24,DI$6<=$G24),"."," ") | DJ24: =IF(AND(DJ$6>=$F24,DJ$6<=$G24),"."," ") | DK24: =IF(AND(DK$6>=$F24,DK$6<=$G24),"."," ") | DN24: =IF(AND(DN$6>=$F24,DN$6<=$G24),"."," ") | DO24: =IF(AND(DO$6>=$F24,DO$6<=$G24),"."," ") | DP24: =IF(AND(DP$6>=$F24,DP$6<=$G24),"."," ") | DQ24: =IF(AND(DQ$6>=$F24,DQ$6<=$G24),"."," ") | DR24: =IF(AND(DR$6>=$F24,DR$6<=$G24),"."," ") | DU24: =IF(AND(DU$6>=$F24,DU$6<=$G24),"."," ") | DV24: =IF(AND(DV$6>=$F24,DV$6<=$G24),"."," ") | DW24: =IF(AND(DW$6>=$F24,DW$6<=$G24),"."," ") | DX24: =IF(AND(DX$6>=$F24,DX$6<=$G24),"."," ") | DY24: =IF(AND(DY$6>=$F24,DY$6<=$G24),"."," ") | EB24: =IF(AND(EB$6>=$F24,EB$6<=$G24),"."," ") | EC24: =IF(AND(EC$6>=$F24,EC$6<=$G24),"."," ") | ED24: =IF(AND(ED$6>=$F24,ED$6<=$G24),"."," ") | EE24: =IF(AND(EE$6>=$F24,EE$6<=$G24),"."," ") | EF24: =IF(AND(EF$6>=$F24,EF$6<=$G24),"."," ") | EI24: =IF(AND(EI$6>=$F24,EI$6<=$G24),"."," ") | EJ24: =IF(AND(EJ$6>=$F24,EJ$6<=$G24),"."," ") | EK24: =IF(AND(EK$6>=$F24,EK$6<=$G24),"."," ") | EL24: =IF(AND(EL$6>=$F24,EL$6<=$G24),"."," ") | EM24: =IF(AND(EM$6>=$F24,EM$6<=$G24),"."," ") | EP24: =IF(AND(EP$6>=$F24,EP$6<=$G24),"."," ") | EQ24: =IF(AND(EQ$6>=$F24,EQ$6<=$G24),"."," ") | ER24: =IF(AND(ER$6>=$F24,ER$6<=$G24),"."," ") | ES24: =IF(AND(ES$6>=$F24,ES$6<=$G24),"."," ") | ET24: =IF(AND(ET$6>=$F24,ET$6<=$G24),"."," ") | EW24: =IF(AND(EW$6>=$F24,EW$6<=$G24),"."," ") | EX24: =IF(AND(EX$6>=$F24,EX$6<=$G24),"."," ") | EY24: =IF(AND(EY$6>=$F24,EY$6<=$G24),"."," ") | EZ24: =IF(AND(EZ$6>=$F24,EZ$6<=$G24),"."," ") | FA24: =IF(AND(FA$6>=$F24,FA$6<=$G24),"."," ") | FD24: =IF(AND(FD$6>=$F24,FD$6<=$G24),"."," ") | FE24: =IF(AND(FE$6>=$F24,FE$6<=$G24),"."," ") | FF24: =IF(AND(FF$6>=$F24,FF$6<=$G24),"."," ") | FG24: =IF(AND(FG$6>=$F24,FG$6<=$G24),"."," ") | FH24: =IF(AND(FH$6>=$F24,FH$6<=$G24),"."," ") | FK24: =IF(AND(FK$6>=$F24,FK$6<=$G24),"."," ") | FL24: =IF(AND(FL$6>=$F24,FL$6<=$G24),"."," ") | FM24: =IF(AND(FM$6>=$F24,FM$6<=$G24),"."," ") | FN24: =IF(AND(FN$6>=$F24,FN$6<=$G24),"."," ") | FO24: =IF(AND(FO$6>=$F24,FO$6<=$G24),"."," ") | FR24: =IF(AND(FR$6>=$F24,FR$6<=$G24),"."," ") | FS24: =IF(AND(FS$6>=$F24,FS$6<=$G24),"."," ") | FT24: =IF(AND(FT$6>=$F24,FT$6<=$G24),"."," ") | FU24: =IF(AND(FU$6>=$F24,FU$6<=$G24),"."," ") | FV24: =IF(AND(FV$6>=$F24,FV$6<=$G24),"."," ") | FY24: =IF(AND(FY$6>=$F24,FY$6<=$G24),"."," ") | FZ24: =IF(AND(FZ$6>=$F24,FZ$6<=$G24),"."," ") | GA24: =IF(AND(GA$6>=$F24,GA$6<=$G24),"."," ") | GB24: =IF(AND(GB$6>=$F24,GB$6<=$G24),"."," ") | GC24: =IF(AND(GC$6>=$F24,GC$6<=$G24),"."," ") | GF24: =IF(AND(GF$6>=$F24,GF$6<=$G24),"."," ") | GG24: =IF(AND(GG$6>=$F24,GG$6<=$G24),"."," ") | GH24: =IF(AND(GH$6>=$F24,GH$6<=$G24),"."," ") | GI24: =IF(AND(GI$6>=$F24,GI$6<=$G24),"."," ") | GJ24: =IF(AND(GJ$6>=$F24,GJ$6<=$G24),"."," ") | GM24: =IF(AND(GM$6>=$F24,GM$6<=$G24),"."," ") | GN24: =IF(AND(GN$6>=$F24,GN$6<=$G24),"."," ") | GO24: =IF(AND(GO$6>=$F24,GO$6<=$G24),"."," ") | GP24: =IF(AND(GP$6>=$F24,GP$6<=$G24),"."," ") | GQ24: =IF(AND(GQ$6>=$F24,GQ$6<=$G24),"."," ") | GT24: =IF(AND(GT$6>=$F24,GT$6<=$G24),"."," ") | GU24: =IF(AND(GU$6>=$F24,GU$6<=$G24),"."," ") | GV24: =IF(AND(GV$6>=$F24,GV$6<=$G24),"."," ") | GW24: =IF(AND(GW$6>=$F24,GW$6<=$G24),"."," ") | GX24: =IF(AND(GX$6>=$F24,GX$6<=$G24),"."," ") | HA24: =IF(AND(HA$6>=$F24,HA$6<=$G24),"."," ") | HB24: =IF(AND(HB$6>=$F24,HB$6<=$G24),"."," ") | HC24: =IF(AND(HC$6>=$F24,HC$6<=$G24),"."," ") | HD24: =IF(AND(HD$6>=$F24,HD$6<=$G24),"."," ") | HE24: =IF(AND(HE$6>=$F24,HE$6<=$G24),"."," ") | HH24: =IF(AND(HH$6>=$F24,HH$6<=$G24),"."," ") | HI24: =IF(AND(HI$6>=$F24,HI$6<=$G24),"."," ") | HJ24: =IF(AND(HJ$6>=$F24,HJ$6<=$G24),"."," ") | HK24: =IF(AND(HK$6>=$F24,HK$6<=$G24),"."," ") | HL24: =IF(AND(HL$6>=$F24,HL$6<=$G24),"."," ") | HO24: =IF(AND(HO$6>=$F24,HO$6<=$G24),"."," ") | HP24: =IF(AND(HP$6>=$F24,HP$6<=$G24),"."," ") | HQ24: =IF(AND(HQ$6>=$F24,HQ$6<=$G24),"."," ") | HR24: =IF(AND(HR$6>=$F24,HR$6<=$G24),"."," ") | HS24: =IF(AND(HS$6>=$F24,HS$6<=$G24),"."," ") | HV24: =IF(AND(HV$6>=$F24,HV$6<=$G24),"."," ") | HW24: =IF(AND(HW$6>=$F24,HW$6<=$G24),"."," ") | HX24: =IF(AND(HX$6>=$F24,HX$6<=$G24),"."," ") | HY24: =IF(AND(HY$6>=$F24,HY$6<=$G24),"."," ") | HZ24: =IF(AND(HZ$6>=$F24,HZ$6<=$G24),"."," ") | IC24: =IF(AND(IC$6>=$F24,IC$6<=$G24),"."," ") | ID24: =IF(AND(ID$6>=$F24,ID$6<=$G24),"."," ") | IE24: =IF(AND(IE$6>=$F24,IE$6<=$G24),"."," ") | IF24: =IF(AND(IF$6>=$F24,IF$6<=$G24),"."," ") | IG24: =IF(AND(IG$6>=$F24,IG$6<=$G24),"."," ") | IJ24: =IF(AND(IJ$6>=$F24,IJ$6<=$G24),"."," ") | IK24: =IF(AND(IK$6>=$F24,IK$6<=$G24),"."," ") | IL24: =IF(AND(IL$6>=$F24,IL$6<=$G24),"."," ") | IM24: =IF(AND(IM$6>=$F24,IM$6<=$G24),"."," ") | IN24: =IF(AND(IN$6>=$F24,IN$6<=$G24),"."," ") | IQ24: =IF(AND(IQ$6>=$F24,IQ$6<=$G24),"."," ") | IR24: =IF(AND(IR$6>=$F24,IR$6<=$G24),"."," ") | IS24: =IF(AND(IS$6>=$F24,IS$6<=$G24),"."," ") | IT24: =IF(AND(IT$6>=$F24,IT$6<=$G24),"."," ") | IU24: =IF(AND(IU$6>=$F24,IU$6<=$G24),"."," ") | IX24: =IF(AND(IX$6>=$F24,IX$6<=$G24),"."," ") | IY24: =IF(AND(IY$6>=$F24,IY$6<=$G24),"."," ") | IZ24: =IF(AND(IZ$6>=$F24,IZ$6<=$G24),"."," ") | JA24: =IF(AND(JA$6>=$F24,JA$6<=$G24),"."," ") | JB24: =IF(AND(JB$6>=$F24,JB$6<=$G24),"."," ") | JE24: =IF(AND(JE$6>=$F24,JE$6<=$G24),"."," ") | JF24: =IF(AND(JF$6>=$F24,JF$6<=$G24),"."," ") | JG24: =IF(AND(JG$6>=$F24,JG$6<=$G24),"."," ") | JH24: =IF(AND(JH$6>=$F24,JH$6<=$G24),"."," ") | JI24: =IF(AND(JI$6>=$F24,JI$6<=$G24),"."," ")
B25: 17 | C25: Build Component 3 | D25: Bob | E25: 15 | F25: =VLOOKUP(E25,$B$6:$G$150,6,FALSE) + 1 -> 42536 | G25: =WORKDAY(F25,H25-1,Config!D24:D43) -> 42542 | H25: 5 | I25: 0 | J25: =IF(((NETWORKDAYS(F25,TODAY(),Data!C20:C39)*100)/H25)/100 > 0,((NETWORKDAYS(F25,TODAY(),Data!C20:C39)*100)/H25)/100,0) -> 328.6 | K25: =IF(J25>1, "100%",$J25) -> 100% | L25: =K25-I25 -> 1 | M25: =IF(AND(M$6>=$F25,M$6<=$G25),"."," ") | N25: =IF(AND(N$6>=$F25,N$6<=$G25),"."," ") | O25: =IF(AND(O$6>=$F25,O$6<=$G25),"."," ") | P25: =IF(AND(P$6>=$F25,P$6<=$G25),"."," ") | Q25: =IF(AND(Q$6>=$F25,Q$6<=$G25),"."," ") | T25: =IF(AND(T$6>=$F25,T$6<=$G25),"."," ") | U25: =IF(AND(U$6>=$F25,U$6<=$G25),"."," ") | V25: =IF(AND(V$6>=$F25,V$6<=$G25),"."," ") | W25: =IF(AND(W$6>=$F25,W$6<=$G25),"."," ") | X25: =IF(AND(X$6>=$F25,X$6<=$G25),"."," ") | AA25: =IF(AND(AA$6>=$F25,AA$6<=$G25),"."," ") | AB25: =IF(AND(AB$6>=$F25,AB$6<=$G25),"."," ") | AC25: =IF(AND(AC$6>=$F25,AC$6<=$G25),"."," ") | AD25: =IF(AND(AD$6>=$F25,AD$6<=$G25),"."," ") | AE25: =IF(AND(AE$6>=$F25,AE$6<=$G25),"."," ") | AH25: =IF(AND(AH$6>=$F25,AH$6<=$G25),"."," ") | AI25: =IF(AND(AI$6>=$F25,AI$6<=$G25),"."," ") | AJ25: =IF(AND(AJ$6>=$F25,AJ$6<=$G25),"."," ") | AK25: =IF(AND(AK$6>=$F25,AK$6<=$G25),"."," ") | AL25: =IF(AND(AL$6>=$F25,AL$6<=$G25),"."," ") | AO25: =IF(AND(AO$6>=$F25,AO$6<=$G25),"."," ") | AP25: =IF(AND(AP$6>=$F25,AP$6<=$G25),"."," ") | AQ25: =IF(AND(AQ$6>=$F25,AQ$6<=$G25),"."," ") | AR25: =IF(AND(AR$6>=$F25,AR$6<=$G25),"."," ") | AS25: =IF(AND(AS$6>=$F25,AS$6<=$G25),"."," ") | AV25: =IF(AND(AV$6>=$F25,AV$6<=$G25),"."," ") | AW25: =IF(AND(AW$6>=$F25,AW$6<=$G25),"."," ") | AX25: =IF(AND(AX$6>=$F25,AX$6<=$G25),"."," ") | AY25: =IF(AND(AY$6>=$F25,AY$6<=$G25),"."," ") | AZ25: =IF(AND(AZ$6>=$F25,AZ$6<=$G25),"."," ") | BC25: =IF(AND(BC$6>=$F25,BC$6<=$G25),"."," ") -> . | BD25: =IF(AND(BD$6>=$F25,BD$6<=$G25),"."," ") -> . | BE25: =IF(AND(BE$6>=$F25,BE$6<=$G25),"."," ") -> . | BF25: =IF(AND(BF$6>=$F25,BF$6<=$G25),"."," ") -> . | BG25: =IF(AND(BG$6>=$F25,BG$6<=$G25),"."," ") -> . | BJ25: =IF(AND(BJ$6>=$F25,BJ$6<=$G25),"."," ") | BK25: =IF(AND(BK$6>=$F25,BK$6<=$G25),"."," ") | BL25: =IF(AND(BL$6>=$F25,BL$6<=$G25),"."," ") | BM25: =IF(AND(BM$6>=$F25,BM$6<=$G25),"."," ") | BN25: =IF(AND(BN$6>=$F25,BN$6<=$G25),"."," ") | BQ25: =IF(AND(BQ$6>=$F25,BQ$6<=$G25),"."," ") | BR25: =IF(AND(BR$6>=$F25,BR$6<=$G25),"."," ") | BS25: =IF(AND(BS$6>=$F25,BS$6<=$G25),"."," ") | BT25: =IF(AND(BT$6>=$F25,BT$6<=$G25),"."," ") | BU25: =IF(AND(BU$6>=$F25,BU$6<=$G25),"."," ") | BX25: =IF(AND(BX$6>=$F25,BX$6<=$G25),"."," ") | BY25: =IF(AND(BY$6>=$F25,BY$6<=$G25),"."," ") | BZ25: =IF(AND(BZ$6>=$F25,BZ$6<=$G25),"."," ") | CA25: =IF(AND(CA$6>=$F25,CA$6<=$G25),"."," ") | CB25: =IF(AND(CB$6>=$F25,CB$6<=$G25),"."," ") | CE25: =IF(AND(CE$6>=$F25,CE$6<=$G25),"."," ") | CF25: =IF(AND(CF$6>=$F25,CF$6<=$G25),"."," ") | CG25: =IF(AND(CG$6>=$F25,CG$6<=$G25),"."," ") | CH25: =IF(AND(CH$6>=$F25,CH$6<=$G25),"."," ") | CI25: =IF(AND(CI$6>=$F25,CI$6<=$G25),"."," ") | CL25: =IF(AND(CL$6>=$F25,CL$6<=$G25),"."," ") | CM25: =IF(AND(CM$6>=$F25,CM$6<=$G25),"."," ") | CN25: =IF(AND(CN$6>=$F25,CN$6<=$G25),"."," ") | CO25: =IF(AND(CO$6>=$F25,CO$6<=$G25),"."," ") | CP25: =IF(AND(CP$6>=$F25,CP$6<=$G25),"."," ") | CS25: =IF(AND(CS$6>=$F25,CS$6<=$G25),"."," ") | CT25: =IF(AND(CT$6>=$F25,CT$6<=$G25),"."," ") | CU25: =IF(AND(CU$6>=$F25,CU$6<=$G25),"."," ") | CV25: =IF(AND(CV$6>=$F25,CV$6<=$G25),"."," ") | CW25: =IF(AND(CW$6>=$F25,CW$6<=$G25),"."," ") | CZ25: =IF(AND(CZ$6>=$F25,CZ$6<=$G25),"."," ") | DA25: =IF(AND(DA$6>=$F25,DA$6<=$G25),"."," ") | DB25: =IF(AND(DB$6>=$F25,DB$6<=$G25),"."," ") | DC25: =IF(AND(DC$6>=$F25,DC$6<=$G25),"."," ") | DD25: =IF(AND(DD$6>=$F25,DD$6<=$G25),"."," ") | DG25: =IF(AND(DG$6>=$F25,DG$6<=$G25),"."," ") | DH25: =IF(AND(DH$6>=$F25,DH$6<=$G25),"."," ") | DI25: =IF(AND(DI$6>=$F25,DI$6<=$G25),"."," ") | DJ25: =IF(AND(DJ$6>=$F25,DJ$6<=$G25),"."," ") | DK25: =IF(AND(DK$6>=$F25,DK$6<=$G25),"."," ") | DN25: =IF(AND(DN$6>=$F25,DN$6<=$G25),"."," ") | DO25: =IF(AND(DO$6>=$F25,DO$6<=$G25),"."," ") | DP25: =IF(AND(DP$6>=$F25,DP$6<=$G25),"."," ") | DQ25: =IF(AND(DQ$6>=$F25,DQ$6<=$G25),"."," ") | DR25: =IF(AND(DR$6>=$F25,DR$6<=$G25),"."," ") | DU25: =IF(AND(DU$6>=$F25,DU$6<=$G25),"."," ") | DV25: =IF(AND(DV$6>=$F25,DV$6<=$G25),"."," ") | DW25: =IF(AND(DW$6>=$F25,DW$6<=$G25),"."," ") | DX25: =IF(AND(DX$6>=$F25,DX$6<=$G25),"."," ") | DY25: =IF(AND(DY$6>=$F25,DY$6<=$G25),"."," ") | EB25: =IF(AND(EB$6>=$F25,EB$6<=$G25),"."," ") | EC25: =IF(AND(EC$6>=$F25,EC$6<=$G25),"."," ") | ED25: =IF(AND(ED$6>=$F25,ED$6<=$G25),"."," ") | EE25: =IF(AND(EE$6>=$F25,EE$6<=$G25),"."," ") | EF25: =IF(AND(EF$6>=$F25,EF$6<=$G25),"."," ") | EI25: =IF(AND(EI$6>=$F25,EI$6<=$G25),"."," ") | EJ25: =IF(AND(EJ$6>=$F25,EJ$6<=$G25),"."," ") | EK25: =IF(AND(EK$6>=$F25,EK$6<=$G25),"."," ") | EL25: =IF(AND(EL$6>=$F25,EL$6<=$G25),"."," ") | EM25: =IF(AND(EM$6>=$F25,EM$6<=$G25),"."," ") | EP25: =IF(AND(EP$6>=$F25,EP$6<=$G25),"."," ") | EQ25: =IF(AND(EQ$6>=$F25,EQ$6<=$G25),"."," ") | ER25: =IF(AND(ER$6>=$F25,ER$6<=$G25),"."," ") | ES25: =IF(AND(ES$6>=$F25,ES$6<=$G25),"."," ") | ET25: =IF(AND(ET$6>=$F25,ET$6<=$G25),"."," ") | EW25: =IF(AND(EW$6>=$F25,EW$6<=$G25),"."," ") | EX25: =IF(AND(EX$6>=$F25,EX$6<=$G25),"."," ") | EY25: =IF(AND(EY$6>=$F25,EY$6<=$G25),"."," ") | EZ25: =IF(AND(EZ$6>=$F25,EZ$6<=$G25),"."," ") | FA25: =IF(AND(FA$6>=$F25,FA$6<=$G25),"."," ") | FD25: =IF(AND(FD$6>=$F25,FD$6<=$G25),"."," ") | FE25: =IF(AND(FE$6>=$F25,FE$6<=$G25),"."," ") | FF25: =IF(AND(FF$6>=$F25,FF$6<=$G25),"."," ") | FG25: =IF(AND(FG$6>=$F25,FG$6<=$G25),"."," ") | FH25: =IF(AND(FH$6>=$F25,FH$6<=$G25),"."," ") | FK25: =IF(AND(FK$6>=$F25,FK$6<=$G25),"."," ") | FL25: =IF(AND(FL$6>=$F25,FL$6<=$G25),"."," ") | FM25: =IF(AND(FM$6>=$F25,FM$6<=$G25),"."," ") | FN25: =IF(AND(FN$6>=$F25,FN$6<=$G25),"."," ") | FO25: =IF(AND(FO$6>=$F25,FO$6<=$G25),"."," ") | FR25: =IF(AND(FR$6>=$F25,FR$6<=$G25),"."," ") | FS25: =IF(AND(FS$6>=$F25,FS$6<=$G25),"."," ") | FT25: =IF(AND(FT$6>=$F25,FT$6<=$G25),"."," ") | FU25: =IF(AND(FU$6>=$F25,FU$6<=$G25),"."," ") | FV25: =IF(AND(FV$6>=$F25,FV$6<=$G25),"."," ") | FY25: =IF(AND(FY$6>=$F25,FY$6<=$G25),"."," ") | FZ25: =IF(AND(FZ$6>=$F25,FZ$6<=$G25),"."," ") | GA25: =IF(AND(GA$6>=$F25,GA$6<=$G25),"."," ") | GB25: =IF(AND(GB$6>=$F25,GB$6<=$G25),"."," ") | GC25: =IF(AND(GC$6>=$F25,GC$6<=$G25),"."," ") | GF25: =IF(AND(GF$6>=$F25,GF$6<=$G25),"."," ") | GG25: =IF(AND(GG$6>=$F25,GG$6<=$G25),"."," ") | GH25: =IF(AND(GH$6>=$F25,GH$6<=$G25),"."," ") | GI25: =IF(AND(GI$6>=$F25,GI$6<=$G25),"."," ") | GJ25: =IF(AND(GJ$6>=$F25,GJ$6<=$G25),"."," ") | GM25: =IF(AND(GM$6>=$F25,GM$6<=$G25),"."," ") | GN25: =IF(AND(GN$6>=$F25,GN$6<=$G25),"."," ") | GO25: =IF(AND(GO$6>=$F25,GO$6<=$G25),"."," ") | GP25: =IF(AND(GP$6>=$F25,GP$6<=$G25),"."," ") | GQ25: =IF(AND(GQ$6>=$F25,GQ$6<=$G25),"."," ") | GT25: =IF(AND(GT$6>=$F25,GT$6<=$G25),"."," ") | GU25: =IF(AND(GU$6>=$F25,GU$6<=$G25),"."," ") | GV25: =IF(AND(GV$6>=$F25,GV$6<=$G25),"."," ") | GW25: =IF(AND(GW$6>=$F25,GW$6<=$G25),"."," ") | GX25: =IF(AND(GX$6>=$F25,GX$6<=$G25),"."," ") | HA25: =IF(AND(HA$6>=$F25,HA$6<=$G25),"."," ") | HB25: =IF(AND(HB$6>=$F25,HB$6<=$G25),"."," ") | HC25: =IF(AND(HC$6>=$F25,HC$6<=$G25),"."," ") | HD25: =IF(AND(HD$6>=$F25,HD$6<=$G25),"."," ") | HE25: =IF(AND(HE$6>=$F25,HE$6<=$G25),"."," ") | HH25: =IF(AND(HH$6>=$F25,HH$6<=$G25),"."," ") | HI25: =IF(AND(HI$6>=$F25,HI$6<=$G25),"."," ") | HJ25: =IF(AND(HJ$6>=$F25,HJ$6<=$G25),"."," ") | HK25: =IF(AND(HK$6>=$F25,HK$6<=$G25),"."," ") | HL25: =IF(AND(HL$6>=$F25,HL$6<=$G25),"."," ") | HO25: =IF(AND(HO$6>=$F25,HO$6<=$G25),"."," ") | HP25: =IF(AND(HP$6>=$F25,HP$6<=$G25),"."," ") | HQ25: =IF(AND(HQ$6>=$F25,HQ$6<=$G25),"."," ") | HR25: =IF(AND(HR$6>=$F25,HR$6<=$G25),"."," ") | HS25: =IF(AND(HS$6>=$F25,HS$6<=$G25),"."," ") | HV25: =IF(AND(HV$6>=$F25,HV$6<=$G25),"."," ") | HW25: =IF(AND(HW$6>=$F25,HW$6<=$G25),"."," ") | HX25: =IF(AND(HX$6>=$F25,HX$6<=$G25),"."," ") | HY25: =IF(AND(HY$6>=$F25,HY$6<=$G25),"."," ") | HZ25: =IF(AND(HZ$6>=$F25,HZ$6<=$G25),"."," ") | IC25: =IF(AND(IC$6>=$F25,IC$6<=$G25),"."," ") | ID25: =IF(AND(ID$6>=$F25,ID$6<=$G25),"."," ") | IE25: =IF(AND(IE$6>=$F25,IE$6<=$G25),"."," ") | IF25: =IF(AND(IF$6>=$F25,IF$6<=$G25),"."," ") | IG25: =IF(AND(IG$6>=$F25,IG$6<=$G25),"."," ") | IJ25: =IF(AND(IJ$6>=$F25,IJ$6<=$G25),"."," ") | IK25: =IF(AND(IK$6>=$F25,IK$6<=$G25),"."," ") | IL25: =IF(AND(IL$6>=$F25,IL$6<=$G25),"."," ") | IM25: =IF(AND(IM$6>=$F25,IM$6<=$G25),"."," ") | IN25: =IF(AND(IN$6>=$F25,IN$6<=$G25),"."," ") | IQ25: =IF(AND(IQ$6>=$F25,IQ$6<=$G25),"."," ") | IR25: =IF(AND(IR$6>=$F25,IR$6<=$G25),"."," ") | IS25: =IF(AND(IS$6>=$F25,IS$6<=$G25),"."," ") | IT25: =IF(AND(IT$6>=$F25,IT$6<=$G25),"."," ") | IU25: =IF(AND(IU$6>=$F25,IU$6<=$G25),"."," ") | IX25: =IF(AND(IX$6>=$F25,IX$6<=$G25),"."," ") | IY25: =IF(AND(IY$6>=$F25,IY$6<=$G25),"."," ") | IZ25: =IF(AND(IZ$6>=$F25,IZ$6<=$G25),"."," ") | JA25: =IF(AND(JA$6>=$F25,JA$6<=$G25),"."," ") | JB25: =IF(AND(JB$6>=$F25,JB$6<=$G25),"."," ") | JE25: =IF(AND(JE$6>=$F25,JE$6<=$G25),"."," ") | JF25: =IF(AND(JF$6>=$F25,JF$6<=$G25),"."," ") | JG25: =IF(AND(JG$6>=$F25,JG$6<=$G25),"."," ") | JH25: =IF(AND(JH$6>=$F25,JH$6<=$G25),"."," ") | JI25: =IF(AND(JI$6>=$F25,JI$6<=$G25),"."," ")
B26: 18 | C26: Build Component 4 | D26: Bob | E26: 16 | F26: =VLOOKUP(E26,$B$6:$G$150,6,FALSE) + 1 -> 42542 | G26: =WORKDAY(F26,H26-1,Config!D25:D44) -> 42543 | H26: 2 | I26: 0 | J26: =IF(((NETWORKDAYS(F26,TODAY(),Data!C21:C40)*100)/H26)/100 > 0,((NETWORKDAYS(F26,TODAY(),Data!C21:C40)*100)/H26)/100,0) -> 819.5 | K26: =IF(J26>1, "100%",$J26) -> 100% | L26: =K26-I26 -> 1 | M26: =IF(AND(M$6>=$F26,M$6<=$G26),"."," ") | N26: =IF(AND(N$6>=$F26,N$6<=$G26),"."," ") | O26: =IF(AND(O$6>=$F26,O$6<=$G26),"."," ") | P26: =IF(AND(P$6>=$F26,P$6<=$G26),"."," ") | Q26: =IF(AND(Q$6>=$F26,Q$6<=$G26),"."," ") | T26: =IF(AND(T$6>=$F26,T$6<=$G26),"."," ") | U26: =IF(AND(U$6>=$F26,U$6<=$G26),"."," ") | V26: =IF(AND(V$6>=$F26,V$6<=$G26),"."," ") | W26: =IF(AND(W$6>=$F26,W$6<=$G26),"."," ") | X26: =IF(AND(X$6>=$F26,X$6<=$G26),"."," ") | AA26: =IF(AND(AA$6>=$F26,AA$6<=$G26),"."," ") | AB26: =IF(AND(AB$6>=$F26,AB$6<=$G26),"."," ") | AC26: =IF(AND(AC$6>=$F26,AC$6<=$G26),"."," ") | AD26: =IF(AND(AD$6>=$F26,AD$6<=$G26),"."," ") | AE26: =IF(AND(AE$6>=$F26,AE$6<=$G26),"."," ") | AH26: =IF(AND(AH$6>=$F26,AH$6<=$G26),"."," ") | AI26: =IF(AND(AI$6>=$F26,AI$6<=$G26),"."," ") | AJ26: =IF(AND(AJ$6>=$F26,AJ$6<=$G26),"."," ") | AK26: =IF(AND(AK$6>=$F26,AK$6<=$G26),"."," ") | AL26: =IF(AND(AL$6>=$F26,AL$6<=$G26),"."," ") | AO26: =IF(AND(AO$6>=$F26,AO$6<=$G26),"."," ") | AP26: =IF(AND(AP$6>=$F26,AP$6<=$G26),"."," ") | AQ26: =IF(AND(AQ$6>=$F26,AQ$6<=$G26),"."," ") | AR26: =IF(AND(AR$6>=$F26,AR$6<=$G26),"."," ") | AS26: =IF(AND(AS$6>=$F26,AS$6<=$G26),"."," ") | AV26: =IF(AND(AV$6>=$F26,AV$6<=$G26),"."," ") | AW26: =IF(AND(AW$6>=$F26,AW$6<=$G26),"."," ") | AX26: =IF(AND(AX$6>=$F26,AX$6<=$G26),"."," ") | AY26: =IF(AND(AY$6>=$F26,AY$6<=$G26),"."," ") | AZ26: =IF(AND(AZ$6>=$F26,AZ$6<=$G26),"."," ") | BC26: =IF(AND(BC$6>=$F26,BC$6<=$G26),"."," ") | BD26: =IF(AND(BD$6>=$F26,BD$6<=$G26),"."," ") | BE26: =IF(AND(BE$6>=$F26,BE$6<=$G26),"."," ") | BF26: =IF(AND(BF$6>=$F26,BF$6<=$G26),"."," ") | BG26: =IF(AND(BG$6>=$F26,BG$6<=$G26),"."," ") | BJ26: =IF(AND(BJ$6>=$F26,BJ$6<=$G26),"."," ") | BK26: =IF(AND(BK$6>=$F26,BK$6<=$G26),"."," ") | BL26: =IF(AND(BL$6>=$F26,BL$6<=$G26),"."," ") | BM26: =IF(AND(BM$6>=$F26,BM$6<=$G26),"."," ") | BN26: =IF(AND(BN$6>=$F26,BN$6<=$G26),"."," ") | BQ26: =IF(AND(BQ$6>=$F26,BQ$6<=$G26),"."," ") | BR26: =IF(AND(BR$6>=$F26,BR$6<=$G26),"."," ") | BS26: =IF(AND(BS$6>=$F26,BS$6<=$G26),"."," ") | BT26: =IF(AND(BT$6>=$F26,BT$6<=$G26),"."," ") | BU26: =IF(AND(BU$6>=$F26,BU$6<=$G26),"."," ") | BX26: =IF(AND(BX$6>=$F26,BX$6<=$G26),"."," ") | BY26: =IF(AND(BY$6>=$F26,BY$6<=$G26),"."," ") | BZ26: =IF(AND(BZ$6>=$F26,BZ$6<=$G26),"."," ") | CA26: =IF(AND(CA$6>=$F26,CA$6<=$G26),"."," ") | CB26: =IF(AND(CB$6>=$F26,CB$6<=$G26),"."," ") | CE26: =IF(AND(CE$6>=$F26,CE$6<=$G26),"."," ") | CF26: =IF(AND(CF$6>=$F26,CF$6<=$G26),"."," ") | CG26: =IF(AND(CG$6>=$F26,CG$6<=$G26),"."," ") | CH26: =IF(AND(CH$6>=$F26,CH$6<=$G26),"."," ") | CI26: =IF(AND(CI$6>=$F26,CI$6<=$G26),"."," ") | CL26: =IF(AND(CL$6>=$F26,CL$6<=$G26),"."," ") | CM26: =IF(AND(CM$6>=$F26,CM$6<=$G26),"."," ") | CN26: =IF(AND(CN$6>=$F26,CN$6<=$G26),"."," ") | CO26: =IF(AND(CO$6>=$F26,CO$6<=$G26),"."," ") | CP26: =IF(AND(CP$6>=$F26,CP$6<=$G26),"."," ") | CS26: =IF(AND(CS$6>=$F26,CS$6<=$G26),"."," ") | CT26: =IF(AND(CT$6>=$F26,CT$6<=$G26),"."," ") | CU26: =IF(AND(CU$6>=$F26,CU$6<=$G26),"."," ") | CV26: =IF(AND(CV$6>=$F26,CV$6<=$G26),"."," ") | CW26: =IF(AND(CW$6>=$F26,CW$6<=$G26),"."," ") | CZ26: =IF(AND(CZ$6>=$F26,CZ$6<=$G26),"."," ") | DA26: =IF(AND(DA$6>=$F26,DA$6<=$G26),"."," ") | DB26: =IF(AND(DB$6>=$F26,DB$6<=$G26),"."," ") | DC26: =IF(AND(DC$6>=$F26,DC$6<=$G26),"."," ") | DD26: =IF(AND(DD$6>=$F26,DD$6<=$G26),"."," ") | DG26: =IF(AND(DG$6>=$F26,DG$6<=$G26),"."," ") | DH26: =IF(AND(DH$6>=$F26,DH$6<=$G26),"."," ") | DI26: =IF(AND(DI$6>=$F26,DI$6<=$G26),"."," ") | DJ26: =IF(AND(DJ$6>=$F26,DJ$6<=$G26),"."," ") | DK26: =IF(AND(DK$6>=$F26,DK$6<=$G26),"."," ") | DN26: =IF(AND(DN$6>=$F26,DN$6<=$G26),"."," ") | DO26: =IF(AND(DO$6>=$F26,DO$6<=$G26),"."," ") | DP26: =IF(AND(DP$6>=$F26,DP$6<=$G26),"."," ") | DQ26: =IF(AND(DQ$6>=$F26,DQ$6<=$G26),"."," ") | DR26: =IF(AND(DR$6>=$F26,DR$6<=$G26),"."," ") | DU26: =IF(AND(DU$6>=$F26,DU$6<=$G26),"."," ") | DV26: =IF(AND(DV$6>=$F26,DV$6<=$G26),"."," ") | DW26: =IF(AND(DW$6>=$F26,DW$6<=$G26),"."," ") | DX26: =IF(AND(DX$6>=$F26,DX$6<=$G26),"."," ") | DY26: =IF(AND(DY$6>=$F26,DY$6<=$G26),"."," ") | EB26: =IF(AND(EB$6>=$F26,EB$6<=$G26),"."," ") | EC26: =IF(AND(EC$6>=$F26,EC$6<=$G26),"."," ") | ED26: =IF(AND(ED$6>=$F26,ED$6<=$G26),"."," ") | EE26: =IF(AND(EE$6>=$F26,EE$6<=$G26),"."," ") | EF26: =IF(AND(EF$6>=$F26,EF$6<=$G26),"."," ") | EI26: =IF(AND(EI$6>=$F26,EI$6<=$G26),"."," ") | EJ26: =IF(AND(EJ$6>=$F26,EJ$6<=$G26),"."," ") | EK26: =IF(AND(EK$6>=$F26,EK$6<=$G26),"."," ") | EL26: =IF(AND(EL$6>=$F26,EL$6<=$G26),"."," ") | EM26: =IF(AND(EM$6>=$F26,EM$6<=$G26),"."," ") | EP26: =IF(AND(EP$6>=$F26,EP$6<=$G26),"."," ") | EQ26: =IF(AND(EQ$6>=$F26,EQ$6<=$G26),"."," ") | ER26: =IF(AND(ER$6>=$F26,ER$6<=$G26),"."," ") | ES26: =IF(AND(ES$6>=$F26,ES$6<=$G26),"."," ") | ET26: =IF(AND(ET$6>=$F26,ET$6<=$G26),"."," ") | EW26: =IF(AND(EW$6>=$F26,EW$6<=$G26),"."," ") | EX26: =IF(AND(EX$6>=$F26,EX$6<=$G26),"."," ") | EY26: =IF(AND(EY$6>=$F26,EY$6<=$G26),"."," ") | EZ26: =IF(AND(EZ$6>=$F26,EZ$6<=$G26),"."," ") | FA26: =IF(AND(FA$6>=$F26,FA$6<=$G26),"."," ") | FD26: =IF(AND(FD$6>=$F26,FD$6<=$G26),"."," ") | FE26: =IF(AND(FE$6>=$F26,FE$6<=$G26),"."," ") | FF26: =IF(AND(FF$6>=$F26,FF$6<=$G26),"."," ") | FG26: =IF(AND(FG$6>=$F26,FG$6<=$G26),"."," ") | FH26: =IF(AND(FH$6>=$F26,FH$6<=$G26),"."," ") | FK26: =IF(AND(FK$6>=$F26,FK$6<=$G26),"."," ") | FL26: =IF(AND(FL$6>=$F26,FL$6<=$G26),"."," ") | FM26: =IF(AND(FM$6>=$F26,FM$6<=$G26),"."," ") | FN26: =IF(AND(FN$6>=$F26,FN$6<=$G26),"."," ") | FO26: =IF(AND(FO$6>=$F26,FO$6<=$G26),"."," ") | FR26: =IF(AND(FR$6>=$F26,FR$6<=$G26),"."," ") | FS26: =IF(AND(FS$6>=$F26,FS$6<=$G26),"."," ") | FT26: =IF(AND(FT$6>=$F26,FT$6<=$G26),"."," ") | FU26: =IF(AND(FU$6>=$F26,FU$6<=$G26),"."," ") | FV26: =IF(AND(FV$6>=$F26,FV$6<=$G26),"."," ") | FY26: =IF(AND(FY$6>=$F26,FY$6<=$G26),"."," ") | FZ26: =IF(AND(FZ$6>=$F26,FZ$6<=$G26),"."," ") | GA26: =IF(AND(GA$6>=$F26,GA$6<=$G26),"."," ") | GB26: =IF(AND(GB$6>=$F26,GB$6<=$G26),"."," ") | GC26: =IF(AND(GC$6>=$F26,GC$6<=$G26),"."," ") | GF26: =IF(AND(GF$6>=$F26,GF$6<=$G26),"."," ") | GG26: =IF(AND(GG$6>=$F26,GG$6<=$G26),"."," ") | GH26: =IF(AND(GH$6>=$F26,GH$6<=$G26),"."," ") | GI26: =IF(AND(GI$6>=$F26,GI$6<=$G26),"."," ") | GJ26: =IF(AND(GJ$6>=$F26,GJ$6<=$G26),"."," ") | GM26: =IF(AND(GM$6>=$F26,GM$6<=$G26),"."," ") | GN26: =IF(AND(GN$6>=$F26,GN$6<=$G26),"."," ") | GO26: =IF(AND(GO$6>=$F26,GO$6<=$G26),"."," ") | GP26: =IF(AND(GP$6>=$F26,GP$6<=$G26),"."," ") | GQ26: =IF(AND(GQ$6>=$F26,GQ$6<=$G26),"."," ") | GT26: =IF(AND(GT$6>=$F26,GT$6<=$G26),"."," ") | GU26: =IF(AND(GU$6>=$F26,GU$6<=$G26),"."," ") | GV26: =IF(AND(GV$6>=$F26,GV$6<=$G26),"."," ") | GW26: =IF(AND(GW$6>=$F26,GW$6<=$G26),"."," ") | GX26: =IF(AND(GX$6>=$F26,GX$6<=$G26),"."," ") | HA26: =IF(AND(HA$6>=$F26,HA$6<=$G26),"."," ") | HB26: =IF(AND(HB$6>=$F26,HB$6<=$G26),"."," ") | HC26: =IF(AND(HC$6>=$F26,HC$6<=$G26),"."," ") | HD26: =IF(AND(HD$6>=$F26,HD$6<=$G26),"."," ") | HE26: =IF(AND(HE$6>=$F26,HE$6<=$G26),"."," ") | HH26: =IF(AND(HH$6>=$F26,HH$6<=$G26),"."," ") | HI26: =IF(AND(HI$6>=$F26,HI$6<=$G26),"."," ") | HJ26: =IF(AND(HJ$6>=$F26,HJ$6<=$G26),"."," ") | HK26: =IF(AND(HK$6>=$F26,HK$6<=$G26),"."," ") | HL26: =IF(AND(HL$6>=$F26,HL$6<=$G26),"."," ") | HO26: =IF(AND(HO$6>=$F26,HO$6<=$G26),"."," ") | HP26: =IF(AND(HP$6>=$F26,HP$6<=$G26),"."," ") | HQ26: =IF(AND(HQ$6>=$F26,HQ$6<=$G26),"."," ") | HR26: =IF(AND(HR$6>=$F26,HR$6<=$G26),"."," ") | HS26: =IF(AND(HS$6>=$F26,HS$6<=$G26),"."," ") | HV26: =IF(AND(HV$6>=$F26,HV$6<=$G26),"."," ") | HW26: =IF(AND(HW$6>=$F26,HW$6<=$G26),"."," ") | HX26: =IF(AND(HX$6>=$F26,HX$6<=$G26),"."," ") | HY26: =IF(AND(HY$6>=$F26,HY$6<=$G26),"."," ") | HZ26: =IF(AND(HZ$6>=$F26,HZ$6<=$G26),"."," ") | IC26: =IF(AND(IC$6>=$F26,IC$6<=$G26),"."," ") | ID26: =IF(AND(ID$6>=$F26,ID$6<=$G26),"."," ") | IE26: =IF(AND(IE$6>=$F26,IE$6<=$G26),"."," ") | IF26: =IF(AND(IF$6>=$F26,IF$6<=$G26),"."," ") | IG26: =IF(AND(IG$6>=$F26,IG$6<=$G26),"."," ") | IJ26: =IF(AND(IJ$6>=$F26,IJ$6<=$G26),"."," ") | IK26: =IF(AND(IK$6>=$F26,IK$6<=$G26),"."," ") | IL26: =IF(AND(IL$6>=$F26,IL$6<=$G26),"."," ") | IM26: =IF(AND(IM$6>=$F26,IM$6<=$G26),"."," ") | IN26: =IF(AND(IN$6>=$F26,IN$6<=$G26),"."," ") | IQ26: =IF(AND(IQ$6>=$F26,IQ$6<=$G26),"."," ") | IR26: =IF(AND(IR$6>=$F26,IR$6<=$G26),"."," ") | IS26: =IF(AND(IS$6>=$F26,IS$6<=$G26),"."," ") | IT26: =IF(AND(IT$6>=$F26,IT$6<=$G26),"."," ") | IU26: =IF(AND(IU$6>=$F26,IU$6<=$G26),"."," ") | IX26: =IF(AND(IX$6>=$F26,IX$6<=$G26),"."," ") | IY26: =IF(AND(IY$6>=$F26,IY$6<=$G26),"."," ") | IZ26: =IF(AND(IZ$6>=$F26,IZ$6<=$G26),"."," ") | JA26: =IF(AND(JA$6>=$F26,JA$6<=$G26),"."," ") | JB26: =IF(AND(JB$6>=$F26,JB$6<=$G26),"."," ") | JE26: =IF(AND(JE$6>=$F26,JE$6<=$G26),"."," ") | JF26: =IF(AND(JF$6>=$F26,JF$6<=$G26),"."," ") | JG26: =IF(AND(JG$6>=$F26,JG$6<=$G26),"."," ") | JH26: =IF(AND(JH$6>=$F26,JH$6<=$G26),"."," ") | JI26: =IF(AND(JI$6>=$F26,JI$6<=$G26),"."," ")
B27: 19 | C27: Build Component 5 | D27: Bob | E27: 17 | F27: =VLOOKUP(E27,$B$6:$G$150,6,FALSE) + 1 -> 42543 | G27: =WORKDAY(F27,H27-1,Config!D26:D45) -> 42545 | H27: 3 | I27: 0 | J27: =IF(((NETWORKDAYS(F27,TODAY(),Data!C22:C41)*100)/H27)/100 > 0,((NETWORKDAYS(F27,TODAY(),Data!C22:C41)*100)/H27)/100,0) -> 546 | K27: =IF(J27>1, "100%",$J27) -> 100% | L27: =K27-I27 -> 1 | M27: =IF(AND(M$6>=$F27,M$6<=$G27),"."," ") | N27: =IF(AND(N$6>=$F27,N$6<=$G27),"."," ") | O27: =IF(AND(O$6>=$F27,O$6<=$G27),"."," ") | P27: =IF(AND(P$6>=$F27,P$6<=$G27),"."," ") | Q27: =IF(AND(Q$6>=$F27,Q$6<=$G27),"."," ") | T27: =IF(AND(T$6>=$F27,T$6<=$G27),"."," ") | U27: =IF(AND(U$6>=$F27,U$6<=$G27),"."," ") | V27: =IF(AND(V$6>=$F27,V$6<=$G27),"."," ") | W27: =IF(AND(W$6>=$F27,W$6<=$G27),"."," ") | X27: =IF(AND(X$6>=$F27,X$6<=$G27),"."," ") | AA27: =IF(AND(AA$6>=$F27,AA$6<=$G27),"."," ") | AB27: =IF(AND(AB$6>=$F27,AB$6<=$G27),"."," ") | AC27: =IF(AND(AC$6>=$F27,AC$6<=$G27),"."," ") | AD27: =IF(AND(AD$6>=$F27,AD$6<=$G27),"."," ") | AE27: =IF(AND(AE$6>=$F27,AE$6<=$G27),"."," ") | AH27: =IF(AND(AH$6>=$F27,AH$6<=$G27),"."," ") | AI27: =IF(AND(AI$6>=$F27,AI$6<=$G27),"."," ") | AJ27: =IF(AND(AJ$6>=$F27,AJ$6<=$G27),"."," ") | AK27: =IF(AND(AK$6>=$F27,AK$6<=$G27),"."," ") | AL27: =IF(AND(AL$6>=$F27,AL$6<=$G27),"."," ") | AO27: =IF(AND(AO$6>=$F27,AO$6<=$G27),"."," ") | AP27: =IF(AND(AP$6>=$F27,AP$6<=$G27),"."," ") | AQ27: =IF(AND(AQ$6>=$F27,AQ$6<=$G27),"."," ") | AR27: =IF(AND(AR$6>=$F27,AR$6<=$G27),"."," ") | AS27: =IF(AND(AS$6>=$F27,AS$6<=$G27),"."," ") | AV27: =IF(AND(AV$6>=$F27,AV$6<=$G27),"."," ") | AW27: =IF(AND(AW$6>=$F27,AW$6<=$G27),"."," ") | AX27: =IF(AND(AX$6>=$F27,AX$6<=$G27),"."," ") | AY27: =IF(AND(AY$6>=$F27,AY$6<=$G27),"."," ") | AZ27: =IF(AND(AZ$6>=$F27,AZ$6<=$G27),"."," ") | BC27: =IF(AND(BC$6>=$F27,BC$6<=$G27),"."," ") | BD27: =IF(AND(BD$6>=$F27,BD$6<=$G27),"."," ") | BE27: =IF(AND(BE$6>=$F27,BE$6<=$G27),"."," ") | BF27: =IF(AND(BF$6>=$F27,BF$6<=$G27),"."," ") | BG27: =IF(AND(BG$6>=$F27,BG$6<=$G27),"."," ") | BJ27: =IF(AND(BJ$6>=$F27,BJ$6<=$G27),"."," ") -> . | BK27: =IF(AND(BK$6>=$F27,BK$6<=$G27),"."," ") -> . | BL27: =IF(AND(BL$6>=$F27,BL$6<=$G27),"."," ") | BM27: =IF(AND(BM$6>=$F27,BM$6<=$G27),"."," ") | BN27: =IF(AND(BN$6>=$F27,BN$6<=$G27),"."," ") | BQ27: =IF(AND(BQ$6>=$F27,BQ$6<=$G27),"."," ") | BR27: =IF(AND(BR$6>=$F27,BR$6<=$G27),"."," ") | BS27: =IF(AND(BS$6>=$F27,BS$6<=$G27),"."," ") | BT27: =IF(AND(BT$6>=$F27,BT$6<=$G27),"."," ") | BU27: =IF(AND(BU$6>=$F27,BU$6<=$G27),"."," ") | BX27: =IF(AND(BX$6>=$F27,BX$6<=$G27),"."," ") | BY27: =IF(AND(BY$6>=$F27,BY$6<=$G27),"."," ") | BZ27: =IF(AND(BZ$6>=$F27,BZ$6<=$G27),"."," ") | CA27: =IF(AND(CA$6>=$F27,CA$6<=$G27),"."," ") | CB27: =IF(AND(CB$6>=$F27,CB$6<=$G27),"."," ") | CE27: =IF(AND(CE$6>=$F27,CE$6<=$G27),"."," ") | CF27: =IF(AND(CF$6>=$F27,CF$6<=$G27),"."," ") | CG27: =IF(AND(CG$6>=$F27,CG$6<=$G27),"."," ") | CH27: =IF(AND(CH$6>=$F27,CH$6<=$G27),"."," ") | CI27: =IF(AND(CI$6>=$F27,CI$6<=$G27),"."," ") | CL27: =IF(AND(CL$6>=$F27,CL$6<=$G27),"."," ") | CM27: =IF(AND(CM$6>=$F27,CM$6<=$G27),"."," ") | CN27: =IF(AND(CN$6>=$F27,CN$6<=$G27),"."," ") | CO27: =IF(AND(CO$6>=$F27,CO$6<=$G27),"."," ") | CP27: =IF(AND(CP$6>=$F27,CP$6<=$G27),"."," ") | CS27: =IF(AND(CS$6>=$F27,CS$6<=$G27),"."," ") | CT27: =IF(AND(CT$6>=$F27,CT$6<=$G27),"."," ") | CU27: =IF(AND(CU$6>=$F27,CU$6<=$G27),"."," ") | CV27: =IF(AND(CV$6>=$F27,CV$6<=$G27),"."," ") | CW27: =IF(AND(CW$6>=$F27,CW$6<=$G27),"."," ") | CZ27: =IF(AND(CZ$6>=$F27,CZ$6<=$G27),"."," ") | DA27: =IF(AND(DA$6>=$F27,DA$6<=$G27),"."," ") | DB27: =IF(AND(DB$6>=$F27,DB$6<=$G27),"."," ") | DC27: =IF(AND(DC$6>=$F27,DC$6<=$G27),"."," ") | DD27: =IF(AND(DD$6>=$F27,DD$6<=$G27),"."," ") | DG27: =IF(AND(DG$6>=$F27,DG$6<=$G27),"."," ") | DH27: =IF(AND(DH$6>=$F27,DH$6<=$G27),"."," ") | DI27: =IF(AND(DI$6>=$F27,DI$6<=$G27),"."," ") | DJ27: =IF(AND(DJ$6>=$F27,DJ$6<=$G27),"."," ") | DK27: =IF(AND(DK$6>=$F27,DK$6<=$G27),"."," ") | DN27: =IF(AND(DN$6>=$F27,DN$6<=$G27),"."," ") | DO27: =IF(AND(DO$6>=$F27,DO$6<=$G27),"."," ") | DP27: =IF(AND(DP$6>=$F27,DP$6<=$G27),"."," ") | DQ27: =IF(AND(DQ$6>=$F27,DQ$6<=$G27),"."," ") | DR27: =IF(AND(DR$6>=$F27,DR$6<=$G27),"."," ") | DU27: =IF(AND(DU$6>=$F27,DU$6<=$G27),"."," ") | DV27: =IF(AND(DV$6>=$F27,DV$6<=$G27),"."," ") | DW27: =IF(AND(DW$6>=$F27,DW$6<=$G27),"."," ") | DX27: =IF(AND(DX$6>=$F27,DX$6<=$G27),"."," ") | DY27: =IF(AND(DY$6>=$F27,DY$6<=$G27),"."," ") | EB27: =IF(AND(EB$6>=$F27,EB$6<=$G27),"."," ") | EC27: =IF(AND(EC$6>=$F27,EC$6<=$G27),"."," ") | ED27: =IF(AND(ED$6>=$F27,ED$6<=$G27),"."," ") | EE27: =IF(AND(EE$6>=$F27,EE$6<=$G27),"."," ") | EF27: =IF(AND(EF$6>=$F27,EF$6<=$G27),"."," ") | EI27: =IF(AND(EI$6>=$F27,EI$6<=$G27),"."," ") | EJ27: =IF(AND(EJ$6>=$F27,EJ$6<=$G27),"."," ") | EK27: =IF(AND(EK$6>=$F27,EK$6<=$G27),"."," ") | EL27: =IF(AND(EL$6>=$F27,EL$6<=$G27),"."," ") | EM27: =IF(AND(EM$6>=$F27,EM$6<=$G27),"."," ") | EP27: =IF(AND(EP$6>=$F27,EP$6<=$G27),"."," ") | EQ27: =IF(AND(EQ$6>=$F27,EQ$6<=$G27),"."," ") | ER27: =IF(AND(ER$6>=$F27,ER$6<=$G27),"."," ") | ES27: =IF(AND(ES$6>=$F27,ES$6<=$G27),"."," ") | ET27: =IF(AND(ET$6>=$F27,ET$6<=$G27),"."," ") | EW27: =IF(AND(EW$6>=$F27,EW$6<=$G27),"."," ") | EX27: =IF(AND(EX$6>=$F27,EX$6<=$G27),"."," ") | EY27: =IF(AND(EY$6>=$F27,EY$6<=$G27),"."," ") | EZ27: =IF(AND(EZ$6>=$F27,EZ$6<=$G27),"."," ") | FA27: =IF(AND(FA$6>=$F27,FA$6<=$G27),"."," ") | FD27: =IF(AND(FD$6>=$F27,FD$6<=$G27),"."," ") | FE27: =IF(AND(FE$6>=$F27,FE$6<=$G27),"."," ") | FF27: =IF(AND(FF$6>=$F27,FF$6<=$G27),"."," ") | FG27: =IF(AND(FG$6>=$F27,FG$6<=$G27),"."," ") | FH27: =IF(AND(FH$6>=$F27,FH$6<=$G27),"."," ") | FK27: =IF(AND(FK$6>=$F27,FK$6<=$G27),"."," ") | FL27: =IF(AND(FL$6>=$F27,FL$6<=$G27),"."," ") | FM27: =IF(AND(FM$6>=$F27,FM$6<=$G27),"."," ") | FN27: =IF(AND(FN$6>=$F27,FN$6<=$G27),"."," ") | FO27: =IF(AND(FO$6>=$F27,FO$6<=$G27),"."," ") | FR27: =IF(AND(FR$6>=$F27,FR$6<=$G27),"."," ") | FS27: =IF(AND(FS$6>=$F27,FS$6<=$G27),"."," ") | FT27: =IF(AND(FT$6>=$F27,FT$6<=$G27),"."," ") | FU27: =IF(AND(FU$6>=$F27,FU$6<=$G27),"."," ") | FV27: =IF(AND(FV$6>=$F27,FV$6<=$G27),"."," ") | FY27: =IF(AND(FY$6>=$F27,FY$6<=$G27),"."," ") | FZ27: =IF(AND(FZ$6>=$F27,FZ$6<=$G27),"."," ") | GA27: =IF(AND(GA$6>=$F27,GA$6<=$G27),"."," ") | GB27: =IF(AND(GB$6>=$F27,GB$6<=$G27),"."," ") | GC27: =IF(AND(GC$6>=$F27,GC$6<=$G27),"."," ") | GF27: =IF(AND(GF$6>=$F27,GF$6<=$G27),"."," ") | GG27: =IF(AND(GG$6>=$F27,GG$6<=$G27),"."," ") | GH27: =IF(AND(GH$6>=$F27,GH$6<=$G27),"."," ") | GI27: =IF(AND(GI$6>=$F27,GI$6<=$G27),"."," ") | GJ27: =IF(AND(GJ$6>=$F27,GJ$6<=$G27),"."," ") | GM27: =IF(AND(GM$6>=$F27,GM$6<=$G27),"."," ") | GN27: =IF(AND(GN$6>=$F27,GN$6<=$G27),"."," ") | GO27: =IF(AND(GO$6>=$F27,GO$6<=$G27),"."," ") | GP27: =IF(AND(GP$6>=$F27,GP$6<=$G27),"."," ") | GQ27: =IF(AND(GQ$6>=$F27,GQ$6<=$G27),"."," ") | GT27: =IF(AND(GT$6>=$F27,GT$6<=$G27),"."," ") | GU27: =IF(AND(GU$6>=$F27,GU$6<=$G27),"."," ") | GV27: =IF(AND(GV$6>=$F27,GV$6<=$G27),"."," ") | GW27: =IF(AND(GW$6>=$F27,GW$6<=$G27),"."," ") | GX27: =IF(AND(GX$6>=$F27,GX$6<=$G27),"."," ") | HA27: =IF(AND(HA$6>=$F27,HA$6<=$G27),"."," ") | HB27: =IF(AND(HB$6>=$F27,HB$6<=$G27),"."," ") | HC27: =IF(AND(HC$6>=$F27,HC$6<=$G27),"."," ") | HD27: =IF(AND(HD$6>=$F27,HD$6<=$G27),"."," ") | HE27: =IF(AND(HE$6>=$F27,HE$6<=$G27),"."," ") | HH27: =IF(AND(HH$6>=$F27,HH$6<=$G27),"."," ") | HI27: =IF(AND(HI$6>=$F27,HI$6<=$G27),"."," ") | HJ27: =IF(AND(HJ$6>=$F27,HJ$6<=$G27),"."," ") | HK27: =IF(AND(HK$6>=$F27,HK$6<=$G27),"."," ") | HL27: =IF(AND(HL$6>=$F27,HL$6<=$G27),"."," ") | HO27: =IF(AND(HO$6>=$F27,HO$6<=$G27),"."," ") | HP27: =IF(AND(HP$6>=$F27,HP$6<=$G27),"."," ") | HQ27: =IF(AND(HQ$6>=$F27,HQ$6<=$G27),"."," ") | HR27: =IF(AND(HR$6>=$F27,HR$6<=$G27),"."," ") | HS27: =IF(AND(HS$6>=$F27,HS$6<=$G27),"."," ") | HV27: =IF(AND(HV$6>=$F27,HV$6<=$G27),"."," ") | HW27: =IF(AND(HW$6>=$F27,HW$6<=$G27),"."," ") | HX27: =IF(AND(HX$6>=$F27,HX$6<=$G27),"."," ") | HY27: =IF(AND(HY$6>=$F27,HY$6<=$G27),"."," ") | HZ27: =IF(AND(HZ$6>=$F27,HZ$6<=$G27),"."," ") | IC27: =IF(AND(IC$6>=$F27,IC$6<=$G27),"."," ") | ID27: =IF(AND(ID$6>=$F27,ID$6<=$G27),"."," ") | IE27: =IF(AND(IE$6>=$F27,IE$6<=$G27),"."," ") | IF27: =IF(AND(IF$6>=$F27,IF$6<=$G27),"."," ") | IG27: =IF(AND(IG$6>=$F27,IG$6<=$G27),"."," ") | IJ27: =IF(AND(IJ$6>=$F27,IJ$6<=$G27),"."," ") | IK27: =IF(AND(IK$6>=$F27,IK$6<=$G27),"."," ") | IL27: =IF(AND(IL$6>=$F27,IL$6<=$G27),"."," ") | IM27: =IF(AND(IM$6>=$F27,IM$6<=$G27),"."," ") | IN27: =IF(AND(IN$6>=$F27,IN$6<=$G27),"."," ") | IQ27: =IF(AND(IQ$6>=$F27,IQ$6<=$G27),"."," ") | IR27: =IF(AND(IR$6>=$F27,IR$6<=$G27),"."," ") | IS27: =IF(AND(IS$6>=$F27,IS$6<=$G27),"."," ") | IT27: =IF(AND(IT$6>=$F27,IT$6<=$G27),"."," ") | IU27: =IF(AND(IU$6>=$F27,IU$6<=$G27),"."," ") | IX27: =IF(AND(IX$6>=$F27,IX$6<=$G27),"."," ") | IY27: =IF(AND(IY$6>=$F27,IY$6<=$G27),"."," ") | IZ27: =IF(AND(IZ$6>=$F27,IZ$6<=$G27),"."," ") | JA27: =IF(AND(JA$6>=$F27,JA$6<=$G27),"."," ") | JB27: =IF(AND(JB$6>=$F27,JB$6<=$G27),"."," ") | JE27: =IF(AND(JE$6>=$F27,JE$6<=$G27),"."," ") | JF27: =IF(AND(JF$6>=$F27,JF$6<=$G27),"."," ") | JG27: =IF(AND(JG$6>=$F27,JG$6<=$G27),"."," ") | JH27: =IF(AND(JH$6>=$F27,JH$6<=$G27),"."," ") | JI27: =IF(AND(JI$6>=$F27,JI$6<=$G27),"."," ")
B28: 20 | C28: Build Component 6 | D28: Bob | E28: 11 | F28: =VLOOKUP(E28,$B$6:$G$150,6,FALSE) + 1 -> 42531 | G28: =WORKDAY(F28,H28-1,Config!D27:D46) -> 42534 | H28: 2 | I28: 0 | J28: =IF(((NETWORKDAYS(F28,TODAY(),Data!C23:C42)*100)/H28)/100 > 0,((NETWORKDAYS(F28,TODAY(),Data!C23:C42)*100)/H28)/100,0) -> 823 | K28: =IF(J28>1, "100%",$J28) -> 100% | L28: =K28-I28 -> 1 | M28: =IF(AND(M$6>=$F28,M$6<=$G28),"."," ") | N28: =IF(AND(N$6>=$F28,N$6<=$G28),"."," ") | O28: =IF(AND(O$6>=$F28,O$6<=$G28),"."," ") | P28: =IF(AND(P$6>=$F28,P$6<=$G28),"."," ") | Q28: =IF(AND(Q$6>=$F28,Q$6<=$G28),"."," ") | T28: =IF(AND(T$6>=$F28,T$6<=$G28),"."," ") | U28: =IF(AND(U$6>=$F28,U$6<=$G28),"."," ") | V28: =IF(AND(V$6>=$F28,V$6<=$G28),"."," ") | W28: =IF(AND(W$6>=$F28,W$6<=$G28),"."," ") | X28: =IF(AND(X$6>=$F28,X$6<=$G28),"."," ") | AA28: =IF(AND(AA$6>=$F28,AA$6<=$G28),"."," ") | AB28: =IF(AND(AB$6>=$F28,AB$6<=$G28),"."," ") | AC28: =IF(AND(AC$6>=$F28,AC$6<=$G28),"."," ") | AD28: =IF(AND(AD$6>=$F28,AD$6<=$G28),"."," ") | AE28: =IF(AND(AE$6>=$F28,AE$6<=$G28),"."," ") | AH28: =IF(AND(AH$6>=$F28,AH$6<=$G28),"."," ") | AI28: =IF(AND(AI$6>=$F28,AI$6<=$G28),"."," ") | AJ28: =IF(AND(AJ$6>=$F28,AJ$6<=$G28),"."," ") | AK28: =IF(AND(AK$6>=$F28,AK$6<=$G28),"."," ") | AL28: =IF(AND(AL$6>=$F28,AL$6<=$G28),"."," ") | AO28: =IF(AND(AO$6>=$F28,AO$6<=$G28),"."," ") | AP28: =IF(AND(AP$6>=$F28,AP$6<=$G28),"."," ") | AQ28: =IF(AND(AQ$6>=$F28,AQ$6<=$G28),"."," ") | AR28: =IF(AND(AR$6>=$F28,AR$6<=$G28),"."," ") | AS28: =IF(AND(AS$6>=$F28,AS$6<=$G28),"."," ") | AV28: =IF(AND(AV$6>=$F28,AV$6<=$G28),"."," ") | AW28: =IF(AND(AW$6>=$F28,AW$6<=$G28),"."," ") -> . | AX28: =IF(AND(AX$6>=$F28,AX$6<=$G28),"."," ") -> . | AY28: =IF(AND(AY$6>=$F28,AY$6<=$G28),"."," ") -> . | AZ28: =IF(AND(AZ$6>=$F28,AZ$6<=$G28),"."," ") -> . | BC28: =IF(AND(BC$6>=$F28,BC$6<=$G28),"."," ") | BD28: =IF(AND(BD$6>=$F28,BD$6<=$G28),"."," ") | BE28: =IF(AND(BE$6>=$F28,BE$6<=$G28),"."," ") | BF28: =IF(AND(BF$6>=$F28,BF$6<=$G28),"."," ") | BG28: =IF(AND(BG$6>=$F28,BG$6<=$G28),"."," ") | BJ28: =IF(AND(BJ$6>=$F28,BJ$6<=$G28),"."," ") | BK28: =IF(AND(BK$6>=$F28,BK$6<=$G28),"."," ") | BL28: =IF(AND(BL$6>=$F28,BL$6<=$G28),"."," ") | BM28: =IF(AND(BM$6>=$F28,BM$6<=$G28),"."," ") | BN28: =IF(AND(BN$6>=$F28,BN$6<=$G28),"."," ") | BQ28: =IF(AND(BQ$6>=$F28,BQ$6<=$G28),"."," ") | BR28: =IF(AND(BR$6>=$F28,BR$6<=$G28),"."," ") | BS28: =IF(AND(BS$6>=$F28,BS$6<=$G28),"."," ") | BT28: =IF(AND(BT$6>=$F28,BT$6<=$G28),"."," ") | BU28: =IF(AND(BU$6>=$F28,BU$6<=$G28),"."," ") | BX28: =IF(AND(BX$6>=$F28,BX$6<=$G28),"."," ") | BY28: =IF(AND(BY$6>=$F28,BY$6<=$G28),"."," ") | BZ28: =IF(AND(BZ$6>=$F28,BZ$6<=$G28),"."," ") | CA28: =IF(AND(CA$6>=$F28,CA$6<=$G28),"."," ") | CB28: =IF(AND(CB$6>=$F28,CB$6<=$G28),"."," ") | CE28: =IF(AND(CE$6>=$F28,CE$6<=$G28),"."," ") | CF28: =IF(AND(CF$6>=$F28,CF$6<=$G28),"."," ") | CG28: =IF(AND(CG$6>=$F28,CG$6<=$G28),"."," ") | CH28: =IF(AND(CH$6>=$F28,CH$6<=$G28),"."," ") | CI28: =IF(AND(CI$6>=$F28,CI$6<=$G28),"."," ") | CL28: =IF(AND(CL$6>=$F28,CL$6<=$G28),"."," ") | CM28: =IF(AND(CM$6>=$F28,CM$6<=$G28),"."," ") | CN28: =IF(AND(CN$6>=$F28,CN$6<=$G28),"."," ") | CO28: =IF(AND(CO$6>=$F28,CO$6<=$G28),"."," ") | CP28: =IF(AND(CP$6>=$F28,CP$6<=$G28),"."," ") | CS28: =IF(AND(CS$6>=$F28,CS$6<=$G28),"."," ") | CT28: =IF(AND(CT$6>=$F28,CT$6<=$G28),"."," ") | CU28: =IF(AND(CU$6>=$F28,CU$6<=$G28),"."," ") | CV28: =IF(AND(CV$6>=$F28,CV$6<=$G28),"."," ") | CW28: =IF(AND(CW$6>=$F28,CW$6<=$G28),"."," ") | CZ28: =IF(AND(CZ$6>=$F28,CZ$6<=$G28),"."," ") | DA28: =IF(AND(DA$6>=$F28,DA$6<=$G28),"."," ") | DB28: =IF(AND(DB$6>=$F28,DB$6<=$G28),"."," ") | DC28: =IF(AND(DC$6>=$F28,DC$6<=$G28),"."," ") | DD28: =IF(AND(DD$6>=$F28,DD$6<=$G28),"."," ") | DG28: =IF(AND(DG$6>=$F28,DG$6<=$G28),"."," ") | DH28: =IF(AND(DH$6>=$F28,DH$6<=$G28),"."," ") | DI28: =IF(AND(DI$6>=$F28,DI$6<=$G28),"."," ") | DJ28: =IF(AND(DJ$6>=$F28,DJ$6<=$G28),"."," ") | DK28: =IF(AND(DK$6>=$F28,DK$6<=$G28),"."," ") | DN28: =IF(AND(DN$6>=$F28,DN$6<=$G28),"."," ") | DO28: =IF(AND(DO$6>=$F28,DO$6<=$G28),"."," ") | DP28: =IF(AND(DP$6>=$F28,DP$6<=$G28),"."," ") | DQ28: =IF(AND(DQ$6>=$F28,DQ$6<=$G28),"."," ") | DR28: =IF(AND(DR$6>=$F28,DR$6<=$G28),"."," ") | DU28: =IF(AND(DU$6>=$F28,DU$6<=$G28),"."," ") | DV28: =IF(AND(DV$6>=$F28,DV$6<=$G28),"."," ") | DW28: =IF(AND(DW$6>=$F28,DW$6<=$G28),"."," ") | DX28: =IF(AND(DX$6>=$F28,DX$6<=$G28),"."," ") | DY28: =IF(AND(DY$6>=$F28,DY$6<=$G28),"."," ") | EB28: =IF(AND(EB$6>=$F28,EB$6<=$G28),"."," ") | EC28: =IF(AND(EC$6>=$F28,EC$6<=$G28),"."," ") | ED28: =IF(AND(ED$6>=$F28,ED$6<=$G28),"."," ") | EE28: =IF(AND(EE$6>=$F28,EE$6<=$G28),"."," ") | EF28: =IF(AND(EF$6>=$F28,EF$6<=$G28),"."," ") | EI28: =IF(AND(EI$6>=$F28,EI$6<=$G28),"."," ") | EJ28: =IF(AND(EJ$6>=$F28,EJ$6<=$G28),"."," ") | EK28: =IF(AND(EK$6>=$F28,EK$6<=$G28),"."," ") | EL28: =IF(AND(EL$6>=$F28,EL$6<=$G28),"."," ") | EM28: =IF(AND(EM$6>=$F28,EM$6<=$G28),"."," ") | EP28: =IF(AND(EP$6>=$F28,EP$6<=$G28),"."," ") | EQ28: =IF(AND(EQ$6>=$F28,EQ$6<=$G28),"."," ") | ER28: =IF(AND(ER$6>=$F28,ER$6<=$G28),"."," ") | ES28: =IF(AND(ES$6>=$F28,ES$6<=$G28),"."," ") | ET28: =IF(AND(ET$6>=$F28,ET$6<=$G28),"."," ") | EW28: =IF(AND(EW$6>=$F28,EW$6<=$G28),"."," ") | EX28: =IF(AND(EX$6>=$F28,EX$6<=$G28),"."," ") | EY28: =IF(AND(EY$6>=$F28,EY$6<=$G28),"."," ") | EZ28: =IF(AND(EZ$6>=$F28,EZ$6<=$G28),"."," ") | FA28: =IF(AND(FA$6>=$F28,FA$6<=$G28),"."," ") | FD28: =IF(AND(FD$6>=$F28,FD$6<=$G28),"."," ") | FE28: =IF(AND(FE$6>=$F28,FE$6<=$G28),"."," ") | FF28: =IF(AND(FF$6>=$F28,FF$6<=$G28),"."," ") | FG28: =IF(AND(FG$6>=$F28,FG$6<=$G28),"."," ") | FH28: =IF(AND(FH$6>=$F28,FH$6<=$G28),"."," ") | FK28: =IF(AND(FK$6>=$F28,FK$6<=$G28),"."," ") | FL28: =IF(AND(FL$6>=$F28,FL$6<=$G28),"."," ") | FM28: =IF(AND(FM$6>=$F28,FM$6<=$G28),"."," ") | FN28: =IF(AND(FN$6>=$F28,FN$6<=$G28),"."," ") | FO28: =IF(AND(FO$6>=$F28,FO$6<=$G28),"."," ") | FR28: =IF(AND(FR$6>=$F28,FR$6<=$G28),"."," ") | FS28: =IF(AND(FS$6>=$F28,FS$6<=$G28),"."," ") | FT28: =IF(AND(FT$6>=$F28,FT$6<=$G28),"."," ") | FU28: =IF(AND(FU$6>=$F28,FU$6<=$G28),"."," ") | FV28: =IF(AND(FV$6>=$F28,FV$6<=$G28),"."," ") | FY28: =IF(AND(FY$6>=$F28,FY$6<=$G28),"."," ") | FZ28: =IF(AND(FZ$6>=$F28,FZ$6<=$G28),"."," ") | GA28: =IF(AND(GA$6>=$F28,GA$6<=$G28),"."," ") | GB28: =IF(AND(GB$6>=$F28,GB$6<=$G28),"."," ") | GC28: =IF(AND(GC$6>=$F28,GC$6<=$G28),"."," ") | GF28: =IF(AND(GF$6>=$F28,GF$6<=$G28),"."," ") | GG28: =IF(AND(GG$6>=$F28,GG$6<=$G28),"."," ") | GH28: =IF(AND(GH$6>=$F28,GH$6<=$G28),"."," ") | GI28: =IF(AND(GI$6>=$F28,GI$6<=$G28),"."," ") | GJ28: =IF(AND(GJ$6>=$F28,GJ$6<=$G28),"."," ") | GM28: =IF(AND(GM$6>=$F28,GM$6<=$G28),"."," ") | GN28: =IF(AND(GN$6>=$F28,GN$6<=$G28),"."," ") | GO28: =IF(AND(GO$6>=$F28,GO$6<=$G28),"."," ") | GP28: =IF(AND(GP$6>=$F28,GP$6<=$G28),"."," ") | GQ28: =IF(AND(GQ$6>=$F28,GQ$6<=$G28),"."," ") | GT28: =IF(AND(GT$6>=$F28,GT$6<=$G28),"."," ") | GU28: =IF(AND(GU$6>=$F28,GU$6<=$G28),"."," ") | GV28: =IF(AND(GV$6>=$F28,GV$6<=$G28),"."," ") | GW28: =IF(AND(GW$6>=$F28,GW$6<=$G28),"."," ") | GX28: =IF(AND(GX$6>=$F28,GX$6<=$G28),"."," ") | HA28: =IF(AND(HA$6>=$F28,HA$6<=$G28),"."," ") | HB28: =IF(AND(HB$6>=$F28,HB$6<=$G28),"."," ") | HC28: =IF(AND(HC$6>=$F28,HC$6<=$G28),"."," ") | HD28: =IF(AND(HD$6>=$F28,HD$6<=$G28),"."," ") | HE28: =IF(AND(HE$6>=$F28,HE$6<=$G28),"."," ") | HH28: =IF(AND(HH$6>=$F28,HH$6<=$G28),"."," ") | HI28: =IF(AND(HI$6>=$F28,HI$6<=$G28),"."," ") | HJ28: =IF(AND(HJ$6>=$F28,HJ$6<=$G28),"."," ") | HK28: =IF(AND(HK$6>=$F28,HK$6<=$G28),"."," ") | HL28: =IF(AND(HL$6>=$F28,HL$6<=$G28),"."," ") | HO28: =IF(AND(HO$6>=$F28,HO$6<=$G28),"."," ") | HP28: =IF(AND(HP$6>=$F28,HP$6<=$G28),"."," ") | HQ28: =IF(AND(HQ$6>=$F28,HQ$6<=$G28),"."," ") | HR28: =IF(AND(HR$6>=$F28,HR$6<=$G28),"."," ") | HS28: =IF(AND(HS$6>=$F28,HS$6<=$G28),"."," ") | HV28: =IF(AND(HV$6>=$F28,HV$6<=$G28),"."," ") | HW28: =IF(AND(HW$6>=$F28,HW$6<=$G28),"."," ") | HX28: =IF(AND(HX$6>=$F28,HX$6<=$G28),"."," ") | HY28: =IF(AND(HY$6>=$F28,HY$6<=$G28),"."," ") | HZ28: =IF(AND(HZ$6>=$F28,HZ$6<=$G28),"."," ") | IC28: =IF(AND(IC$6>=$F28,IC$6<=$G28),"."," ") | ID28: =IF(AND(ID$6>=$F28,ID$6<=$G28),"."," ") | IE28: =IF(AND(IE$6>=$F28,IE$6<=$G28),"."," ") | IF28: =IF(AND(IF$6>=$F28,IF$6<=$G28),"."," ") | IG28: =IF(AND(IG$6>=$F28,IG$6<=$G28),"."," ") | IJ28: =IF(AND(IJ$6>=$F28,IJ$6<=$G28),"."," ") | IK28: =IF(AND(IK$6>=$F28,IK$6<=$G28),"."," ") | IL28: =IF(AND(IL$6>=$F28,IL$6<=$G28),"."," ") | IM28: =IF(AND(IM$6>=$F28,IM$6<=$G28),"."," ") | IN28: =IF(AND(IN$6>=$F28,IN$6<=$G28),"."," ") | IQ28: =IF(AND(IQ$6>=$F28,IQ$6<=$G28),"."," ") | IR28: =IF(AND(IR$6>=$F28,IR$6<=$G28),"."," ") | IS28: =IF(AND(IS$6>=$F28,IS$6<=$G28),"."," ") | IT28: =IF(AND(IT$6>=$F28,IT$6<=$G28),"."," ") | IU28: =IF(AND(IU$6>=$F28,IU$6<=$G28),"."," ") | IX28: =IF(AND(IX$6>=$F28,IX$6<=$G28),"."," ") | IY28: =IF(AND(IY$6>=$F28,IY$6<=$G28),"."," ") | IZ28: =IF(AND(IZ$6>=$F28,IZ$6<=$G28),"."," ") | JA28: =IF(AND(JA$6>=$F28,JA$6<=$G28),"."," ") | JB28: =IF(AND(JB$6>=$F28,JB$6<=$G28),"."," ") | JE28: =IF(AND(JE$6>=$F28,JE$6<=$G28),"."," ") | JF28: =IF(AND(JF$6>=$F28,JF$6<=$G28),"."," ") | JG28: =IF(AND(JG$6>=$F28,JG$6<=$G28),"."," ") | JH28: =IF(AND(JH$6>=$F28,JH$6<=$G28),"."," ") | JI28: =IF(AND(JI$6>=$F28,JI$6<=$G28),"."," ")
B29: 21 | C29: Build Component 7 | D29: Bob | E29: 19 | F29: =VLOOKUP(E29,$B$6:$G$150,6,FALSE) + 1 -> 42546 | G29: =WORKDAY(F29,H29-1,Config!D28:D47) -> 42550 | H29: 4 | I29: 0 | J29: =IF(((NETWORKDAYS(F29,TODAY(),Data!C24:C43)*100)/H29)/100 > 0,((NETWORKDAYS(F29,TODAY(),Data!C24:C43)*100)/H29)/100,0) -> 408.75 | K29: =IF(J29>1, "100%",$J29) -> 100% | L29: =K29-I29 -> 1 | M29: =IF(AND(M$6>=$F29,M$6<=$G29),"."," ") | N29: =IF(AND(N$6>=$F29,N$6<=$G29),"."," ") | O29: =IF(AND(O$6>=$F29,O$6<=$G29),"."," ") | P29: =IF(AND(P$6>=$F29,P$6<=$G29),"."," ") | Q29: =IF(AND(Q$6>=$F29,Q$6<=$G29),"."," ") | T29: =IF(AND(T$6>=$F29,T$6<=$G29),"."," ") | U29: =IF(AND(U$6>=$F29,U$6<=$G29),"."," ") | V29: =IF(AND(V$6>=$F29,V$6<=$G29),"."," ") | W29: =IF(AND(W$6>=$F29,W$6<=$G29),"."," ") | X29: =IF(AND(X$6>=$F29,X$6<=$G29),"."," ") | AA29: =IF(AND(AA$6>=$F29,AA$6<=$G29),"."," ") | AB29: =IF(AND(AB$6>=$F29,AB$6<=$G29),"."," ") | AC29: =IF(AND(AC$6>=$F29,AC$6<=$G29),"."," ") | AD29: =IF(AND(AD$6>=$F29,AD$6<=$G29),"."," ") | AE29: =IF(AND(AE$6>=$F29,AE$6<=$G29),"."," ") | AH29: =IF(AND(AH$6>=$F29,AH$6<=$G29),"."," ") | AI29: =IF(AND(AI$6>=$F29,AI$6<=$G29),"."," ") | AJ29: =IF(AND(AJ$6>=$F29,AJ$6<=$G29),"."," ") | AK29: =IF(AND(AK$6>=$F29,AK$6<=$G29),"."," ") | AL29: =IF(AND(AL$6>=$F29,AL$6<=$G29),"."," ") | AO29: =IF(AND(AO$6>=$F29,AO$6<=$G29),"."," ") | AP29: =IF(AND(AP$6>=$F29,AP$6<=$G29),"."," ") | AQ29: =IF(AND(AQ$6>=$F29,AQ$6<=$G29),"."," ") | AR29: =IF(AND(AR$6>=$F29,AR$6<=$G29),"."," ") | AS29: =IF(AND(AS$6>=$F29,AS$6<=$G29),"."," ") | AV29: =IF(AND(AV$6>=$F29,AV$6<=$G29),"."," ") | AW29: =IF(AND(AW$6>=$F29,AW$6<=$G29),"."," ") | AX29: =IF(AND(AX$6>=$F29,AX$6<=$G29),"."," ") | AY29: =IF(AND(AY$6>=$F29,AY$6<=$G29),"."," ") | AZ29: =IF(AND(AZ$6>=$F29,AZ$6<=$G29),"."," ") | BC29: =IF(AND(BC$6>=$F29,BC$6<=$G29),"."," ") | BD29: =IF(AND(BD$6>=$F29,BD$6<=$G29),"."," ") | BE29: =IF(AND(BE$6>=$F29,BE$6<=$G29),"."," ") | BF29: =IF(AND(BF$6>=$F29,BF$6<=$G29),"."," ") | BG29: =IF(AND(BG$6>=$F29,BG$6<=$G29),"."," ") | BJ29: =IF(AND(BJ$6>=$F29,BJ$6<=$G29),"."," ") | BK29: =IF(AND(BK$6>=$F29,BK$6<=$G29),"."," ") | BL29: =IF(AND(BL$6>=$F29,BL$6<=$G29),"."," ") -> . | BM29: =IF(AND(BM$6>=$F29,BM$6<=$G29),"."," ") -> . | BN29: =IF(AND(BN$6>=$F29,BN$6<=$G29),"."," ") -> . | BQ29: =IF(AND(BQ$6>=$F29,BQ$6<=$G29),"."," ") | BR29: =IF(AND(BR$6>=$F29,BR$6<=$G29),"."," ") | BS29: =IF(AND(BS$6>=$F29,BS$6<=$G29),"."," ") | BT29: =IF(AND(BT$6>=$F29,BT$6<=$G29),"."," ") | BU29: =IF(AND(BU$6>=$F29,BU$6<=$G29),"."," ") | BX29: =IF(AND(BX$6>=$F29,BX$6<=$G29),"."," ") | BY29: =IF(AND(BY$6>=$F29,BY$6<=$G29),"."," ") | BZ29: =IF(AND(BZ$6>=$F29,BZ$6<=$G29),"."," ") | CA29: =IF(AND(CA$6>=$F29,CA$6<=$G29),"."," ") | CB29: =IF(AND(CB$6>=$F29,CB$6<=$G29),"."," ") | CE29: =IF(AND(CE$6>=$F29,CE$6<=$G29),"."," ") | CF29: =IF(AND(CF$6>=$F29,CF$6<=$G29),"."," ") | CG29: =IF(AND(CG$6>=$F29,CG$6<=$G29),"."," ") | CH29: =IF(AND(CH$6>=$F29,CH$6<=$G29),"."," ") | CI29: =IF(AND(CI$6>=$F29,CI$6<=$G29),"."," ") | CL29: =IF(AND(CL$6>=$F29,CL$6<=$G29),"."," ") | CM29: =IF(AND(CM$6>=$F29,CM$6<=$G29),"."," ") | CN29: =IF(AND(CN$6>=$F29,CN$6<=$G29),"."," ") | CO29: =IF(AND(CO$6>=$F29,CO$6<=$G29),"."," ") | CP29: =IF(AND(CP$6>=$F29,CP$6<=$G29),"."," ") | CS29: =IF(AND(CS$6>=$F29,CS$6<=$G29),"."," ") | CT29: =IF(AND(CT$6>=$F29,CT$6<=$G29),"."," ") | CU29: =IF(AND(CU$6>=$F29,CU$6<=$G29),"."," ") | CV29: =IF(AND(CV$6>=$F29,CV$6<=$G29),"."," ") | CW29: =IF(AND(CW$6>=$F29,CW$6<=$G29),"."," ") | CZ29: =IF(AND(CZ$6>=$F29,CZ$6<=$G29),"."," ") | DA29: =IF(AND(DA$6>=$F29,DA$6<=$G29),"."," ") | DB29: =IF(AND(DB$6>=$F29,DB$6<=$G29),"."," ") | DC29: =IF(AND(DC$6>=$F29,DC$6<=$G29),"."," ") | DD29: =IF(AND(DD$6>=$F29,DD$6<=$G29),"."," ") | DG29: =IF(AND(DG$6>=$F29,DG$6<=$G29),"."," ") | DH29: =IF(AND(DH$6>=$F29,DH$6<=$G29),"."," ") | DI29: =IF(AND(DI$6>=$F29,DI$6<=$G29),"."," ") | DJ29: =IF(AND(DJ$6>=$F29,DJ$6<=$G29),"."," ") | DK29: =IF(AND(DK$6>=$F29,DK$6<=$G29),"."," ") | DN29: =IF(AND(DN$6>=$F29,DN$6<=$G29),"."," ") | DO29: =IF(AND(DO$6>=$F29,DO$6<=$G29),"."," ") | DP29: =IF(AND(DP$6>=$F29,DP$6<=$G29),"."," ") | DQ29: =IF(AND(DQ$6>=$F29,DQ$6<=$G29),"."," ") | DR29: =IF(AND(DR$6>=$F29,DR$6<=$G29),"."," ") | DU29: =IF(AND(DU$6>=$F29,DU$6<=$G29),"."," ") | DV29: =IF(AND(DV$6>=$F29,DV$6<=$G29),"."," ") | DW29: =IF(AND(DW$6>=$F29,DW$6<=$G29),"."," ") | DX29: =IF(AND(DX$6>=$F29,DX$6<=$G29),"."," ") | DY29: =IF(AND(DY$6>=$F29,DY$6<=$G29),"."," ") | EB29: =IF(AND(EB$6>=$F29,EB$6<=$G29),"."," ") | EC29: =IF(AND(EC$6>=$F29,EC$6<=$G29),"."," ") | ED29: =IF(AND(ED$6>=$F29,ED$6<=$G29),"."," ") | EE29: =IF(AND(EE$6>=$F29,EE$6<=$G29),"."," ") | EF29: =IF(AND(EF$6>=$F29,EF$6<=$G29),"."," ") | EI29: =IF(AND(EI$6>=$F29,EI$6<=$G29),"."," ") | EJ29: =IF(AND(EJ$6>=$F29,EJ$6<=$G29),"."," ") | EK29: =IF(AND(EK$6>=$F29,EK$6<=$G29),"."," ") | EL29: =IF(AND(EL$6>=$F29,EL$6<=$G29),"."," ") | EM29: =IF(AND(EM$6>=$F29,EM$6<=$G29),"."," ") | EP29: =IF(AND(EP$6>=$F29,EP$6<=$G29),"."," ") | EQ29: =IF(AND(EQ$6>=$F29,EQ$6<=$G29),"."," ") | ER29: =IF(AND(ER$6>=$F29,ER$6<=$G29),"."," ") | ES29: =IF(AND(ES$6>=$F29,ES$6<=$G29),"."," ") | ET29: =IF(AND(ET$6>=$F29,ET$6<=$G29),"."," ") | EW29: =IF(AND(EW$6>=$F29,EW$6<=$G29),"."," ") | EX29: =IF(AND(EX$6>=$F29,EX$6<=$G29),"."," ") | EY29: =IF(AND(EY$6>=$F29,EY$6<=$G29),"."," ") | EZ29: =IF(AND(EZ$6>=$F29,EZ$6<=$G29),"."," ") | FA29: =IF(AND(FA$6>=$F29,FA$6<=$G29),"."," ") | FD29: =IF(AND(FD$6>=$F29,FD$6<=$G29),"."," ") | FE29: =IF(AND(FE$6>=$F29,FE$6<=$G29),"."," ") | FF29: =IF(AND(FF$6>=$F29,FF$6<=$G29),"."," ") | FG29: =IF(AND(FG$6>=$F29,FG$6<=$G29),"."," ") | FH29: =IF(AND(FH$6>=$F29,FH$6<=$G29),"."," ") | FK29: =IF(AND(FK$6>=$F29,FK$6<=$G29),"."," ") | FL29: =IF(AND(FL$6>=$F29,FL$6<=$G29),"."," ") | FM29: =IF(AND(FM$6>=$F29,FM$6<=$G29),"."," ") | FN29: =IF(AND(FN$6>=$F29,FN$6<=$G29),"."," ") | FO29: =IF(AND(FO$6>=$F29,FO$6<=$G29),"."," ") | FR29: =IF(AND(FR$6>=$F29,FR$6<=$G29),"."," ") | FS29: =IF(AND(FS$6>=$F29,FS$6<=$G29),"."," ") | FT29: =IF(AND(FT$6>=$F29,FT$6<=$G29),"."," ") | FU29: =IF(AND(FU$6>=$F29,FU$6<=$G29),"."," ") | FV29: =IF(AND(FV$6>=$F29,FV$6<=$G29),"."," ") | FY29: =IF(AND(FY$6>=$F29,FY$6<=$G29),"."," ") | FZ29: =IF(AND(FZ$6>=$F29,FZ$6<=$G29),"."," ") | GA29: =IF(AND(GA$6>=$F29,GA$6<=$G29),"."," ") | GB29: =IF(AND(GB$6>=$F29,GB$6<=$G29),"."," ") | GC29: =IF(AND(GC$6>=$F29,GC$6<=$G29),"."," ") | GF29: =IF(AND(GF$6>=$F29,GF$6<=$G29),"."," ") | GG29: =IF(AND(GG$6>=$F29,GG$6<=$G29),"."," ") | GH29: =IF(AND(GH$6>=$F29,GH$6<=$G29),"."," ") | GI29: =IF(AND(GI$6>=$F29,GI$6<=$G29),"."," ") | GJ29: =IF(AND(GJ$6>=$F29,GJ$6<=$G29),"."," ") | GM29: =IF(AND(GM$6>=$F29,GM$6<=$G29),"."," ") | GN29: =IF(AND(GN$6>=$F29,GN$6<=$G29),"."," ") | GO29: =IF(AND(GO$6>=$F29,GO$6<=$G29),"."," ") | GP29: =IF(AND(GP$6>=$F29,GP$6<=$G29),"."," ") | GQ29: =IF(AND(GQ$6>=$F29,GQ$6<=$G29),"."," ") | GT29: =IF(AND(GT$6>=$F29,GT$6<=$G29),"."," ") | GU29: =IF(AND(GU$6>=$F29,GU$6<=$G29),"."," ") | GV29: =IF(AND(GV$6>=$F29,GV$6<=$G29),"."," ") | GW29: =IF(AND(GW$6>=$F29,GW$6<=$G29),"."," ") | GX29: =IF(AND(GX$6>=$F29,GX$6<=$G29),"."," ") | HA29: =IF(AND(HA$6>=$F29,HA$6<=$G29),"."," ") | HB29: =IF(AND(HB$6>=$F29,HB$6<=$G29),"."," ") | HC29: =IF(AND(HC$6>=$F29,HC$6<=$G29),"."," ") | HD29: =IF(AND(HD$6>=$F29,HD$6<=$G29),"."," ") | HE29: =IF(AND(HE$6>=$F29,HE$6<=$G29),"."," ") | HH29: =IF(AND(HH$6>=$F29,HH$6<=$G29),"."," ") | HI29: =IF(AND(HI$6>=$F29,HI$6<=$G29),"."," ") | HJ29: =IF(AND(HJ$6>=$F29,HJ$6<=$G29),"."," ") | HK29: =IF(AND(HK$6>=$F29,HK$6<=$G29),"."," ") | HL29: =IF(AND(HL$6>=$F29,HL$6<=$G29),"."," ") | HO29: =IF(AND(HO$6>=$F29,HO$6<=$G29),"."," ") | HP29: =IF(AND(HP$6>=$F29,HP$6<=$G29),"."," ") | HQ29: =IF(AND(HQ$6>=$F29,HQ$6<=$G29),"."," ") | HR29: =IF(AND(HR$6>=$F29,HR$6<=$G29),"."," ") | HS29: =IF(AND(HS$6>=$F29,HS$6<=$G29),"."," ") | HV29: =IF(AND(HV$6>=$F29,HV$6<=$G29),"."," ") | HW29: =IF(AND(HW$6>=$F29,HW$6<=$G29),"."," ") | HX29: =IF(AND(HX$6>=$F29,HX$6<=$G29),"."," ") | HY29: =IF(AND(HY$6>=$F29,HY$6<=$G29),"."," ") | HZ29: =IF(AND(HZ$6>=$F29,HZ$6<=$G29),"."," ") | IC29: =IF(AND(IC$6>=$F29,IC$6<=$G29),"."," ") | ID29: =IF(AND(ID$6>=$F29,ID$6<=$G29),"."," ") | IE29: =IF(AND(IE$6>=$F29,IE$6<=$G29),"."," ") | IF29: =IF(AND(IF$6>=$F29,IF$6<=$G29),"."," ") | IG29: =IF(AND(IG$6>=$F29,IG$6<=$G29),"."," ") | IJ29: =IF(AND(IJ$6>=$F29,IJ$6<=$G29),"."," ") | IK29: =IF(AND(IK$6>=$F29,IK$6<=$G29),"."," ") | IL29: =IF(AND(IL$6>=$F29,IL$6<=$G29),"."," ") | IM29: =IF(AND(IM$6>=$F29,IM$6<=$G29),"."," ") | IN29: =IF(AND(IN$6>=$F29,IN$6<=$G29),"."," ") | IQ29: =IF(AND(IQ$6>=$F29,IQ$6<=$G29),"."," ") | IR29: =IF(AND(IR$6>=$F29,IR$6<=$G29),"."," ") | IS29: =IF(AND(IS$6>=$F29,IS$6<=$G29),"."," ") | IT29: =IF(AND(IT$6>=$F29,IT$6<=$G29),"."," ") | IU29: =IF(AND(IU$6>=$F29,IU$6<=$G29),"."," ") | IX29: =IF(AND(IX$6>=$F29,IX$6<=$G29),"."," ") | IY29: =IF(AND(IY$6>=$F29,IY$6<=$G29),"."," ") | IZ29: =IF(AND(IZ$6>=$F29,IZ$6<=$G29),"."," ") | JA29: =IF(AND(JA$6>=$F29,JA$6<=$G29),"."," ") | JB29: =IF(AND(JB$6>=$F29,JB$6<=$G29),"."," ") | JE29: =IF(AND(JE$6>=$F29,JE$6<=$G29),"."," ") | JF29: =IF(AND(JF$6>=$F29,JF$6<=$G29),"."," ") | JG29: =IF(AND(JG$6>=$F29,JG$6<=$G29),"."," ") | JH29: =IF(AND(JH$6>=$F29,JH$6<=$G29),"."," ") | JI29: =IF(AND(JI$6>=$F29,JI$6<=$G29),"."," ")
